Workbook

Sheet README
A1: Concurrences Gate 2 Expert Review Template
A3: Purpose | B3: This workbook is for reviewing generated answers and retrieved sources for Approved benchmark questions only.
A5: How experts should use this file
A6: 1. Open the tab for your question, for example Q01.
A7: 2. Review the generated answer and the sources retrieved by the system.
A8: 3. For each legal claim, mark whether the cited source supports it.
A9: 4. Add a short comment only where something must be fixed or clarified.
A10: 5. Mark the final expert verdict at the bottom of each question tab.
A11: 6. The team will use Review Status and Scoring Summary to track progress and calculate metrics.
A14: Key dates
A15: Answers and retrieval sets generated by | B15: 46251
A16: Expert claim-by-claim review completed by | B16: 2026-08-21
A18: Batch 1
A19: Q15
A20: Q16
A21: Q17
A22: Q25
A23: Q28 ⚠️
A24: Q29
A25: Q35
A26: Q41

Sheet Review Status
A1: Review Status
A3: Question ID | B3: Topic | C3: Scope | D3: Question | E3: Expert review status | F3: Reviewer | G3: Main issue / follow-up | H3: Open tab
A4: 1 | B4: Food delivery — market definition | C4: EU + UK + ES | D4: The relevant market in a food-delivery acquisition — how have the Commission and national authorities defined the relevant product and geographic markets, and on what rationales? | E4: ='Q01'!B40 | F4: ='Q01'!B37 | G4: ='Q01'!B39 | H4: =HYPERLINK("https://docs.google.com/spreadsheets/d/1SGTTCNk9crU1EZRgL9dlNhuv_RvcJLmSnfJtXz3RjEE/edit#gid=522724517&range=A1","Open")
A5: 2 | B5: Food delivery — multi-sided platforms | C5: EU + UK + ES | D5: Food delivery as a multi-sided platform — have authorities analysed these platforms as two- or multi-sided markets, and which sides actually entered the analysis? | E5: ='Q02'!B40 | F5: ='Q02'!B37 | G5: ='Q02'!B39 | H5: =HYPERLINK("https://docs.google.com/spreadsheets/d/1SGTTCNk9crU1EZRgL9dlNhuv_RvcJLmSnfJtXz3RjEE/edit#gid=297064813&range=A1","Open")
A6: 3 | B6: Food delivery — market boundary | C6: UK (ES colour) | D6: Grocery, quick commerce, and the market boundary — separate markets from restaurant meal delivery, or one broad on-demand delivery market? | E6: ='Q03'!B40 | F6: ='Q03'!B37 | G6: ='Q03'!B39 | H6: =HYPERLINK("https://docs.google.com/spreadsheets/d/1SGTTCNk9crU1EZRgL9dlNhuv_RvcJLmSnfJtXz3RjEE/edit#gid=1817894368&range=A1","Open")
A7: 4 | B7: Food delivery — failing-firm defence | C7: UK | D7: The failing-firm defence in food delivery — has an exiting-firm counterfactual ever been accepted, did it survive to the final decision, and on what evidence? | E7: ='Q04'!B40 | F7: ='Q04'!B37 | G7: ='Q04'!B39 | H7: =HYPERLINK("https://docs.google.com/spreadsheets/d/1SGTTCNk9crU1EZRgL9dlNhuv_RvcJLmSnfJtXz3RjEE/edit#gid=1366002813&range=A1","Open")
A8: 5 | B8: Food delivery — COVID-19 | C8: UK | D8: COVID-19 in the competitive assessment — how did the pandemic actually enter the analysis: counterfactual, market definition, or not at all? | E8: ='Q05'!B40 | F8: ='Q05'!B37 | G8: ='Q05'!B39 | H8: =HYPERLINK("https://docs.google.com/spreadsheets/d/1SGTTCNk9crU1EZRgL9dlNhuv_RvcJLmSnfJtXz3RjEE/edit#gid=1044237719&range=A1","Open")
A9: 6 | B9: Food delivery — potential competition | C9: UK | D9: Potential competition and re-entry — where the acquirer is not active in the UK, how has the CMA treated entry or re-entry absent the merger? | E9: ='Q06'!B40 | F9: ='Q06'!B37 | G9: ='Q06'!B39 | H9: =HYPERLINK("https://docs.google.com/spreadsheets/d/1SGTTCNk9crU1EZRgL9dlNhuv_RvcJLmSnfJtXz3RjEE/edit#gid=1384317690&range=A1","Open")
A10: 7 | B10: Food delivery — no-poach agreements | C10: EU | D10: No-poach agreements under Article 101 — can a reciprocal agreement not to hire each other's staff infringe Article 101, and what is the leading precedent and fine? | E10: ='Q07'!B40 | F10: ='Q07'!B37 | G10: ='Q07'!B39 | H10: =HYPERLINK("https://docs.google.com/spreadsheets/d/1SGTTCNk9crU1EZRgL9dlNhuv_RvcJLmSnfJtXz3RjEE/edit#gid=480477156&range=A1","Open")
A11: 8 | B11: Food delivery — remedies | C11: EU + UK + ES | D11: Remedies in food-delivery mergers — which European reviews ended in remedies or commitments, and what did they look like? | E11: ='Q08'!B40 | F11: ='Q08'!B37 | G11: ='Q08'!B39 | H11: =HYPERLINK("https://docs.google.com/spreadsheets/d/1SGTTCNk9crU1EZRgL9dlNhuv_RvcJLmSnfJtXz3RjEE/edit#gid=255925358&range=A1","Open")
A12: 9 | B12: Food delivery — Spanish practice | C12: ES | D12: The Spanish (CNMC) food-delivery reviews — what is the CNMC's decisional practice, how many cases, and how were they resolved? | E12: ='Q09'!B40 | F12: ='Q09'!B37 | G12: ='Q09'!B39 | H12: =HYPERLINK("https://docs.google.com/spreadsheets/d/1SGTTCNk9crU1EZRgL9dlNhuv_RvcJLmSnfJtXz3RjEE/edit#gid=2000953996&range=A1","Open")
A13: 10 | B13: Food delivery — minority shareholdings | C13: EU + UK | D13: Material influence and minority shareholdings — on what basis did the CMA take jurisdiction over a c.16% stake, and how else have authorities treated minority shareholdings in merger control? | E13: ='Q10'!B40 | F13: ='Q10'!B37 | G13: ='Q10'!B39 | H13: =HYPERLINK("https://docs.google.com/spreadsheets/d/1SGTTCNk9crU1EZRgL9dlNhuv_RvcJLmSnfJtXz3RjEE/edit#gid=1185272458&range=A1","Open")
A14: 11 | B14: Food delivery — evolution of practice | C14: EU + UK + ES | D14: The evolution of European food-delivery merger control, 2017–2025 — how has practice evolved from the first national marketplace consolidations to the recent Commission decisions? | E14: ='Q11'!B40 | F14: ='Q11'!B37 | G14: ='Q11'!B39 | H14: =HYPERLINK("https://docs.google.com/spreadsheets/d/1SGTTCNk9crU1EZRgL9dlNhuv_RvcJLmSnfJtXz3RjEE/edit#gid=1792039940&range=A1","Open")
A15: 12 | B15: Dawn raids — legal professional privilege | C15: France | D15: At what stage is attorney-client privilege breached during a dawn raid — when the inspector reads the document, or only when it is later used? | E15: ='Q12'!B40 | F15: ='Q12'!B37 | G15: ='Q12'!B39 | H15: =HYPERLINK("https://docs.google.com/spreadsheets/d/1SGTTCNk9crU1EZRgL9dlNhuv_RvcJLmSnfJtXz3RjEE/edit#gid=1162681808&range=A1","Open")
A16: 13 | B16: Dawn raids — personal data | C16: France | D16: Under what conditions must the Competition Authority protect personal data during a dawn raid? Does the GDPR apply? Must documents be sealed on request? | E16: ='Q13'!B40 | F16: ='Q13'!B37 | G16: ='Q13'!B39 | H16: =HYPERLINK("https://docs.google.com/spreadsheets/d/1SGTTCNk9crU1EZRgL9dlNhuv_RvcJLmSnfJtXz3RjEE/edit#gid=1447177020&range=A1","Open")
A17: 14 | B17: Dawn raids — challenging a seizure | C17: France | D17: After a dawn raid, can the President of the Court of Appeal be seized in interim proceedings to urgently resolve attorney-client privilege disputes? On what legal basis and under what conditions? | E17: ='Q14'!B40 | F17: ='Q14'!B37 | G17: ='Q14'!B39 | H17: =HYPERLINK("https://docs.google.com/spreadsheets/d/1SGTTCNk9crU1EZRgL9dlNhuv_RvcJLmSnfJtXz3RjEE/edit#gid=1075356362&range=A1","Open")
A18: 15 | B18: Dawn raids — legal professional privilege | C18: EU | D18: At what stage is attorney-client privilege breached during a European Commission inspection under Article 20 of Regulation 1/2003 — when the inspector reads the document, or only when the Commission later uses it? | E18: ='Q15'!B40 | F18: ='Q15'!B37 | G18: ='Q15'!B39 | H18: =HYPERLINK("https://docs.google.com/spreadsheets/d/1SGTTCNk9crU1EZRgL9dlNhuv_RvcJLmSnfJtXz3RjEE/edit#gid=620738959&range=A1","Open")
A19: 16 | B19: Dawn raids — personal data | C19: EU | D19: Under what conditions must the European Commission protect personal data during an inspection? Does the GDPR apply? Must documents be sealed on request? | E19: ='Q16'!B40 | F19: ='Q16'!B37 | G19: ='Q16'!B39 | H19: =HYPERLINK("https://docs.google.com/spreadsheets/d/1SGTTCNk9crU1EZRgL9dlNhuv_RvcJLmSnfJtXz3RjEE/edit#gid=141567022&range=A1","Open")
A20: 17 | B20: Dawn raids — challenging a seizure | C20: EU | D20: What procedural avenues exist to challenge seizure of privileged documents after a European Commission inspection? | E20: ='Q17'!B40 | F20: ='Q17'!B37 | G20: ='Q17'!B39 | H20: =HYPERLINK("https://docs.google.com/spreadsheets/d/1SGTTCNk9crU1EZRgL9dlNhuv_RvcJLmSnfJtXz3RjEE/edit#gid=393784023&range=A1","Open")
A21: 18 | B21: Dawn raids — legal professional privilege | C21: US | D21: At what stage is attorney-client privilege breached when US antitrust authorities gather documents — when the investigator reads the document, or only when it is later used? | E21: ='Q18'!B40 | F21: ='Q18'!B37 | G21: ='Q18'!B39 | H21: =HYPERLINK("https://docs.google.com/spreadsheets/d/1SGTTCNk9crU1EZRgL9dlNhuv_RvcJLmSnfJtXz3RjEE/edit#gid=631067114&range=A1","Open")
A22: 19 | B22: Dawn raids — personal data | C22: US | D22: What protections apply to personal or otherwise sensitive data gathered by U.S. antitrust authorities, and on what grounds may material that is irrelevant, overbroad, privileged, or otherwise protected be segregated, withheld, returned, or destroyed? | E22: ='Q19'!B40 | F22: ='Q19'!B37 | G22: ='Q19'!B39 | H22: =HYPERLINK("https://docs.google.com/spreadsheets/d/1SGTTCNk9crU1EZRgL9dlNhuv_RvcJLmSnfJtXz3RjEE/edit#gid=1900000019&range=A1","Open")
A23: 20 | B23: Dawn raids — challenging a seizure | C23: US | D23: What procedural avenues exist to challenge the seizure, review, retention, or use of privileged documents following the execution of a search warrant in a criminal antitrust investigation, and how do those remedies differ from procedures for modifying or setting aside a subpoena or Civil Investigative Demand (CID) in a civil antitrust investigation? | E23: ='Q20'!B40 | F23: ='Q20'!B37 | G23: ='Q20'!B39 | H23: =HYPERLINK("https://docs.google.com/spreadsheets/d/1SGTTCNk9crU1EZRgL9dlNhuv_RvcJLmSnfJtXz3RjEE/edit#gid=1900000020&range=A1","Open")
A24: 21 | B24: Food delivery — data access | C24: EU + UK | D24: Where a platform like Uber leverages data collected across its ecosystem to improve and strengthen its food delivery arm, how would such conduct be characterised under EU competition law — as tying/bundling, as an exploitative abuse, as leveraging into an adjacent market, or as a distinct data-driven theory of harm? Which category best fits, and what would be required to establish it under Article 102 TFEU? | E24: ='Q21'!B40 | F24: ='Q21'!B37 | G24: ='Q21'!B39 | H24: =HYPERLINK("https://docs.google.com/spreadsheets/d/1SGTTCNk9crU1EZRgL9dlNhuv_RvcJLmSnfJtXz3RjEE/edit#gid=832901646&range=A1","Open")
A25: 22 | B25: Food delivery — own fleet vs marketplace | C25: EU + UK + ES | D25: Can a food-delivery platform qualify as a provider of online intermediation services within the meaning of the P2B Regulation (EU) 2019/1150 — and if so, which obligations would it additionally have to comply with should it be designated as a gatekeeper under the DMA? | E25: ='Q22'!B40 | F25: ='Q22'!B37 | G25: ='Q22'!B39 | H25: =HYPERLINK("https://docs.google.com/spreadsheets/d/1SGTTCNk9crU1EZRgL9dlNhuv_RvcJLmSnfJtXz3RjEE/edit#gid=1144467272&range=A1","Open")
A26: 23 | B26: Food delivery — which authority reviews | C26: EU + UK + ES | D26: Food-delivery transactions frequently fall below the EU Merger Regulation turnover thresholds yet raise cross-border concerns. In light of the CJEU's Illumina/Grail judgment restricting Article 22 upward referrals for deals that do not meet any national threshold, what mechanisms remain for the Commission to capture a below-threshold food-delivery 'killer acquisition'? | E26: ='Q23'!B40 | F26: ='Q23'!B37 | G26: ='Q23'!B39 | H26: =HYPERLINK("https://docs.google.com/spreadsheets/d/1SGTTCNk9crU1EZRgL9dlNhuv_RvcJLmSnfJtXz3RjEE/edit#gid=1842731106&range=A1","Open")
A27: 24 | B27: Dawn raids — legal professional privilege | C27: EU | D27: Does legal professional privilege in EU competition law cover advice from a company's own in-house lawyers? How have the courts justified where the line falls, and what does that mean in practice during an inspection? | E27: ='Q24'!B40 | F27: ='Q24'!B37 | G27: ='Q24'!B39 | H27: =HYPERLINK("https://docs.google.com/spreadsheets/d/1SGTTCNk9crU1EZRgL9dlNhuv_RvcJLmSnfJtXz3RjEE/edit#gid=358280174&range=A1","Open")
A28: 25 | B28: Dawn raids — legal professional privilege | C28: France | D28: Where a French dawn raid seizes a mailbox or a set of files in bulk and privileged correspondence is found inside afterwards, what is the procedure for having it returned or destroyed, and who decides? | E28: ='Q25'!B40 | F28: ='Q25'!B37 | G28: ='Q25'!B39 | H28: =HYPERLINK("https://docs.google.com/spreadsheets/d/1SGTTCNk9crU1EZRgL9dlNhuv_RvcJLmSnfJtXz3RjEE/edit#gid=1832451430&range=A1","Open")
A29: 26 | B29: Dawn raids — challenging a seizure | C29: France | D29: French law separates a challenge to the order authorising a dawn raid from a challenge to how the raid was carried out. What are the two routes, who hears each, what are the time limits, and what can each achieve? | E29: ='Q26'!B40 | F29: ='Q26'!B37 | G29: ='Q26'!B39 | H29: =HYPERLINK("https://docs.google.com/spreadsheets/d/1SGTTCNk9crU1EZRgL9dlNhuv_RvcJLmSnfJtXz3RjEE/edit#gid=1060349846&range=A1","Open")
A30: 27 | B30: Dawn raids — the inspection decision | C30: EU | D30: What is the extent of the Commission's duty to state reasons under Article 20(4) of Regulation 1/2003 as regards the subject matter and purpose of an inspection decision and the identification of its addressees — and what are the consequences, in light of Nexans, Deutsche Bahn and Les Laboratoires Servier, where the scope of the inspection exceeds the reasonable grounds (indicia) actually in the Commission's possession? | E30: ='Q27'!B40 | F30: ='Q27'!B37 | G30: ='Q27'!B39 | H30: =HYPERLINK("https://docs.google.com/spreadsheets/d/1SGTTCNk9crU1EZRgL9dlNhuv_RvcJLmSnfJtXz3RjEE/edit#gid=854637919&range=A1","Open")
A31: 28 | B31: Dawn raids — the inspection decision | C31: EU | D31: Can an inspection decision be annulled in part where the Commission's evidence supports only some of the suspected infringement period it covers, and what then happens to material already gathered? | E31: ='Q28'!B40 | F31: ='Q28'!B37 | G31: ='Q28'!B39 | H31: =HYPERLINK("https://docs.google.com/spreadsheets/d/1SGTTCNk9crU1EZRgL9dlNhuv_RvcJLmSnfJtXz3RjEE/edit#gid=481311560&range=A1","Open")
A32: 29 | B32: Dawn raids — the inspection decision | C32: France | D32: How specific must a French dawn-raid authorisation be about the premises to be visited, the practices suspected, and the period covered? What has been held insufficient? | E32: ='Q29'!B40 | F32: ='Q29'!B37 | G32: ='Q29'!B39 | H32: =HYPERLINK("https://docs.google.com/spreadsheets/d/1SGTTCNk9crU1EZRgL9dlNhuv_RvcJLmSnfJtXz3RjEE/edit#gid=1094927511&range=A1","Open")
A33: 30 | B33: Dawn raids — obstruction and seals | C33: EU | D33: Does the obstruction regime of Article 23(1) of Regulation 1/2003 — conceived for physical records and corporate email — still fit an environment of ephemeral, encrypted messaging on employees' personal devices? Where does the deletion of a WhatsApp or Signal message during or ahead of an inspection cross from ordinary personal housekeeping into a sanctionable procedural infringement, and how must intent and attribution be established when the device and the account belong to the individual rather than the undertaking? | E33: ='Q30'!B40 | F33: ='Q30'!B37 | G33: ='Q30'!B39 | H33: =HYPERLINK("https://docs.google.com/spreadsheets/d/1SGTTCNk9crU1EZRgL9dlNhuv_RvcJLmSnfJtXz3RjEE/edit#gid=719176577&range=A1","Open")
A34: 31 | B34: Dawn raids — obstruction and seals | C34: EU | D34: To what extent may an undertaking be fined for the breaking of a seal in the absence of any fault or intent, and how is that reconciled with the presumption of innocence? | E34: ='Q31'!B40 | F34: ='Q31'!B37 | G34: ='Q31'!B39 | H34: =HYPERLINK("https://docs.google.com/spreadsheets/d/1SGTTCNk9crU1EZRgL9dlNhuv_RvcJLmSnfJtXz3RjEE/edit#gid=987315445&range=A1","Open")
A35: 32 | B35: Dawn raids — obstruction and seals | C35: France | D35: What behavior during a French dawn raid (OVS) exposes a company to obstruction liability, and what training precautions follow from recent enforcement? | E35: ='Q32'!B40 | F35: ='Q32'!B37 | G35: ='Q32'!B39 | H35: =HYPERLINK("https://docs.google.com/spreadsheets/d/1SGTTCNk9crU1EZRgL9dlNhuv_RvcJLmSnfJtXz3RjEE/edit#gid=1892631162&range=A1","Open")
A36: 33 | B36: Dawn raids — obstruction and preservation of evidence | C36: US | D36: What consequences may follow from obstructing an actual or contemplated federal antitrust investigation, including by destroying, altering, or concealing evidence, and when do separate legal obligations to preserve potentially relevant evidence arise? | E36: ='Q33'!B40 | F36: ='Q33'!B37 | G36: ='Q33'!B39 | H36: =HYPERLINK("https://docs.google.com/spreadsheets/d/1SGTTCNk9crU1EZRgL9dlNhuv_RvcJLmSnfJtXz3RjEE/edit#gid=1900000037&range=A1","Open")
A37: 34 | B37: Dawn raids — questioning staff | C37: EU | D37: To what extent may the Commission compel answers under Article 20(2)(e) of Regulation 1/2003 before the privilege against self-incrimination intervenes — and how the distinction between answering questions of fact and admitting an infringement remain workable in practice? | E37: ='Q34'!B40 | F37: ='Q34'!B37 | G37: ='Q34'!B39 | H37: =HYPERLINK("https://docs.google.com/spreadsheets/d/1SGTTCNk9crU1EZRgL9dlNhuv_RvcJLmSnfJtXz3RjEE/edit#gid=1725701280&range=A1","Open")
A38: 35 | B38: Dawn raids — questioning staff | C38: France | D38: Can employees be required to answer questions during a French dawn raid, and what protection against self-incrimination do they and the company have? | E38: ='Q35'!B40 | F38: ='Q35'!B37 | G38: ='Q35'!B39 | H38: =HYPERLINK("https://docs.google.com/spreadsheets/d/1SGTTCNk9crU1EZRgL9dlNhuv_RvcJLmSnfJtXz3RjEE/edit#gid=786847173&range=A1","Open")
A39: 36 | B39: Dawn raids — questioning staff | C39: US | D39: How does the Fifth Amendment privilege against self-incrimination apply in a U.S. antitrust investigation to compelled oral testimony versus the production of documents? Why does the privilege belong to natural persons rather than corporations, and how does the collective-entity doctrine affect an individual custodian who is required to produce corporate records? | E39: ='Q36'!B40 | F39: ='Q36'!B37 | G39: ='Q36'!B39 | H39: =HYPERLINK("https://docs.google.com/spreadsheets/d/1SGTTCNk9crU1EZRgL9dlNhuv_RvcJLmSnfJtXz3RjEE/edit#gid=1900000040&range=A1","Open")
A40: 37 | B40: Dawn raids — electronic data | C40: EU | D40: May the Commission take a forensic copy of a company's electronic data and carry on examining it at its own premises after the inspection has ended? What safeguards apply, and what rights does the company keep over that copy? | E40: ='Q37'!B40 | F40: ='Q37'!B37 | G40: ='Q37'!B39 | H40: =HYPERLINK("https://docs.google.com/spreadsheets/d/1SGTTCNk9crU1EZRgL9dlNhuv_RvcJLmSnfJtXz3RjEE/edit#gid=581550900&range=A1","Open")
A41: 38 | B41: Dawn raids — electronic data | C41: EU | D41: Whose interests prevail when an inspection captures the private communications of employees who are not themselves under investigation — the Commission's investigative reach, or the privacy protected by Articles 7 and 8 of the Charter? And when does an undertaking's effort to shield that data become obstruction? | E41: ='Q38'!B40 | F41: ='Q38'!B37 | G41: ='Q38'!B39 | H41: =HYPERLINK("https://docs.google.com/spreadsheets/d/1SGTTCNk9crU1EZRgL9dlNhuv_RvcJLmSnfJtXz3RjEE/edit#gid=290888835&range=A1","Open")
A42: 39 | B42: Dawn raids — electronic data | C42: France | D42: Under what conditions can French competition authorities seize entire mailboxes during a dawn raid rather than sorting them on-site, how is the in-scope material subsequently identified, and what happens to material found to be out of scope? | E42: ='Q39'!B40 | F42: ='Q39'!B37 | G42: ='Q39'!B39 | H42: =HYPERLINK("https://docs.google.com/spreadsheets/d/1SGTTCNk9crU1EZRgL9dlNhuv_RvcJLmSnfJtXz3RjEE/edit#gid=224496350&range=A1","Open")
A43: 40 | B43: Dawn raids — electronic data | C43: US | D43: In a criminal U.S. antitrust investigation, when may electronic devices or electronically stored information be seized or copied for later off-site review, and what limits do the search warrant, Rule 41, the Fourth Amendment, and privilege-review procedures impose? | E43: ='Q40'!B40 | F43: ='Q40'!B37 | G43: ='Q40'!B39 | H43: =HYPERLINK("https://docs.google.com/spreadsheets/d/1SGTTCNk9crU1EZRgL9dlNhuv_RvcJLmSnfJtXz3RjEE/edit#gid=1900000044&range=A1","Open")
A44: 41 | B44: Dawn raids — evidence found by accident | C44: EU | D44: May the Commission use evidence of an infringement falling outside the subject matter of the inspection decision? What are the limits imposed by the relevant case law on the use of such incidental findings, and on what conditions may a chance discovery justify a new inspection? | E44: ='Q41'!B40 | F44: ='Q41'!B37 | G44: ='Q41'!B39 | H44: =HYPERLINK("https://docs.google.com/spreadsheets/d/1SGTTCNk9crU1EZRgL9dlNhuv_RvcJLmSnfJtXz3RjEE/edit#gid=394068235&range=A1","Open")
A45: 42 | B45: Dawn raids — evidence found by accident | C45: EU | D45: Can the Commission inspect a company over conduct a national authority has already investigated? What limits apply, and how have the courts treated the overlap? | E45: ='Q42'!B40 | F45: ='Q42'!B37 | G45: ='Q42'!B39 | H45: =HYPERLINK("https://docs.google.com/spreadsheets/d/1SGTTCNk9crU1EZRgL9dlNhuv_RvcJLmSnfJtXz3RjEE/edit#gid=23567523&range=A1","Open")
A46: 43 | B46: Dawn raids — premises and the courts | C46: EU | D46: How is the inviolability of business premises reconciled with the Commission's inspection powers under Article 20 of Regulation 1/2003 — in particular, when is prior judicial authorisation required, and what may the national court asked to authorise coercive assistance review under Article 20(8)? | E46: ='Q43'!B40 | F46: ='Q43'!B37 | G46: ='Q43'!B39 | H46: =HYPERLINK("https://docs.google.com/spreadsheets/d/1SGTTCNk9crU1EZRgL9dlNhuv_RvcJLmSnfJtXz3RjEE/edit#gid=1337837468&range=A1","Open")
A47: 44 | B47: Dawn raids — premises and the courts | C47: EU | D47: In light of the recent case law of the Court of Justice, may a national competition authority seize an undertaking's business emails without prior judicial authorisation, and does full ex post review adequately protect the right to respect for communications under Article 7 of the Charter? | E47: ='Q44'!B40 | F47: ='Q44'!B37 | G47: ='Q44'!B39 | H47: =HYPERLINK("https://docs.google.com/spreadsheets/d/1SGTTCNk9crU1EZRgL9dlNhuv_RvcJLmSnfJtXz3RjEE/edit#gid=415100601&range=A1","Open")
A48: 45 | B48: Dawn raids — premises and the courts | C48: France | D48: When must a French dawn raid be authorised in advance by the juge des libertés et de la détention , and what does that judge control before, during, and after the operation? | E48: ='Q45'!B40 | F48: ='Q45'!B37 | G48: ='Q45'!B39 | H48: =HYPERLINK("https://docs.google.com/spreadsheets/d/1SGTTCNk9crU1EZRgL9dlNhuv_RvcJLmSnfJtXz3RjEE/edit#gid=1504695928&range=A1","Open")
A49: 46 | B49: Dawn raids — premises and the courts | C49: US | D49: What must the Department of Justice establish to obtain and execute a search warrant in a criminal antitrust investigation, and what limits apply to the search? How do criminal search warrants differ from grand-jury subpoenas in criminal investigations and from subpoenas or Civil Investigative Demands (CIDs) used in civil antitrust investigations? | E49: ='Q46'!B40 | F49: ='Q46'!B37 | G49: ='Q46'!B39 | H49: =HYPERLINK("https://docs.google.com/spreadsheets/d/1SGTTCNk9crU1EZRgL9dlNhuv_RvcJLmSnfJtXz3RjEE/edit#gid=1900000050&range=A1","Open")
A50: 47 | B50: Dawn raids — personal data | C50: EU | D50: To what extent may the Commission inspect private correspondence, personal devices and employees’ personal data during a dawn raid, and does the sealed-envelope procedure extend beyond legally privileged material? | E50: ='Q47'!B40 | F50: ='Q47'!B37 | G50: ='Q47'!B39 | H50: =HYPERLINK("https://docs.google.com/spreadsheets/d/1SGTTCNk9crU1EZRgL9dlNhuv_RvcJLmSnfJtXz3RjEE/edit#gid=1734276489&range=A1","Open")
A51: 48 | B51: Dawn raids — legal professional privilege | C51: France | D51: Under French law, to what extent are communications between a company and its lawyers protected during a competition dawn raid, how can the company challenge the seizure of allegedly privileged material, and what remedies are available if privileged documents have been seized (including return, destruction, or exclusion from the investigation)? | E51: ='Q48'!B40 | F51: ='Q48'!B37 | G51: ='Q48'!B39 | H51: =HYPERLINK("https://docs.google.com/spreadsheets/d/1SGTTCNk9crU1EZRgL9dlNhuv_RvcJLmSnfJtXz3RjEE/edit#gid=1544115431&range=A1","Open")
A52: 49 | B52: Dawn raids — grounds for an inspection | C52: EU | D52: What evidentiary threshold must the European Commission meet to justify a dawn raid, including the requirement for “sufficiently serious indicia”? | E52: ='Q49'!B40 | F52: ='Q49'!B37 | G52: ='Q49'!B39 | H52: =HYPERLINK("https://docs.google.com/spreadsheets/d/1SGTTCNk9crU1EZRgL9dlNhuv_RvcJLmSnfJtXz3RjEE/edit#gid=1497151088&range=A1","Open")
A53: 50 | B53: Dawn raids — grounds for an inspection | C53: EU | D53: What is an undertaking entitled to know about the indicia underpinning an inspection decision, beyond its subject matter and purpose under Article 20(4) of Regulation 1/2003? | E53: ='Q50'!B40 | F53: ='Q50'!B37 | G53: ='Q50'!B39 | H53: =HYPERLINK("https://docs.google.com/spreadsheets/d/1SGTTCNk9crU1EZRgL9dlNhuv_RvcJLmSnfJtXz3RjEE/edit#gid=11098577&range=A1","Open")
A54: 51 | B54: Dawn raids — legal professional privilege | C54: US | D54: How are attorney-client privilege and work-product protection safeguarded in U.S. antitrust investigations conducted through criminal search warrants or civil compulsory process? What protections, including filter teams or special masters, prevent privileged material from reaching the investigating team, and at what stages can privilege concerns arise — seizure, initial review, disclosure, retention, or derivative use? | E54: ='Q51'!B40 | F54: ='Q51'!B37 | G54: ='Q51'!B39 | H54: =HYPERLINK("https://docs.google.com/spreadsheets/d/1SGTTCNk9crU1EZRgL9dlNhuv_RvcJLmSnfJtXz3RjEE/edit#gid=1900000055&range=A1","Open")
A55: 52 | B55: Dawn raids — electronic data | C55: US | D55: How does obtaining and reviewing electronically stored information through subpoenas or Civil Investigative Demands (CIDs) in civil antitrust investigations differ from the criminal-search process? | E55: ='Q52'!B40 | F55: ='Q52'!B37 | G55: ='Q52'!B39 | H55: =HYPERLINK("https://docs.google.com/spreadsheets/d/1SGTTCNk9crU1EZRgL9dlNhuv_RvcJLmSnfJtXz3RjEE/edit#gid=1900000056&range=A1","Open")

Sheet Q01
A1: Q01 — Expert Review
A2: Question metadata
A3: Question ID | B3: 1
A4: Topic | B4: Food delivery — market definition
A5: Scope | B5: EU + UK + ES
A6: Original reviewer | B6: Carolina
A7: Original status | B7: Approved
A8: Question | B8: The relevant market in a food-delivery acquisition — how have the Commission and national authorities defined the relevant product and geographic markets, and on what rationales?
A9: Generated answer
A10: Paste the generated answer here.
A11: Run ID | C11: Run date
A12: Retrieval set review
A13: Rank | B13: Document name | C13: Document class | D13: Jurisdiction | E13: URL / Document ID | F13: Required source? | G13: Expert verdict | H13: Notes
A14: 1
A15: 2
A16: 3
A17: 4
A18: 5
A19: 6
A20: 7
A21: 8
A22: 9
A24: Claim-by-claim review
A25: Claim ID | B25: Claim from answer | C25: Cited document | D25: Expert verdict | E25: Cited passage | F25: Required fix / comment
A26: 1
A27: 2
A28: 3
A29: 4
A30: 5
A31: 6
A32: 7
A33: 8
A34: 9
A36: Final expert verdict
A37: Reviewer
A38: Is the answer acceptable?
A39: Overall comment / required fixes
A40: Review completed?

Sheet Lists
A1: A | B1: B | C1: C | D1: D | E1: E | F1: F | G1: G | H1: H
A2: Yes | B2: Not started | C2: Acceptable | D2: Supported | E2: None | F2: Primary law | G2: Yes | H2: Relevant
A3: No | B3: In review | C3: Partly acceptable | D3: Partly supported | E3: Missing source | F3: Concurrences commentary | G3: No | H3: Not relevant
B4: Completed | C4: Not acceptable | D4: Not supported | E4: Wrong citation | F4: Other commentary | G4: Unsure | H4: Duplicate
B5: Needs follow-up | D5: Wrong source | E5: Overclaim | F5: Other | H5: Trap
D6: Missing citation | E6: Unsupported claim | H6: Missing important source
D7: Not a legal claim | E7: Ambiguous wording
E8: Other

Sheet Scoring Summary
A1: Scoring Summary
A2: Team-facing summary. Experts only need to complete the question tabs; this sheet pulls verdicts together.
A4: Question ID | B4: Total claims | C4: Supports claim | D4: Partially supports claim | E4: Does not support claim
A5: 1 | B5: =COUNTA('Q01'!B26:B34) | C5: =COUNTIF('Q01'!D26:D34,"Supports claim") | D5: =COUNTIF('Q01'!D26:D34,"Partially supports claim") | E5: =COUNTIF('Q01'!D26:D34,"Does not support claim")
A6: 2 | B6: =COUNTA('Q02'!B26:B34) | C6: =COUNTIF('Q02'!D26:D34,"Supports claim") | D6: =COUNTIF('Q02'!D26:D34,"Partially supports claim") | E6: =COUNTIF('Q02'!D26:D34,"Does not support claim")
A7: 3 | B7: =COUNTA('Q03'!B26:B34) | C7: =COUNTIF('Q03'!D26:D34,"Supports claim") | D7: =COUNTIF('Q03'!D26:D34,"Partially supports claim") | E7: =COUNTIF('Q03'!D26:D34,"Does not support claim")
A8: 4 | B8: =COUNTA('Q04'!B26:B34) | C8: =COUNTIF('Q04'!D26:D34,"Supports claim") | D8: =COUNTIF('Q04'!D26:D34,"Partially supports claim") | E8: =COUNTIF('Q04'!D26:D34,"Does not support claim")
A9: 5 | B9: =COUNTA('Q05'!B26:B34) | C9: =COUNTIF('Q05'!D26:D34,"Supports claim") | D9: =COUNTIF('Q05'!D26:D34,"Partially supports claim") | E9: =COUNTIF('Q05'!D26:D34,"Does not support claim")
A10: 6 | B10: =COUNTA('Q06'!B26:B34) | C10: =COUNTIF('Q06'!D26:D34,"Supports claim") | D10: =COUNTIF('Q06'!D26:D34,"Partially supports claim") | E10: =COUNTIF('Q06'!D26:D34,"Does not support claim")
A11: 7 | B11: =COUNTA('Q07'!B26:B34) | C11: =COUNTIF('Q07'!D26:D34,"Supports claim") | D11: =COUNTIF('Q07'!D26:D34,"Partially supports claim") | E11: =COUNTIF('Q07'!D26:D34,"Does not support claim")
A12: 8 | B12: =COUNTA('Q08'!B26:B34) | C12: =COUNTIF('Q08'!D26:D34,"Supports claim") | D12: =COUNTIF('Q08'!D26:D34,"Partially supports claim") | E12: =COUNTIF('Q08'!D26:D34,"Does not support claim")
A13: 9 | B13: =COUNTA('Q09'!B26:B34) | C13: =COUNTIF('Q09'!D26:D34,"Supports claim") | D13: =COUNTIF('Q09'!D26:D34,"Partially supports claim") | E13: =COUNTIF('Q09'!D26:D34,"Does not support claim")
A14: 10 | B14: =COUNTA('Q10'!B26:B34) | C14: =COUNTIF('Q10'!D26:D34,"Supports claim") | D14: =COUNTIF('Q10'!D26:D34,"Partially supports claim") | E14: =COUNTIF('Q10'!D26:D34,"Does not support claim")
A15: 11 | B15: =COUNTA('Q11'!B26:B34) | C15: =COUNTIF('Q11'!D26:D34,"Supports claim") | D15: =COUNTIF('Q11'!D26:D34,"Partially supports claim") | E15: =COUNTIF('Q11'!D26:D34,"Does not support claim")
A16: 12 | B16: =COUNTA('Q12'!B26:B34) | C16: =COUNTIF('Q12'!D26:D34,"Supports claim") | D16: =COUNTIF('Q12'!D26:D34,"Partially supports claim") | E16: =COUNTIF('Q12'!D26:D34,"Does not support claim")
A17: 13 | B17: =COUNTA('Q13'!B26:B34) | C17: =COUNTIF('Q13'!D26:D34,"Supports claim") | D17: =COUNTIF('Q13'!D26:D34,"Partially supports claim") | E17: =COUNTIF('Q13'!D26:D34,"Does not support claim")
A18: 14 | B18: =COUNTA('Q14'!B26:B34) | C18: =COUNTIF('Q14'!D26:D34,"Supports claim") | D18: =COUNTIF('Q14'!D26:D34,"Partially supports claim") | E18: =COUNTIF('Q14'!D26:D34,"Does not support claim")
A19: 15 | B19: =COUNTA('Q15'!B26:B34) | C19: =COUNTIF('Q15'!D26:D34,"Supports claim") | D19: =COUNTIF('Q15'!D26:D34,"Partially supports claim") | E19: =COUNTIF('Q15'!D26:D34,"Does not support claim")
A20: 16 | B20: =COUNTA('Q16'!B26:B34) | C20: =COUNTIF('Q16'!D26:D34,"Supports claim") | D20: =COUNTIF('Q16'!D26:D34,"Partially supports claim") | E20: =COUNTIF('Q16'!D26:D34,"Does not support claim")
A21: 17 | B21: =COUNTA('Q17'!B26:B34) | C21: =COUNTIF('Q17'!D26:D34,"Supports claim") | D21: =COUNTIF('Q17'!D26:D34,"Partially supports claim") | E21: =COUNTIF('Q17'!D26:D34,"Does not support claim")
A22: 18 | B22: =COUNTA('Q18'!B26:B34) | C22: =COUNTIF('Q18'!D26:D34,"Supports claim") | D22: =COUNTIF('Q18'!D26:D34,"Partially supports claim") | E22: =COUNTIF('Q18'!D26:D34,"Does not support claim")
A23: 19 | B23: =COUNTA('Q19'!B26:B34) | C23: =COUNTIF('Q19'!D26:D34,"Supports claim") | D23: =COUNTIF('Q19'!D26:D34,"Partially supports claim") | E23: =COUNTIF('Q19'!D26:D34,"Does not support claim")
A24: 20 | B24: =COUNTA('Q20'!B26:B34) | C24: =COUNTIF('Q20'!D26:D34,"Supports claim") | D24: =COUNTIF('Q20'!D26:D34,"Partially supports claim") | E24: =COUNTIF('Q20'!D26:D34,"Does not support claim")
A25: 21 | B25: =COUNTA('Q21'!B26:B34) | C25: =COUNTIF('Q21'!D26:D34,"Supports claim") | D25: =COUNTIF('Q21'!D26:D34,"Partially supports claim") | E25: =COUNTIF('Q21'!D26:D34,"Does not support claim")
A26: 22 | B26: =COUNTA('Q22'!B26:B34) | C26: =COUNTIF('Q22'!D26:D34,"Supports claim") | D26: =COUNTIF('Q22'!D26:D34,"Partially supports claim") | E26: =COUNTIF('Q22'!D26:D34,"Does not support claim")
A27: 23 | B27: =COUNTA('Q23'!B26:B34) | C27: =COUNTIF('Q23'!D26:D34,"Supports claim") | D27: =COUNTIF('Q23'!D26:D34,"Partially supports claim") | E27: =COUNTIF('Q23'!D26:D34,"Does not support claim")
A28: 24 | B28: =COUNTA('Q24'!B26:B34) | C28: =COUNTIF('Q24'!D26:D34,"Supports claim") | D28: =COUNTIF('Q24'!D26:D34,"Partially supports claim") | E28: =COUNTIF('Q24'!D26:D34,"Does not support claim")
A29: 25 | B29: =COUNTA('Q25'!B26:B34) | C29: =COUNTIF('Q25'!D26:D34,"Supports claim") | D29: =COUNTIF('Q25'!D26:D34,"Partially supports claim") | E29: =COUNTIF('Q25'!D26:D34,"Does not support claim")
A30: 26 | B30: =COUNTA('Q26'!B26:B34) | C30: =COUNTIF('Q26'!D26:D34,"Supports claim") | D30: =COUNTIF('Q26'!D26:D34,"Partially supports claim") | E30: =COUNTIF('Q26'!D26:D34,"Does not support claim")
A31: 27 | B31: =COUNTA('Q27'!B26:B34) | C31: =COUNTIF('Q27'!D26:D34,"Supports claim") | D31: =COUNTIF('Q27'!D26:D34,"Partially supports claim") | E31: =COUNTIF('Q27'!D26:D34,"Does not support claim")
A32: 28 | B32: =COUNTA('Q28'!B26:B34) | C32: =COUNTIF('Q28'!D26:D34,"Supports claim") | D32: =COUNTIF('Q28'!D26:D34,"Partially supports claim") | E32: =COUNTIF('Q28'!D26:D34,"Does not support claim")
A33: 29 | B33: =COUNTA('Q29'!B26:B34) | C33: =COUNTIF('Q29'!D26:D34,"Supports claim") | D33: =COUNTIF('Q29'!D26:D34,"Partially supports claim") | E33: =COUNTIF('Q29'!D26:D34,"Does not support claim")
A34: 30 | B34: =COUNTA('Q30'!B26:B34) | C34: =COUNTIF('Q30'!D26:D34,"Supports claim") | D34: =COUNTIF('Q30'!D26:D34,"Partially supports claim") | E34: =COUNTIF('Q30'!D26:D34,"Does not support claim")
A35: 31 | B35: =COUNTA('Q31'!B26:B34) | C35: =COUNTIF('Q31'!D26:D34,"Supports claim") | D35: =COUNTIF('Q31'!D26:D34,"Partially supports claim") | E35: =COUNTIF('Q31'!D26:D34,"Does not support claim")
A36: 32 | B36: =COUNTA('Q32'!B26:B34) | C36: =COUNTIF('Q32'!D26:D34,"Supports claim") | D36: =COUNTIF('Q32'!D26:D34,"Partially supports claim") | E36: =COUNTIF('Q32'!D26:D34,"Does not support claim")
A37: 33 | B37: =COUNTA('Q33'!B26:B34) | C37: =COUNTIF('Q33'!D26:D34,"Supports claim") | D37: =COUNTIF('Q33'!D26:D34,"Partially supports claim") | E37: =COUNTIF('Q33'!D26:D34,"Does not support claim")
A38: 34 | B38: =COUNTA('Q34'!B26:B34) | C38: =COUNTIF('Q34'!D26:D34,"Supports claim") | D38: =COUNTIF('Q34'!D26:D34,"Partially supports claim") | E38: =COUNTIF('Q34'!D26:D34,"Does not support claim")
A39: 35 | B39: =COUNTA('Q35'!B26:B34) | C39: =COUNTIF('Q35'!D26:D34,"Supports claim") | D39: =COUNTIF('Q35'!D26:D34,"Partially supports claim") | E39: =COUNTIF('Q35'!D26:D34,"Does not support claim")
A40: 36 | B40: =COUNTA('Q36'!B26:B34) | C40: =COUNTIF('Q36'!D26:D34,"Supports claim") | D40: =COUNTIF('Q36'!D26:D34,"Partially supports claim") | E40: =COUNTIF('Q36'!D26:D34,"Does not support claim")
A41: 37 | B41: =COUNTA('Q37'!B26:B34) | C41: =COUNTIF('Q37'!D26:D34,"Supports claim") | D41: =COUNTIF('Q37'!D26:D34,"Partially supports claim") | E41: =COUNTIF('Q37'!D26:D34,"Does not support claim")
A42: 38 | B42: =COUNTA('Q38'!B26:B34) | C42: =COUNTIF('Q38'!D26:D34,"Supports claim") | D42: =COUNTIF('Q38'!D26:D34,"Partially supports claim") | E42: =COUNTIF('Q38'!D26:D34,"Does not support claim")
A43: 39 | B43: =COUNTA('Q39'!B26:B34) | C43: =COUNTIF('Q39'!D26:D34,"Supports claim") | D43: =COUNTIF('Q39'!D26:D34,"Partially supports claim") | E43: =COUNTIF('Q39'!D26:D34,"Does not support claim")
A44: 40 | B44: =COUNTA('Q40'!B26:B34) | C44: =COUNTIF('Q40'!D26:D34,"Supports claim") | D44: =COUNTIF('Q40'!D26:D34,"Partially supports claim") | E44: =COUNTIF('Q40'!D26:D34,"Does not support claim")
A45: 41 | B45: =COUNTA('Q41'!B26:B34) | C45: =COUNTIF('Q41'!D26:D34,"Supports claim") | D45: =COUNTIF('Q41'!D26:D34,"Partially supports claim") | E45: =COUNTIF('Q41'!D26:D34,"Does not support claim")
A46: 42 | B46: =COUNTA('Q42'!B26:B34) | C46: =COUNTIF('Q42'!D26:D34,"Supports claim") | D46: =COUNTIF('Q42'!D26:D34,"Partially supports claim") | E46: =COUNTIF('Q42'!D26:D34,"Does not support claim")
A47: 43 | B47: =COUNTA('Q43'!B26:B34) | C47: =COUNTIF('Q43'!D26:D34,"Supports claim") | D47: =COUNTIF('Q43'!D26:D34,"Partially supports claim") | E47: =COUNTIF('Q43'!D26:D34,"Does not support claim")
A48: 44 | B48: =COUNTA('Q44'!B26:B34) | C48: =COUNTIF('Q44'!D26:D34,"Supports claim") | D48: =COUNTIF('Q44'!D26:D34,"Partially supports claim") | E48: =COUNTIF('Q44'!D26:D34,"Does not support claim")
A49: 45 | B49: =COUNTA('Q45'!B26:B34) | C49: =COUNTIF('Q45'!D26:D34,"Supports claim") | D49: =COUNTIF('Q45'!D26:D34,"Partially supports claim") | E49: =COUNTIF('Q45'!D26:D34,"Does not support claim")
A50: 46 | B50: =COUNTA('Q46'!B26:B34) | C50: =COUNTIF('Q46'!D26:D34,"Supports claim") | D50: =COUNTIF('Q46'!D26:D34,"Partially supports claim") | E50: =COUNTIF('Q46'!D26:D34,"Does not support claim")
A51: 47 | B51: =COUNTA('Q47'!B26:B34) | C51: =COUNTIF('Q47'!D26:D34,"Supports claim") | D51: =COUNTIF('Q47'!D26:D34,"Partially supports claim") | E51: =COUNTIF('Q47'!D26:D34,"Does not support claim")
A52: 48 | B52: =COUNTA('Q48'!B26:B34) | C52: =COUNTIF('Q48'!D26:D34,"Supports claim") | D52: =COUNTIF('Q48'!D26:D34,"Partially supports claim") | E52: =COUNTIF('Q48'!D26:D34,"Does not support claim")
A53: 49 | B53: =COUNTA('Q49'!B26:B34) | C53: =COUNTIF('Q49'!D26:D34,"Supports claim") | D53: =COUNTIF('Q49'!D26:D34,"Partially supports claim") | E53: =COUNTIF('Q49'!D26:D34,"Does not support claim")
A54: 50 | B54: =COUNTA('Q50'!B26:B34) | C54: =COUNTIF('Q50'!D26:D34,"Supports claim") | D54: =COUNTIF('Q50'!D26:D34,"Partially supports claim") | E54: =COUNTIF('Q50'!D26:D34,"Does not support claim")
A55: 51 | B55: =COUNTA('Q51'!B26:B34) | C55: =COUNTIF('Q51'!D26:D34,"Supports claim") | D55: =COUNTIF('Q51'!D26:D34,"Partially supports claim") | E55: =COUNTIF('Q51'!D26:D34,"Does not support claim")
A56: 52 | B56: =COUNTA('Q52'!B26:B34) | C56: =COUNTIF('Q52'!D26:D34,"Supports claim") | D56: =COUNTIF('Q52'!D26:D34,"Partially supports claim") | E56: =COUNTIF('Q52'!D26:D34,"Does not support claim")

Sheet Q02
A1: Q02 — Expert Review
A2: Question metadata
A3: Question ID | B3: 2
A4: Topic | B4: Food delivery — multi-sided platforms
A5: Scope | B5: EU + UK + ES
A6: Original reviewer | B6: Carolina
A7: Original status | B7: Approved
A8: Question | B8: Food delivery as a multi-sided platform — have authorities analysed these platforms as two- or multi-sided markets, and which sides actually entered the analysis?
A9: Generated answer
A10: Paste the generated answer here.
A11: Run ID | C11: Run date
A12: Retrieval set review
A13: Rank | B13: Document name | C13: Document class | D13: Jurisdiction | E13: URL / Document ID | F13: Required source? | G13: Expert verdict | H13: Notes
A14: 1
A15: 2
A16: 3
A17: 4
A18: 5
A19: 6
A20: 7
A21: 8
A22: 9
A24: Claim-by-claim review
A25: Claim ID | B25: Claim from answer | C25: Cited document | D25: Expert verdict | E25: Cited passage | F25: Required fix / comment
A26: 1
A27: 2
A28: 3
A29: 4
A30: 5
A31: 6
A32: 7
A33: 8
A34: 9
A36: Final expert verdict
A37: Reviewer
A38: Is the answer acceptable?
A39: Overall comment / required fixes
A40: Review completed?
A69: Original source notes
A70: WAB notes
A71: Reviewer notes from question approval

Sheet Q03
A1: Q03 — Expert Review
A2: Question metadata
A3: Question ID | B3: 3
A4: Topic | B4: Food delivery — market boundary
A5: Scope | B5: UK (ES colour)
A6: Original reviewer | B6: Carolina
A7: Original status | B7: Approved
A8: Question | B8: Grocery, quick commerce, and the market boundary — separate markets from restaurant meal delivery, or one broad on-demand delivery market?
A9: Generated answer
A10: Paste the generated answer here.
A11: Run ID | C11: Run date
A12: Retrieval set review
A13: Rank | B13: Document name | C13: Document class | D13: Jurisdiction | E13: URL / Document ID | F13: Required source? | G13: Expert verdict | H13: Notes
A14: 1
A15: 2
A16: 3
A17: 4
A18: 5
A19: 6
A20: 7
A21: 8
A22: 9
A24: Claim-by-claim review
A25: Claim ID | B25: Claim from answer | C25: Cited document | D25: Expert verdict | E25: Cited passage | F25: Required fix / comment
A26: 1
A27: 2
A28: 3
A29: 4
A30: 5
A31: 6
A32: 7
A33: 8
A34: 9
A36: Final expert verdict
A37: Reviewer
A38: Is the answer acceptable?
A39: Overall comment / required fixes
A40: Review completed?
A69: Original source notes
A70: WAB notes
A71: Reviewer notes from question approval

Sheet Q04
A1: Q04 — Expert Review
A2: Question metadata
A3: Question ID | B3: 4
A4: Topic | B4: Food delivery — failing-firm defence
A5: Scope | B5: UK
A6: Original reviewer | B6: Carolina
A7: Original status | B7: Approved
A8: Question | B8: The failing-firm defence in food delivery — has an exiting-firm counterfactual ever been accepted, did it survive to the final decision, and on what evidence?
A9: Generated answer
A10: Paste the generated answer here.
A11: Run ID | C11: Run date
A12: Retrieval set review
A13: Rank | B13: Document name | C13: Document class | D13: Jurisdiction | E13: URL / Document ID | F13: Required source? | G13: Expert verdict | H13: Notes
A14: 1
A15: 2
A16: 3
A17: 4
A18: 5
A19: 6
A20: 7
A21: 8
A22: 9
A24: Claim-by-claim review
A25: Claim ID | B25: Claim from answer | C25: Cited document | D25: Expert verdict | E25: Cited passage | F25: Required fix / comment
A26: 1
A27: 2
A28: 3
A29: 4
A30: 5
A31: 6
A32: 7
A33: 8
A34: 9
A36: Final expert verdict
A37: Reviewer
A38: Is the answer acceptable?
A39: Overall comment / required fixes
A40: Review completed?
A69: Original source notes
A70: WAB notes
A71: Reviewer notes from question approval

Sheet Q05
A1: Q05 — Expert Review
A2: Question metadata
A3: Question ID | B3: 5
A4: Topic | B4: Food delivery — COVID-19
A5: Scope | B5: UK
A6: Original reviewer | B6: Carolina
A7: Original status | B7: Approved
A8: Question | B8: COVID-19 in the competitive assessment — how did the pandemic actually enter the analysis: counterfactual, market definition, or not at all?
A9: Generated answer
A10: Paste the generated answer here.
A11: Run ID | C11: Run date
A12: Retrieval set review
A13: Rank | B13: Document name | C13: Document class | D13: Jurisdiction | E13: URL / Document ID | F13: Required source? | G13: Expert verdict | H13: Notes
A14: 1
A15: 2
A16: 3
A17: 4
A18: 5
A19: 6
A20: 7
A21: 8
A22: 9
A24: Claim-by-claim review
A25: Claim ID | B25: Claim from answer | C25: Cited document | D25: Expert verdict | E25: Cited passage | F25: Required fix / comment
A26: 1
A27: 2
A28: 3
A29: 4
A30: 5
A31: 6
A32: 7
A33: 8
A34: 9
A36: Final expert verdict
A37: Reviewer
A38: Is the answer acceptable?
A39: Overall comment / required fixes
A40: Review completed?
A69: Original source notes
A70: WAB notes
A71: Reviewer notes from question approval

Sheet Q06
A1: Q06 — Expert Review
A2: Question metadata
A3: Question ID | B3: 6
A4: Topic | B4: Food delivery — potential competition
A5: Scope | B5: UK
A6: Original reviewer | B6: Carolina
A7: Original status | B7: Approved
A8: Question | B8: Potential competition and re-entry — where the acquirer is not active in the UK, how has the CMA treated entry or re-entry absent the merger?
A9: Generated answer
A10: Paste the generated answer here.
A11: Run ID | C11: Run date
A12: Retrieval set review
A13: Rank | B13: Document name | C13: Document class | D13: Jurisdiction | E13: URL / Document ID | F13: Required source? | G13: Expert verdict | H13: Notes
A14: 1
A15: 2
A16: 3
A17: 4
A18: 5
A19: 6
A20: 7
A21: 8
A22: 9
A24: Claim-by-claim review
A25: Claim ID | B25: Claim from answer | C25: Cited document | D25: Expert verdict | E25: Cited passage | F25: Required fix / comment
A26: 1
A27: 2
A28: 3
A29: 4
A30: 5
A31: 6
A32: 7
A33: 8
A34: 9
A36: Final expert verdict
A37: Reviewer
A38: Is the answer acceptable?
A39: Overall comment / required fixes
A40: Review completed?
A69: Original source notes
A70: WAB notes
A71: Reviewer notes from question approval

Sheet Q07
A1: Q07 — Expert Review
A2: Question metadata
A3: Question ID | B3: 7
A4: Topic | B4: Food delivery — no-poach agreements
A5: Scope | B5: EU
A6: Original reviewer | B6: Carolina
A7: Original status | B7: Approved
A8: Question | B8: No-poach agreements under Article 101 — can a reciprocal agreement not to hire each other's staff infringe Article 101, and what is the leading precedent and fine?
A9: Generated answer
A10: Paste the generated answer here.
A11: Run ID | C11: Run date
A12: Retrieval set review
A13: Rank | B13: Document name | C13: Document class | D13: Jurisdiction | E13: URL / Document ID | F13: Required source? | G13: Expert verdict | H13: Notes
A14: 1
A15: 2
A16: 3
A17: 4
A18: 5
A19: 6
A20: 7
A21: 8
A22: 9
A24: Claim-by-claim review
A25: Claim ID | B25: Claim from answer | C25: Cited document | D25: Expert verdict | E25: Cited passage | F25: Required fix / comment
A26: 1
A27: 2
A28: 3
A29: 4
A30: 5
A31: 6
A32: 7
A33: 8
A34: 9
A36: Final expert verdict
A37: Reviewer
A38: Is the answer acceptable?
A39: Overall comment / required fixes
A40: Review completed?
A69: Original source notes
A70: WAB notes
A71: Reviewer notes from question approval

Sheet Q08
A1: Q08 — Expert Review
A2: Question metadata
A3: Question ID | B3: 8
A4: Topic | B4: Food delivery — remedies
A5: Scope | B5: EU + UK + ES
A6: Original reviewer | B6: Carolina
A7: Original status | B7: Approved
A8: Question | B8: Remedies in food-delivery mergers — which European reviews ended in remedies or commitments, and what did they look like?
A9: Generated answer
A10: Paste the generated answer here.
A11: Run ID | C11: Run date
A12: Retrieval set review
A13: Rank | B13: Document name | C13: Document class | D13: Jurisdiction | E13: URL / Document ID | F13: Required source? | G13: Expert verdict | H13: Notes
A14: 1
A15: 2
A16: 3
A17: 4
A18: 5
A19: 6
A20: 7
A21: 8
A22: 9
A24: Claim-by-claim review
A25: Claim ID | B25: Claim from answer | C25: Cited document | D25: Expert verdict | E25: Cited passage | F25: Required fix / comment
A26: 1
A27: 2
A28: 3
A29: 4
A30: 5
A31: 6
A32: 7
A33: 8
A34: 9
A36: Final expert verdict
A37: Reviewer
A38: Is the answer acceptable?
A39: Overall comment / required fixes
A40: Review completed?
A69: Original source notes
A70: WAB notes
A71: Reviewer notes from question approval

Sheet Q09
A1: Q09 — Expert Review
A2: Question metadata
A3: Question ID | B3: 9
A4: Topic | B4: Food delivery — Spanish practice
A5: Scope | B5: ES
A6: Original reviewer | B6: Carolina
A7: Original status | B7: Approved
A8: Question | B8: The Spanish (CNMC) food-delivery reviews — what is the CNMC's decisional practice, how many cases, and how were they resolved?
A9: Generated answer
A10: Paste the generated answer here.
A11: Run ID | C11: Run date
A12: Retrieval set review
A13: Rank | B13: Document name | C13: Document class | D13: Jurisdiction | E13: URL / Document ID | F13: Required source? | G13: Expert verdict | H13: Notes
A14: 1
A15: 2
A16: 3
A17: 4
A18: 5
A19: 6
A20: 7
A21: 8
A22: 9
A24: Claim-by-claim review
A25: Claim ID | B25: Claim from answer | C25: Cited document | D25: Expert verdict | E25: Cited passage | F25: Required fix / comment
A26: 1
A27: 2
A28: 3
A29: 4
A30: 5
A31: 6
A32: 7
A33: 8
A34: 9
A36: Final expert verdict
A37: Reviewer
A38: Is the answer acceptable?
A39: Overall comment / required fixes
A40: Review completed?
A69: Original source notes
A70: WAB notes
A71: Reviewer notes from question approval

Sheet Q10
A1: Q10 — Expert Review
A2: Question metadata
A3: Question ID | B3: 10
A4: Topic | B4: Food delivery — minority shareholdings
A5: Scope | B5: EU + UK
A6: Original reviewer | B6: Carolina
A7: Original status | B7: Approved
A8: Question | B8: Material influence and minority shareholdings — on what basis did the CMA take jurisdiction over a c.16% stake, and how else have authorities treated minority shareholdings in merger control?
A9: Generated answer
A10: Paste the generated answer here.
A11: Run ID | C11: Run date
A12: Retrieval set review
A13: Rank | B13: Document name | C13: Document class | D13: Jurisdiction | E13: URL / Document ID | F13: Required source? | G13: Expert verdict | H13: Notes
A14: 1
A15: 2
A16: 3
A17: 4
A18: 5
A19: 6
A20: 7
A21: 8
A22: 9
A24: Claim-by-claim review
A25: Claim ID | B25: Claim from answer | C25: Cited document | D25: Expert verdict | E25: Cited passage | F25: Required fix / comment
A26: 1
A27: 2
A28: 3
A29: 4
A30: 5
A31: 6
A32: 7
A33: 8
A34: 9
A36: Final expert verdict
A37: Reviewer
A38: Is the answer acceptable?
A39: Overall comment / required fixes
A40: Review completed?
A69: Original source notes
A70: WAB notes
A71: Reviewer notes from question approval

Sheet Q11
A1: Q11 — Expert Review
A2: Question metadata
A3: Question ID | B3: 11
A4: Topic | B4: Food delivery — evolution of practice
A5: Scope | B5: EU + UK + ES
A6: Original reviewer | B6: Carolina
A7: Original status | B7: Approved
A8: Question | B8: The evolution of European food-delivery merger control, 2017–2025 — how has practice evolved from the first national marketplace consolidations to the recent Commission decisions?
A9: Generated answer
A10: Paste the generated answer here.
A11: Run ID | C11: Run date
A12: Retrieval set review
A13: Rank | B13: Document name | C13: Document class | D13: Jurisdiction | E13: URL / Document ID | F13: Required source? | G13: Expert verdict | H13: Notes
A14: 1
A15: 2
A16: 3
A17: 4
A18: 5
A19: 6
A20: 7
A21: 8
A22: 9
A24: Claim-by-claim review
A25: Claim ID | B25: Claim from answer | C25: Cited document | D25: Expert verdict | E25: Cited passage | F25: Required fix / comment
A26: 1
A27: 2
A28: 3
A29: 4
A30: 5
A31: 6
A32: 7
A33: 8
A34: 9
A36: Final expert verdict
A37: Reviewer
A38: Is the answer acceptable?
A39: Overall comment / required fixes
A40: Review completed?
A69: Original source notes
A70: WAB notes
A71: Reviewer notes from question approval

Sheet Q12
A1: Q12 — Expert Review
A2: Question metadata
A3: Question ID | B3: 12
A4: Topic | B4: Dawn raids — legal professional privilege
A5: Scope | B5: France
A6: Original reviewer | B6: Carolina
A7: Original status | B7: Approved
A8: Question | B8: At what stage is attorney-client privilege breached during a dawn raid — when the inspector reads the document, or only when it is later used?
A9: Generated answer
A10: Paste the generated answer here.
A11: Run ID | C11: Run date
A12: Retrieval set review
A13: Rank | B13: Document name | C13: Document class | D13: Jurisdiction | E13: URL / Document ID | F13: Required source? | G13: Expert verdict | H13: Notes
A14: 1
A15: 2
A16: 3
A17: 4
A18: 5
A19: 6
A20: 7
A21: 8
A22: 9
A24: Claim-by-claim review
A25: Claim ID | B25: Claim from answer | C25: Cited document | D25: Expert verdict | E25: Cited passage | F25: Required fix / comment
A26: 1
A27: 2
A28: 3
A29: 4
A30: 5
A31: 6
A32: 7
A33: 8
A34: 9
A36: Final expert verdict
A37: Reviewer
A38: Is the answer acceptable?
A39: Overall comment / required fixes
A40: Review completed?
A69: Original source notes
A70: WAB notes | B70: Your wording, unchanged. We had drafted a wider French question instead — how correspondence between a company and its lawyer is protected, how a seizure of it is contested, and whether the remedy is return, destruction or exclusion from the file. We put yours back because it is sharper. Tell us if you want the wider version, or both.
A71: Reviewer notes from question approval | B71: I would keep both, the one we provided and this one too, which i like as because it relies more on the general principles regarding the definition and applicability of legal professional privilege as a legal concept.

Sheet Q13
A1: Q13 — Expert Review
A2: Question metadata
A3: Question ID | B3: 13
A4: Topic | B4: Dawn raids — personal data
A5: Scope | B5: France
A6: Original reviewer | B6: Carolina
A7: Original status | B7: Approved
A8: Question | B8: Under what conditions must the Competition Authority protect personal data during a dawn raid? Does the GDPR apply? Must documents be sealed on request?
A9: Generated answer
A10: Paste the generated answer here.
A11: Run ID | C11: Run date
A12: Retrieval set review
A13: Rank | B13: Document name | C13: Document class | D13: Jurisdiction | E13: URL / Document ID | F13: Required source? | G13: Expert verdict | H13: Notes
A14: 1
A15: 2
A16: 3
A17: 4
A18: 5
A19: 6
A20: 7
A21: 8
A22: 9
A24: Claim-by-claim review
A25: Claim ID | B25: Claim from answer | C25: Cited document | D25: Expert verdict | E25: Cited passage | F25: Required fix / comment
A26: 1
A27: 2
A28: 3
A29: 4
A30: 5
A31: 6
A32: 7
A33: 8
A34: 9
A36: Final expert verdict
A37: Reviewer
A38: Is the answer acceptable?
A39: Overall comment / required fixes
A40: Review completed?
A69: Original source notes
A70: WAB notes | B70: Your wording, unchanged.
A71: Reviewer notes from question approval | B71: agreed.

Sheet Q14
A1: Q14 — Expert Review
A2: Question metadata
A3: Question ID | B3: 14
A4: Topic | B4: Dawn raids — challenging a seizure
A5: Scope | B5: France
A6: Original reviewer | B6: Carolina
A7: Original status | B7: Approved
A8: Question | B8: After a dawn raid, can the President of the Court of Appeal be seized in interim proceedings to urgently resolve attorney-client privilege disputes? On what legal basis and under what conditions?
A9: Generated answer
A10: Paste the generated answer here.
A11: Run ID | C11: Run date
A12: Retrieval set review
A13: Rank | B13: Document name | C13: Document class | D13: Jurisdiction | E13: URL / Document ID | F13: Required source? | G13: Expert verdict | H13: Notes
A14: 1
A15: 2
A16: 3
A17: 4
A18: 5
A19: 6
A20: 7
A21: 8
A22: 9
A24: Claim-by-claim review
A25: Claim ID | B25: Claim from answer | C25: Cited document | D25: Expert verdict | E25: Cited passage | F25: Required fix / comment
A26: 1
A27: 2
A28: 3
A29: 4
A30: 5
A31: 6
A32: 7
A33: 8
A34: 9
A36: Final expert verdict
A37: Reviewer
A38: Is the answer acceptable?
A39: Overall comment / required fixes
A40: Review completed?
A69: Original source notes
A70: WAB notes | B70: Your wording, unchanged. One point to check: we understand Article L.450-4 of the Code de commerce to designate the FIRST President of the Court of Appeal (premier président), not the President. We have left your wording and are raising it rather than correcting it.
A71: Reviewer notes from question approval | B71: nothing to be changed.

Sheet Q15
A1: Q15 — Expert Review
A2: Question metadata
A3: Question ID | B3: 15
A4: Topic | B4: Dawn raids — legal professional privilege
A5: Scope | B5: EU
A6: Original reviewer | B6: Carolina
A7: Original status | B7: Approved
A8: Question | B8: At what stage is attorney-client privilege breached during a European Commission inspection under Article 20 of Regulation 1/2003 — when the inspector reads the document, or only when the Commission later uses it?
A9: Generated answer
A10: Paste the generated answer here.
A11: Run ID | C11: Run date
A12: Retrieval set review
A13: Rank | B13: Document name | C13: Document class | D13: Jurisdiction | E13: URL / Document ID | F13: Required source? | G13: Expert verdict | H13: Notes
A14: 1 | B14: inspections-eu-law-2nd--3_chapter_1_-_inspections_upon_decision_regulation_1_2003_article_20_4.md | C14: Book (Livre) | E14: d28b1d20-a2c6-425f-a401-498eab28d744
A15: 2 | B15: eu-antitrust-enforcement--14_xiii_legal_professional_privilege_in_eu_antitrust_enforcement_law_policy_and_procedure.md | C15: Book (Livre) | E15: 751159c7-e8b0-4cba-8ae1-5652058d7980 | H15: Cited in answer: YES
A16: 3 | B16: 62020CC0682.md | C16: Article (Review) | D16: EU | E16: f6fc977b-8c8d-467b-a5f7-04beb77f1b93 | H16: Cited in answer: YES
A17: 4 | B17: 62017TJ0249.md | C17: Court Decision | D17: EU | E17: dbf7bda8-39fa-4eb5-a6e2-f02b0787cb54
A18: 5 | B18: eu-antitrust-enforcement--11_x_fundamental_procedural_rights_and_effective_enforcement_of_articles_101_and_102_tfeu_in_the_european_competition_network.md | C18: Book (Livre) | E18: 44d971b2-9615-45f5-94c3-342633964481
A19: 6 | B19: 62018CJ0403.md | C19: Court Decision | D19: EU | E19: 5b155c4b-0345-4afa-8dee-d56351895c8f
A20: 7 | B20: eu-antitrust-enforcement--12_xi_the_role_of_the_hearing_officer_in_antitrust_proceedings_before_the_european_commission.md | C20: Book (Livre) | E20: 27d55d8c-5b59-43c1-8576-7a718bd009d4
A21: 8 | B21: 121144.md | C21: Bulletin article | E21: 9f96a5ff-2537-45cd-a34f-b0f82767f132
A22: 9 | B22: 62020CJ0693.md | C22: Court Decision | D22: EU | E22: 74ccf3f4-5d27-4c74-9208-62829cc5bcf1
A23: 10 | B23: 62023TJ1097.md | C23: Court Decision | D23: EU | E23: 17ecc724-b05f-4f42-9a28-b1282ba34327
A24: 11 | B24: 67860.md | C24: Bulletin article | E24: f3b54f3e-52e4-4232-8e7a-129fe9239fec
A25: 12 | B25: 62007CJ0550.md | C25: Court Decision | D25: EU | E25: 77a4dd19-04ce-410f-ba8e-9998f2902880 | H25: Cited in answer: YES
A26: 13 | B26: 62020CC0682.md | C26: Bulletin article | D26: EU | E26: 4228e89d-bc15-4a00-9ed7-bd703f8ec05a | H26: Cited in answer: YES
A27: 14 | B27: 61979CJ0155.md | C27: Court Decision | D27: EU | E27: 5353da9e-012f-4409-bde2-d1256386ccb7 | H27: Cited in answer: YES
A28: 15 | B28: AT.40588-DEC_3BB0CA7D-3722-43A5-85E8-BF3CA6EB441B_-ATT6339.md | C28: Regulatory Decision | D28: EU | E28: 9d692a02-4ebd-41a5-ae70-af412829d83f
A29: 16 | B29: 62023TJ1097.md | C29: Court Decision | D29: EU | E29: 19135079-d5db-4c66-b2d1-4bc35297af23
A30: 17 | B30: 91835.md | C30: Article (Review) | E30: f6ec0179-d152-4059-9a3f-81d669d422b0
A31: 18 | B31: 62003TJ0125.md | C31: Court Decision | D31: EU | E31: a8c1d5f4-d4fb-4365-bf78-e327971748f9 | H31: Cited in answer: YES
A32: 19 | B32: 62020CJ0682.md | C32: Court Decision | D32: EU | E32: 408cfe67-7fe4-45a8-9c3e-de39d86d56cb
A33: 20 | B33: 62020CJ0690.md | C33: Court Decision | D33: EU | E33: 75c2da13-00ee-43b2-baa4-a6f2e5a71e73
A34: 21 | B34: compendium-eu-competition-law--p20.md | C34: Legislation | E34: 4051fc69-a489-4b05-95ab-16bd651b54f1
A35: 22 | B35: AT.37990-DEC_D1115C27-9B1D-401A-A930-8895EBEFC8F6_-ATT3581.md | C35: Regulatory Decision | D35: EU | E35: b320e5cc-5605-4cb5-9f85-f6decae603d2
A36: 23 | B36: 96586.md | C36: Article (Review) | E36: 4cb5c154-4d3a-46c3-8bca-8f09c7e6c562
A37: 24 | B37: 41554.md | C37: Bulletin article | E37: 7ac322df-dba5-454b-a0e6-0bff2167a703
A38: 25 | B38: 62020TJ0451.md | C38: Court Decision | D38: EU | E38: 48c42881-8462-4197-885e-35fd7e697950
A39: 26 | B39: judicial-review-competition-cases--6_european_union_-_judicial_review_of_inspection_decisions.md | C39: Article (Review) | E39: 21a3ec2e-1c42-4307-ab97-e45011d6660a
A40: 27 | B40: AT.38589-DEC_3E35814B-057B-4DBA-846C-7E857FD065EA_-ATT4669.md | C40: Regulatory Decision | D40: EU | E40: 4c1b86f8-9f04-46e8-acde-128a983395c5
A41: 28 | B41: 62009TJ0135.md | C41: Court Decision | D41: EU | E41: 10418f10-8b6f-4bcc-adf6-39e168b49440
A42: 29 | B42: eu-antitrust-enforcement--15_xiv_procedural_rights_and_obligations_of_third_parties_in_antitrust_investigations_and_proceedings_by_the_european_commission.md | C42: Book (Livre) | E42: b2429dd2-ef75-4f34-8bf2-95b08c3a4de5
A43: 30 | B43: 62020TJ0452.md | C43: Court Decision | D43: EU | E43: b2ad17a9-5061-42da-938b-6bc18c4c1e54
A44: 31 | B44: m10149.md | C44: Regulatory Decision | D44: EU | E44: 440344d8-5df6-4302-a894-bc58447b2a18
A45: 32 | B45: AT.39612-DEC_5C6ACA13-ABDB-424E-BCCD-DAD64547B586_-ATT12422.md | C45: Regulatory Decision | D45: EU | E45: 721711b5-0be0-4aed-9af6-c718c0f75e94
A46: 33 | B46: 79963.md | C46: Article (Review) | E46: b0c5f913-948d-4dcc-9ea4-98f6136ca5a7
A47: 34 | B47: competition-case-law-digest-5th--p09.md | C47: Book (Livre) | E47: 2f0afdb0-43c8-41b3-99e2-c3003ab906c1
A48: 35 | B48: 65144.md | C48: Bulletin article | E48: ce8f9970-7bea-4576-a4de-4bd06551adb1
A49: 36 | B49: eu-antitrust-enforcement--10_ix_the_compatibility_with_fundamental_rights_of_the_eu_antitrust_enforcement_system_in_which_the_european_commission_acts_both_as_investigator_and_as_first_instance_decision_maker.md | C49: Article (Review) | E49: 2c996db6-dd0f-46f5-be34-12be8f73b817
A50: 37 | B50: AT.39685-DEC_B33871A4-85CF-4460-AF10-A316F0FCD1B3_-ATT1976.md | C50: Regulatory Decision | D50: EU | E50: f4c38de6-b0b1-4d43-bba1-95b9f50b711c
A51: 38 | B51: competition-inspections-25-jurisdictions--23_sweden.md | C51: Article (Review) | E51: dcf6ff3a-fc96-4095-bbc3-ecdd4afa4808
A52: 39 | B52: competition-inspections-25-jurisdictions--16_netherlands.md | C52: Article (Review) | E52: bd91d513-0a9b-4001-afec-498af0c4e9c4
A53: 40 | B53: eu-antitrust-enforcement--17_xvi_re_adoption_by_the_european_commission_of_cartel_decisions_annulled_on_procedural_grounds_by_the_eu_courts.md | C53: Article (Review) | E53: 71ba5e7f-b51e-4068-b010-b7e7f422add9
A54: 41 | B54: eu-antitrust-enforcement--16_xv_publication_of_antitrust_decisions_of_the_european_commission.md | C54: Book (Livre) | E54: 3c9799ff-7e91-4daf-9fef-671444f16757
A55: 42 | B55: 62010TJ0027.md | C55: Court Decision | D55: EU | E55: bc02167d-8c4b-4b56-831c-f9c775215394
A56: 43 | B56: 62010TJ0047.md | C56: Court Decision | D56: EU | E56: 3cc76128-e075-4858-8344-bb863faf33fb
A57: 44 | B57: 62023TJ1119.md | C57: Court Decision | D57: EU | E57: ce0e3df2-f4ea-4345-a297-e54a4f805a9f
A58: 45 | B58: judicial-review-competition-cases--7_european_union_-_are_there_any_limits_to_unlimited_jurisdiction_judicial_review_of_commission_discretion_in_setting_fines_for_breaches_of_eu_competition_rules.md | C58: Article (Review) | E58: db161723-dcab-4880-a411-5ede0c406c3a
A59: 46 | B59: 112075.md | C59: Bulletin article | E59: d2417411-7570-40c0-8fde-72b358d5c65a
A60: 47 | B60: competition-inspections-25-jurisdictions--7_european_union.md | C60: Article (Review) | E60: 1c2fa592-34f0-4656-96c2-024c5ea88b1e
A61: 48 | B61: eu-antitrust-enforcement--13_xii_the_oral_hearing_in_antitrust_proceedings_before_the_european_commission.md | C61: Article (Review) | E61: 8edbd753-7757-4163-9662-1b5feeeadeb4
A62: 49 | B62: 129921.md | C62: Article (Review) | E62: f778c4be-e8ad-469a-a0b4-810de049896e | H62: Cited in answer: YES
A63: 50 | B63: 81215.md | C63: Article (Review) | E63: 1326c749-4c6d-42ec-974e-b228dd1bf722
A64: 51 | B64: 62018CC0606.md | C64: Article (Review) | D64: EU | E64: 0655b4ec-4821-4b46-91b6-b6ddaebd8d5d
A65: 52 | B65: competition-case-law-digest-5th--p10.md | C65: Book (Livre) | E65: 65e060cb-bdeb-413d-b4e8-b9ffe0ed3995
A66: 53 | B66: 131823.md | C66: Bulletin article | E66: 9a53486d-c10b-4126-a9f0-2a80c4e4e2d2
A67: 54 | B67: 95849-3360-inspections-the-court-of-justice-of-the-european-union-gives-the-commission.md | C67: Bulletin article | E67: afe07022-9e8e-4270-a8d4-2c0aaa70652f
A68: 55 | B68: 125471-20-dawn-raids-the-general-court-upholds-the-european-commissions-overall-assessm.md | C68: Bulletin article | E68: e97ed81a-60ca-4112-9207-21a8613078bd
A69: 56 | B69: 62018CJ0606.md | C69: Court Decision | D69: EU | E69: 2d074327-045b-484e-8bbc-1a0f9c7ed660
A70: 57 | B70: 89462-10-dawn-raids-under-challenge-due-process-aspects-on-the-european-commissions-da.md | C70: Book (Livre) | E70: d99f40e5-7676-4078-8409-e9b39b24278d
A71: 58 | B71: 88314-25-dawn-raids-under-challenge-due-process-aspects-on-the-european-commissions-da.md | C71: Book (Livre) | E71: 5b9b4609-8335-4feb-aca4-61b1b39072de
A72: 59 | B72: 120985.md | C72: Bulletin article | E72: 8743ed4a-36f8-448f-9aa9-ccf29abfc760
A73: 60 | B73: 62023TJ0263.md | C73: Court Decision | D73: EU | E73: 16791fea-a958-4950-92a6-5a1b65fb3a04
A74: 61 | B74: AT.39482-DEC_73751038-699C-4409-B44D-C84DA7B4B25F_-ATT3130.md | C74: Regulatory Decision | D74: EU | E74: 818ed882-d0ec-470c-9150-e05c4b7c6fc9
A75: 62 | B75: AT.39612-DEC_5C6ACA13-ABDB-424E-BCCD-DAD64547B586_-ATT12448.md | C75: Regulatory Decision | D75: EU | E75: 1a9afee4-0461-4462-b812-f357beb0d2ba
A76: 63 | B76: 62020TO0451(01).md | C76: Court Decision | D76: EU | E76: b261ed51-2a85-4d85-a20a-92143a7cd6a5
A77: 64 | B77: 32019R2175.md | C77: Legislation | D77: EU | E77: c31e89e5-5dcc-4313-b8ac-62706d7adbc8
A78: 65 | B78: 62011TJ0289.md | C78: Court Decision | D78: EU | E78: 7ecb1eda-828c-4ed1-831c-9ba3cd309425
A79: 66 | B79: 62017TJ0255.md | C79: Court Decision | D79: EU | E79: 23c88310-f2d4-4b6b-8829-eaeec8aab044
A80: 67 | B80: ca-19-9589-6253cdd2bd3db21cbdd949c4.md | C80: Court Decision | D80: France | E80: 2d3b47f6-ca93-43a9-a14a-151e329548f1
A81: 68 | B81: 32022R2065.md | C81: Legislation | D81: EU | E81: bc43d714-c2f6-4d10-8f9b-c76bb8feacc9
A82: 69 | B82: 62014CC0247.md | C82: Article (Review) | D82: EU | E82: 9fefd6d8-a7ab-424b-a847-9a604ddaaf0f
A83: 70 | B83: 50285.md | C83: Bulletin article | E83: f17418b6-489e-4049-92f0-b9ce2b58968f
A84: 71 | B84: AT.39226-DEC_0F3A3B18-111D-43A8-836E-D0A7EA9CD4E1_-ATT8310.md | C84: Regulatory Decision | D84: EU | E84: 530c713d-168b-4e73-828b-429d06bf028f
A85: 72 | B85: AT.39686-DEC_521D2B6D-9DBD-4072-ADCF-8A8F61DE7124_-ATT4072.md | D85: EU | E85: c9e9d07f-8e70-4043-a6b0-4878b37605bf
A86: 73 | B86: 82445.md | C86: Article (Review) | E86: 1be45df1-87e1-4ba2-bdd9-76e5fe184f97
A87: 74 | B87: 62014TJ0701.md | C87: Court Decision | D87: EU | E87: 82bcdb25-439b-4260-9d81-4848737b9274
A88: 75 | B88: AT.39633-DEC_62D4718F-BD2F-45AF-AFDC-5E507C178E5D_-ATT2636.md | C88: Regulatory Decision | D88: EU | E88: 1b324af0-06b4-4824-b7a9-b8fda722b228
A89: 76 | B89: 62020TO0452(01).md | C89: Court Decision | D89: EU | E89: 2768689e-df78-453e-8a77-732820fda1c8
A90: 77 | B90: 62011TJ0296.md | C90: Court Decision | D90: EU | E90: 9bd983cd-32e8-43eb-bad0-dc190b31c9d2
A91: 78 | B91: 62013CC0037.md | C91: Bulletin article | D91: EU | E91: 632273f6-990f-4cc6-85ff-77f86f45c537
A92: 79 | B92: 22157.md | C92: Bulletin article | E92: e7eb6518-b108-4b38-8eb8-fcfd3533d624
A93: 80 | B93: inspections-eu-law-2nd--4_chapter_2_-_inspections_upon_authorisation_regulation_1_2003_article_20_3.md | C93: Book (Livre) | E93: 303ee9d6-4f67-4e00-a80a-195318e324af
A94: 81 | B94: AT.39092-DEC_AF683DFA-81B0-4590-AC30-AF899F345B55_-ATT7226.md | C94: Regulatory Decision | D94: EU | E94: bebbf97a-c491-4421-9668-8ace73d43bd0
A95: 82 | B95: 57935-361-decisions-adopted-during-an-inspection-the-general-court-reminds-the-commiss.md | C95: Bulletin article | E95: 882aa354-e6cf-464a-b1e2-9486b1cca48f
A96: 83 | B96: 62014TJ0475.md | C96: Court Decision | D96: EU | E96: cba40d0a-c143-4bc9-af97-af13ef20db3a
A97: 84 | B97: 86251-3110-exchanges-of-in-house-lawyers-the-first-president-of-the-paris-court-of-app.md | C97: Bulletin article | E97: 6ab55554-c702-44a9-8efc-1690b4bc016e
A98: 85 | B98: 62014TJ0705.md | C98: Court Decision | D98: EU | E98: a795bd44-0811-455c-9d8e-6e9c125b497b
A99: 86 | B99: 45408-the-eu-court-of-justice-holds-that-in-house-lawyers-are-not-protected-by-legal-p.md | C99: Bulletin article | E99: 7af38e62-27f7-4570-be20-5b4f80937e5e
A100: 87 | B100: 62011TJ0297.md | C100: Court Decision | D100: EU | E100: b5e94e7b-4cfc-4447-a323-0eaa92692c11
...

Sheet Q16
A1: Q16 — Expert Review
A2: Question metadata
A3: Question ID | B3: 16
A4: Topic | B4: Dawn raids — personal data
A5: Scope | B5: EU
A6: Original reviewer | B6: Carolina
A7: Original status | B7: Approved
A8: Question | B8: Under what conditions must the European Commission protect personal data during an inspection? Does the GDPR apply? Must documents be sealed on request?
A9: Generated answer
A10: Paste the generated answer here.
A11: Run ID | C11: Run date
A12: Retrieval set review
A13: Rank | B13: Document name | C13: Document class | D13: Jurisdiction | E13: URL / Document ID | F13: Required source? | G13: Expert verdict | H13: Notes
A14: 1 | B14: inspections-eu-law-2nd--3_chapter_1_-_inspections_upon_decision_regulation_1_2003_article_20_4.md | C14: Book (Livre) | E14: d28b1d20-a2c6-425f-a401-498eab28d744
A15: 2 | B15: 32018D1927.md | C15: Legislation | D15: EU | E15: 4b2f4063-4380-45e9-a0c5-38939bcc1d22 | H15: Cited in answer: YES
A16: 3 | B16: 62020TO0451(01).md | C16: Court Decision | D16: EU | E16: b261ed51-2a85-4d85-a20a-92143a7cd6a5 | H16: Cited in answer: YES
A17: 4 | B17: 62020TO0452(01).md | C17: Court Decision | D17: EU | E17: 2768689e-df78-453e-8a77-732820fda1c8
A18: 5 | B18: 62023TJ1097.md | C18: Court Decision | D18: EU | E18: 17ecc724-b05f-4f42-9a28-b1282ba34327
A19: 6 | B19: 62023TJ1119.md | C19: Court Decision | D19: EU | E19: ce0e3df2-f4ea-4345-a297-e54a4f805a9f
A20: 7 | B20: eu-antitrust-enforcement--15_xiv_procedural_rights_and_obligations_of_third_parties_in_antitrust_investigations_and_proceedings_by_the_european_commission.md | C20: Book (Livre) | E20: b2429dd2-ef75-4f34-8bf2-95b08c3a4de5
A21: 8 | B21: 128250-35-dawn-raids-the-general-court-of-the-european-union-partially-upholds-the-lega.md | C21: Bulletin article | E21: e34c0e6d-2771-4073-8165-4a73eff42d4c
A22: 9 | B22: 62020TJ0451.md | C22: Court Decision | D22: EU | E22: 48c42881-8462-4197-885e-35fd7e697950
A23: 10 | B23: 97110-2850-inspection-the-general-court-of-the-european-union-partially-annuls-decisio.md | C23: Bulletin article | E23: 0ff86075-a215-4bce-ac53-21a9aa21cd71
A24: 11 | B24: 125471-20-dawn-raids-the-general-court-upholds-the-european-commissions-overall-assessm.md | C24: Bulletin article | E24: e97ed81a-60ca-4112-9207-21a8613078bd
A25: 12 | B25: 62020TJ0452.md | C25: Court Decision | D25: EU | E25: b2ad17a9-5061-42da-938b-6bc18c4c1e54
A26: 13 | B26: 131688-30-inspections-the-general-court-of-the-european-union-upholds-the-european-comm.md | C26: Bulletin article | E26: 7de191c9-0221-423b-b670-ef1e047a0196
A27: 14 | B27: 57935-361-decisions-adopted-during-an-inspection-the-general-court-reminds-the-commiss.md | C27: Bulletin article | E27: 882aa354-e6cf-464a-b1e2-9486b1cca48f
A28: 15 | B28: competition-inspections-25-jurisdictions--7_european_union.md | C28: Article (Review) | E28: 1c2fa592-34f0-4656-96c2-024c5ea88b1e | H28: Cited in answer: YES
A29: 16 | B29: 96586.md | C29: Article (Review) | E29: 4cb5c154-4d3a-46c3-8bca-8f09c7e6c562
A30: 17 | B30: eu-antitrust-enforcement--16_xv_publication_of_antitrust_decisions_of_the_european_commission.md | C30: Book (Livre) | E30: 3c9799ff-7e91-4daf-9fef-671444f16757
A31: 18 | B31: 32019D1862.md | C31: Legislation | D31: EU | E31: b5b6f4c2-f369-46e5-a382-72fbc8df883a
A32: 19 | B32: 32022R1925.md | C32: Legislation | D32: EU | E32: 2bb20ffc-93ba-4ba0-8872-0bbfc5b98609
A33: 20 | B33: 32024R1689.md | C33: Legislation | D33: EU | E33: d164805a-0886-4c4e-933f-d963ad9182ea
A34: 21 | B34: competition-case-law-digest-5th--p09.md | C34: Book (Livre) | E34: 2f0afdb0-43c8-41b3-99e2-c3003ab906c1
A35: 22 | B35: 103260-35-necessary-limits-to-the-commission-s-inspection-powers.md | C35: Article (Review) | E35: bef18b4b-bb03-49c0-a7aa-afed485ec5d2
A36: 23 | B36: 127929-the-eu-general-court-upholds-the-commissions-inspection-methodology-based-on-pub.md | C36: Bulletin article | E36: af2e8c94-00c3-40d4-8e35-233542ca536d
A37: 24 | B37: 32018R1725.md | C37: Legislation | D37: EU | E37: bc2299a1-c240-4a91-aa11-b5bd00c815b5
A38: 25 | B38: 32025R0327.md | C38: Legislation | D38: EU | E38: 10cab083-f284-482e-8d36-a5faf47762ab
A39: 26 | B39: 127186-20-inspection-the-general-court-of-the-european-union-considers-that-the-commiss.md | C39: Bulletin article | E39: 329bd68b-1104-4f5c-b636-e9925175dbc6
A40: 27 | B40: 62023TJ1097.md | C40: Court Decision | D40: EU | E40: 19135079-d5db-4c66-b2d1-4bc35297af23
A41: 28 | B41: AT.40684-ATT13405.md | D41: EU | E41: f845d2d5-a7e2-4ba9-b525-8aebbe7f3d30
A42: 29 | B42: compendium-eu-competition-law--p46.md | C42: Legislation | E42: 21d91f72-d429-4ad0-b9aa-f0efaffcf8b6
A43: 30 | B43: judicial-review-competition-cases--6_european_union_-_judicial_review_of_inspection_decisions.md | C43: Article (Review) | E43: 21a3ec2e-1c42-4307-ab97-e45011d6660a | H43: Cited in answer: YES
A44: 31 | B44: 32024R1143.md | C44: Legislation | D44: EU | E44: bf3097a4-74c1-4dbe-9a7f-5817030b37e8
A45: 32 | B45: 93706-0060-dawn-raids-advocate-general-kokott-calls-on-the-court-of-justice-to-uphold.md | C45: Bulletin article | E45: 42a1613c-b25b-476e-a3b4-e1cac9b5add2
A46: 33 | B46: eu-antitrust-enforcement--10_ix_the_compatibility_with_fundamental_rights_of_the_eu_antitrust_enforcement_system_in_which_the_european_commission_acts_both_as_investigator_and_as_first_instance_decision_maker.md | C46: Article (Review) | E46: 2c996db6-dd0f-46f5-be34-12be8f73b817
A47: 34 | B47: 32020Q1120(02).md | C47: Regulatory Decision | D47: EU | E47: 34a3789a-6b42-4095-93c7-459a976d1720
A48: 35 | B48: 32024R1781.md | C48: Legislation | D48: EU | E48: 67197a30-5dc9-4e78-9547-4ede1a401d06
A49: 36 | B49: 32026R1744.md | C49: Legislation | D49: EU | E49: efe52fd4-21cb-404d-929f-fbd3ee861b39
A50: 37 | B50: 32022R2560.md | C50: Legislation | D50: EU | E50: dfe609ca-a196-4dd1-8599-fb95fffa69e9
A51: 38 | B51: 32024R2847.md | C51: Legislation | D51: EU | E51: 8e023084-4728-49d6-b8d8-712e5184a680
A52: 39 | B52: 32020Q1113(01).md | C52: Regulatory Decision | D52: EU | E52: 2e360f32-5e39-401d-9774-af396dc6ca64
A53: 40 | B53: competition-inspections-25-jurisdictions--2_austria.md | C53: Article (Review) | E53: ec7e95f2-ae1b-4c2b-9635-0ae49e53ba19
A54: 41 | B54: 32024R0590.md | C54: Legislation | D54: EU | E54: 8b234b5b-05b4-4329-8070-eba71167091c
A55: 42 | B55: 62023CJ0258.md | C55: Court Decision | D55: EU | E55: 5aa970eb-b95b-47f7-848c-8251ba16e8bc
A56: 43 | B56: 32024R1938.md | C56: Legislation | D56: EU | E56: 196dcd68-9570-40a2-9ca3-475e4b1a9382
A57: 44 | B57: 129469.md | C57: Bulletin article | E57: 96fff51a-7108-4bec-abbc-3cd592bf0bb3
A58: 45 | B58: 107877.md | C58: Bulletin article | E58: 632bea47-be17-43c1-937e-08ba80d687d0
A59: 46 | B59: compendium-eu-competition-law--p19.md | C59: Book (Livre) | E59: 9bfde211-445b-477f-98b1-057754da3b52
A60: 47 | B60: compendium-eu-competition-law--p44.md | C60: Legislation | E60: a132148a-896b-4c54-b8ad-f38a24877738
A61: 48 | B61: 62014TJ0449.md | C61: Court Decision | D61: EU | E61: 2f594756-bc0a-4332-829f-e65319b3211c
A62: 49 | B62: eu-antitrust-enforcement--12_xi_the_role_of_the_hearing_officer_in_antitrust_proceedings_before_the_european_commission.md | C62: Book (Livre) | E62: 27d55d8c-5b59-43c1-8576-7a718bd009d4
A63: 50 | B63: eu-antitrust-enforcement--13_xii_the_oral_hearing_in_antitrust_proceedings_before_the_european_commission.md | C63: Article (Review) | E63: 8edbd753-7757-4163-9662-1b5feeeadeb4
A64: 51 | B64: 62018CJ0601.md | C64: Court Decision | D64: EU | E64: d94571df-d56d-45c1-a02e-834714984963
A65: 52 | B65: 32019D0802(01).md | C65: Legislation | D65: EU | E65: 2d00c1e9-a0ca-4279-8326-9cab88cc2394
A66: 53 | B66: 32023R0956.md | C66: Legislation | D66: EU | E66: 5407807d-3b1e-455f-8877-f8649979d874
A67: 54 | B67: 123082.md | C67: Bulletin article | E67: 18ab192b-10fe-48eb-95a5-bfcc61cd2c9d
A68: 55 | B68: 32018D1961.md | C68: Legislation | D68: EU | E68: c17962c2-b09e-4438-90aa-9d264db0ca9d | H68: Cited in answer: YES
A69: 56 | B69: 32019D0236.md | C69: Legislation | D69: EU | E69: 456bebae-b062-4aa4-bf2c-a9c9d4e4c653
A70: 57 | B70: 32024R0903.md | C70: Legislation | D70: EU | E70: a6d17cc5-caab-4a60-b65e-ea78e2b93d9c
A71: 58 | B71: 32018D1962.md | C71: Legislation | D71: EU | E71: 0a2b2c31-a865-44a0-b94f-c0ec4ee0d480
A72: 59 | B72: competition-inspections-25-jurisdictions--22_spain.md | C72: Article (Review) | E72: c612bb23-e93e-4e90-be30-4979d304f10e
A73: 60 | B73: 32022R2370.md | C73: Legislation | D73: EU | E73: 272a3c0d-fd88-47d2-a7a6-d98736410d5f
A74: 61 | B74: 32023R1543.md | C74: Legislation | D74: EU | E74: 18e9fb80-801f-4a5a-8690-2b6515bd2f86
A75: 62 | B75: 131258-the-eu-general-court-dismisses-an-action-challenging-commission-s-inspection-pow.md | C75: Bulletin article | E75: b5e40090-4f79-422a-997e-8eaa7a359c88
A76: 63 | B76: 62014CC0033.md | C76: Bulletin article | D76: EU | E76: 1dfad74b-fd57-47bb-bfab-18e86ff8d695
A77: 64 | B77: 32026R1881.md | C77: Legislation | D77: EU | E77: 40a473f4-06f8-499e-b320-b38c507d379f
A78: 65 | B78: 62009TJ0135.md | C78: Court Decision | D78: EU | E78: 10418f10-8b6f-4bcc-adf6-39e168b49440
A79: 66 | B79: 62023CC0070.md | C79: Bulletin article | D79: EU | E79: 2a493229-62c6-48e3-be4c-c06477e996fc
A80: 67 | B80: 129745.md | C80: Bulletin article | E80: d77ab0a2-b289-4ca9-981f-ff910bb4451b
A81: 68 | B81: m10262.md | C81: Regulatory Decision | D81: EU | E81: 371d0689-523b-4cfd-b127-c2e6980e3905
A82: 69 | B82: 32024R1183.md | C82: Legislation | D82: EU | E82: 89650652-fe90-42ae-a966-9c0b2e32ce85
A83: 70 | B83: judicial-review-competition-cases--7_european_union_-_are_there_any_limits_to_unlimited_jurisdiction_judicial_review_of_commission_discretion_in_setting_fines_for_breaches_of_eu_competition_rules.md | C83: Article (Review) | E83: db161723-dcab-4880-a411-5ede0c406c3a
A84: 71 | B84: 62015CO0523.md | C84: Court Decision | D84: EU | E84: b66f8514-c7d7-4322-9e3d-b85b2b24d658
A85: 72 | B85: competition-inspections-25-jurisdictions--10_germany.md | C85: Article (Review) | E85: 6e56030e-0de4-4565-963d-135aab5bd6f9
A86: 73 | B86: 32024R0573.md | C86: Legislation | D86: EU | E86: 56eae7f7-f179-4903-ab1e-31d7e0d44149
A87: 74 | B87: 32021R1232.md | C87: Legislation | D87: EU | E87: ed05fda7-fe84-4d6d-a820-541b65416c70
A88: 75 | B88: 32024L3101.md | C88: Legislation | D88: EU | E88: 3101f376-52b6-46ca-987f-5eeb77a44122
A89: 76 | B89: competition-case-law-digest-5th--p10.md | C89: Book (Livre) | E89: 65e060cb-bdeb-413d-b4e8-b9ffe0ed3995
A90: 77 | B90: AT.39793-DEC_029956AD-063E-4990-A487-E6815902F29D_-ATT489.md | D90: EU | E90: 23f85cf2-ba1b-4daf-b6bf-fd4ebdc0fc24
A91: 78 | B91: 62014CJ0033.md | C91: Court Decision | D91: EU | E91: 416f824d-8129-498b-86b2-330a30a0f664
A92: 79 | B92: 62020CC0376.md | C92: Court Decision | D92: EU | E92: cebd4962-06e0-43a6-ac13-b9cc9b05c9e7
A93: 80 | B93: 32019R2175.md | C93: Legislation | D93: EU | E93: c31e89e5-5dcc-4313-b8ac-62706d7adbc8
A94: 81 | B94: 32020Q1113(01).md | C94: Legislation | D94: EU | E94: 915950a6-17d1-4005-9100-aa942bbc9fe3
A95: 82 | B95: 62019CJ0563.md | C95: Court Decision | D95: EU | E95: e913f312-653c-49c1-b77a-4a633a3b4bfc
A96: 83 | B96: 62011TJ0479.md | C96: Court Decision | D96: EU | E96: 90b1484a-0221-4975-aa87-a00b163ae751
A97: 84 | B97: 32023R2854.md | C97: Legislation | D97: EU | E97: 2458f7d0-ad1b-49e0-9d6a-a57dc36ddd3e
A98: 85 | B98: 62018CJ0595.md | C98: Court Decision | D98: EU | E98: 9cef1570-4dfe-4218-9740-d8f6d239921b
A99: 86 | B99: 62021CJ0042.md | C99: Court Decision | D99: EU | E99: 80e27c6b-81ff-4712-8f72-2122091ffb8f
A100: 87 | B100: 62018CJ0312.md | C100: Court Decision | D100: EU | E100: 08dfceb2-3d7f-4ffa-9cfb-5b557d7cae14
...

Sheet Q17
A1: Q17 — Expert Review
A2: Question metadata
A3: Question ID | B3: 17
A4: Topic | B4: Dawn raids — challenging a seizure
A5: Scope | B5: EU
A6: Original reviewer | B6: Carolina
A7: Original status | B7: Approved
A8: Question | B8: What procedural avenues exist to challenge seizure of privileged documents after a European Commission inspection?
A9: Generated answer
A10: Paste the generated answer here.
A11: Run ID | C11: Run date
A12: Retrieval set review
A13: Rank | B13: Document name | C13: Document class | D13: Jurisdiction | E13: URL / Document ID | F13: Required source? | G13: Expert verdict | H13: Notes
A14: 1 | B14: inspections-eu-law-2nd--3_chapter_1_-_inspections_upon_decision_regulation_1_2003_article_20_4.md | C14: Book (Livre) | E14: d28b1d20-a2c6-425f-a401-498eab28d744
A15: 2 | B15: 62018CJ0403.md | C15: Court Decision | D15: EU | E15: 5b155c4b-0345-4afa-8dee-d56351895c8f
A16: 3 | B16: 129921.md | C16: Article (Review) | E16: f778c4be-e8ad-469a-a0b4-810de049896e
A17: 4 | B17: judicial-review-competition-cases--6_european_union_-_judicial_review_of_inspection_decisions.md | C17: Article (Review) | E17: 21a3ec2e-1c42-4307-ab97-e45011d6660a | H17: Cited in answer: YES
A18: 5 | B18: 62023TJ1097.md | C18: Court Decision | D18: EU | E18: 17ecc724-b05f-4f42-9a28-b1282ba34327
A19: 6 | B19: competition-case-law-digest-5th--p10.md | C19: Book (Livre) | E19: 65e060cb-bdeb-413d-b4e8-b9ffe0ed3995
A20: 7 | B20: 131688-30-inspections-the-general-court-of-the-european-union-upholds-the-european-comm.md | C20: Bulletin article | E20: 7de191c9-0221-423b-b670-ef1e047a0196
A21: 8 | B21: judicial-review-competition-cases--7_european_union_-_are_there_any_limits_to_unlimited_jurisdiction_judicial_review_of_commission_discretion_in_setting_fines_for_breaches_of_eu_competition_rules.md | C21: Article (Review) | E21: db161723-dcab-4880-a411-5ede0c406c3a
A22: 9 | B22: 62020CC0682.md | C22: Article (Review) | D22: EU | E22: f6fc977b-8c8d-467b-a5f7-04beb77f1b93
A23: 10 | B23: 128250-35-dawn-raids-the-general-court-of-the-european-union-partially-upholds-the-lega.md | C23: Bulletin article | E23: e34c0e6d-2771-4073-8165-4a73eff42d4c
A24: 11 | B24: 97110-2850-inspection-the-general-court-of-the-european-union-partially-annuls-decisio.md | C24: Bulletin article | E24: 0ff86075-a215-4bce-ac53-21a9aa21cd71
A25: 12 | B25: eu-antitrust-enforcement--12_xi_the_role_of_the_hearing_officer_in_antitrust_proceedings_before_the_european_commission.md | C25: Book (Livre) | E25: 27d55d8c-5b59-43c1-8576-7a718bd009d4 | H25: Cited in answer: YES
A26: 13 | B26: 91835.md | C26: Article (Review) | E26: f6ec0179-d152-4059-9a3f-81d669d422b0
A27: 14 | B27: 125471-20-dawn-raids-the-general-court-upholds-the-european-commissions-overall-assessm.md | C27: Bulletin article | E27: e97ed81a-60ca-4112-9207-21a8613078bd
A28: 15 | B28: 93706-0060-dawn-raids-advocate-general-kokott-calls-on-the-court-of-justice-to-uphold.md | C28: Bulletin article | E28: 42a1613c-b25b-476e-a3b4-e1cac9b5add2
A29: 16 | B29: 57935-361-decisions-adopted-during-an-inspection-the-general-court-reminds-the-commiss.md | C29: Bulletin article | E29: 882aa354-e6cf-464a-b1e2-9486b1cca48f
A30: 17 | B30: 62017TJ0249.md | C30: Court Decision | D30: EU | E30: dbf7bda8-39fa-4eb5-a6e2-f02b0787cb54
A31: 18 | B31: eu-antitrust-enforcement--15_xiv_procedural_rights_and_obligations_of_third_parties_in_antitrust_investigations_and_proceedings_by_the_european_commission.md | C31: Book (Livre) | E31: b2429dd2-ef75-4f34-8bf2-95b08c3a4de5
A32: 19 | B32: eu-antitrust-enforcement--14_xiii_legal_professional_privilege_in_eu_antitrust_enforcement_law_policy_and_procedure.md | C32: Book (Livre) | E32: 751159c7-e8b0-4cba-8ae1-5652058d7980 | H32: Cited in answer: YES
A33: 20 | B33: 62007CJ0550.md | C33: Court Decision | D33: EU | E33: 77a4dd19-04ce-410f-ba8e-9998f2902880 | H33: Cited in answer: YES
A34: 21 | B34: 121144.md | C34: Bulletin article | E34: 9f96a5ff-2537-45cd-a34f-b0f82767f132
A35: 22 | B35: 79963.md | C35: Article (Review) | E35: b0c5f913-948d-4dcc-9ea4-98f6136ca5a7
A36: 23 | B36: 96845-the-eu-court-of-justice-rules-that-legal-professional-privilege-does-not-cover-c.md | C36: Bulletin article | E36: ffcd147d-9482-4eff-8ba1-f4eafa068ea6
A37: 24 | B37: 62020CJ0682.md | C37: Court Decision | D37: EU | E37: 408cfe67-7fe4-45a8-9c3e-de39d86d56cb
A38: 25 | B38: 62023TJ1097.md | C38: Court Decision | D38: EU | E38: 19135079-d5db-4c66-b2d1-4bc35297af23
A39: 26 | B39: 62003TJ0125.md | C39: Court Decision | D39: EU | E39: a8c1d5f4-d4fb-4365-bf78-e327971748f9 | H39: Cited in answer: YES
A40: 27 | B40: 95849-3360-inspections-the-court-of-justice-of-the-european-union-gives-the-commission.md | C40: Bulletin article | E40: afe07022-9e8e-4270-a8d4-2c0aaa70652f
A41: 28 | B41: 112075.md | C41: Bulletin article | E41: d2417411-7570-40c0-8fde-72b358d5c65a
A42: 29 | B42: 65144.md | C42: Bulletin article | E42: ce8f9970-7bea-4576-a4de-4bd06551adb1
A43: 30 | B43: 127929-the-eu-general-court-upholds-the-commissions-inspection-methodology-based-on-pub.md | C43: Bulletin article | E43: af2e8c94-00c3-40d4-8e35-233542ca536d
A44: 31 | B44: 62014TJ0701.md | C44: Court Decision | D44: EU | E44: 82bcdb25-439b-4260-9d81-4848737b9274
A45: 32 | B45: 62020TJ0451.md | C45: Court Decision | D45: EU | E45: 48c42881-8462-4197-885e-35fd7e697950
A46: 33 | B46: 96586.md | C46: Article (Review) | E46: 4cb5c154-4d3a-46c3-8bca-8f09c7e6c562
A47: 34 | B47: 127186-20-inspection-the-general-court-of-the-european-union-considers-that-the-commiss.md | C47: Bulletin article | E47: 329bd68b-1104-4f5c-b636-e9925175dbc6
A48: 35 | B48: 50285.md | C48: Bulletin article | E48: f17418b6-489e-4049-92f0-b9ce2b58968f
A49: 36 | B49: 131823.md | C49: Bulletin article | E49: 9a53486d-c10b-4126-a9f0-2a80c4e4e2d2
A50: 37 | B50: 62020CC0682.md | C50: Bulletin article | D50: EU | E50: 4228e89d-bc15-4a00-9ed7-bd703f8ec05a
A51: 38 | B51: eu-antitrust-enforcement--10_ix_the_compatibility_with_fundamental_rights_of_the_eu_antitrust_enforcement_system_in_which_the_european_commission_acts_both_as_investigator_and_as_first_instance_decision_maker.md | C51: Article (Review) | E51: 2c996db6-dd0f-46f5-be34-12be8f73b817
A52: 39 | B52: compendium-eu-competition-law--p20.md | C52: Legislation | E52: 4051fc69-a489-4b05-95ab-16bd651b54f1
A53: 40 | B53: 62023TJ1119.md | C53: Court Decision | D53: EU | E53: ce0e3df2-f4ea-4345-a297-e54a4f805a9f
A54: 41 | B54: 62011TJ0289.md | C54: Court Decision | D54: EU | E54: 7ecb1eda-828c-4ed1-831c-9ba3cd309425
A55: 42 | B55: eu-antitrust-enforcement--11_x_fundamental_procedural_rights_and_effective_enforcement_of_articles_101_and_102_tfeu_in_the_european_competition_network.md | C55: Book (Livre) | E55: 44d971b2-9615-45f5-94c3-342633964481
A56: 43 | B56: 126520.md | C56: Bulletin article | E56: 12452b73-c2de-4280-8e98-eaf8be0779ba
A57: 44 | B57: 34843.md | C57: Bulletin article | D57: EU | E57: 76b0b83a-c3dd-4742-972b-2e257224bb41
A58: 45 | B58: 62014TJ0103.md | C58: Bulletin article | D58: EU | E58: 71644769-41f5-4da2-82b3-225292de42cb
A59: 46 | B59: 41021.md | C59: Bulletin article | E59: 7b2a2c23-bf06-4bb0-84da-b780b94a649c
A60: 47 | B60: 62014TJ0705.md | C60: Court Decision | D60: EU | E60: a795bd44-0811-455c-9d8e-6e9c125b497b
A61: 48 | B61: 120985.md | C61: Bulletin article | E61: 8743ed4a-36f8-448f-9aa9-ccf29abfc760
A62: 49 | B62: competition-case-law-digest-5th--p09.md | C62: Book (Livre) | E62: 2f0afdb0-43c8-41b3-99e2-c3003ab906c1
A63: 50 | B63: 72606.md | C63: Bulletin article | E63: 83edad42-3128-49b7-8bf5-14acc3d80b0c
A64: 51 | B64: 62020CJ0690.md | C64: Court Decision | D64: EU | E64: 75c2da13-00ee-43b2-baa4-a6f2e5a71e73
A65: 52 | B65: 62020CJ0693.md | C65: Court Decision | D65: EU | E65: 74ccf3f4-5d27-4c74-9208-62829cc5bcf1
A66: 53 | B66: 62014CJ0033.md | C66: Court Decision | D66: EU | E66: 416f824d-8129-498b-86b2-330a30a0f664
A67: 54 | B67: 74797.md | C67: Bulletin article | E67: 7aa935c3-59fb-4514-b6c3-08e34df697ff
A68: 55 | B68: 62018CJ0606.md | C68: Court Decision | D68: EU | E68: 2d074327-045b-484e-8bbc-1a0f9c7ed660
A69: 56 | B69: 130104-the-eu-commission-issues-a-policy-brief-on-legal-professional-privilege-in-compe.md | C69: Bulletin article | E69: 865b10b4-e120-4887-a566-4d32965a6785
A70: 57 | B70: 62022CJ0381.md | C70: Court Decision | D70: EU | E70: 71722674-1979-43b0-b9fb-45efc66190fe
A71: 58 | B71: eu-antitrust-enforcement--17_xvi_re_adoption_by_the_european_commission_of_cartel_decisions_annulled_on_procedural_grounds_by_the_eu_courts.md | C71: Article (Review) | E71: 71ba5e7f-b51e-4068-b010-b7e7f422add9
A72: 59 | B72: 97568-3340-investigation-the-court-of-justice-of-the-european-union-recognizes-the-eur.md | C72: Bulletin article | E72: 0a9a6620-916c-4d26-8e97-e91a08871183
A73: 60 | B73: 62015TJ0554.md | C73: Court Decision | D73: EU | E73: 92f51d45-f144-4968-8d1a-ac8a3c851e76
A74: 61 | B74: 86349.md | C74: Article (Review) | E74: 1cdd887b-6171-4114-a519-848559eecb91
A75: 62 | B75: 81215.md | C75: Article (Review) | E75: 1326c749-4c6d-42ec-974e-b228dd1bf722
A76: 63 | B76: 96910-3420-dawn-raids-the-court-of-justice-of-the-european-union-confirms-the-power-of.md | C76: Bulletin article | E76: a95ca40b-ceae-4436-8de6-a7a126b177e3
A77: 64 | B77: 62015TJ0274.md | C77: Court Decision | D77: EU | E77: d42f923b-c267-4df9-acb3-5abda361a0d6
A78: 65 | B78: 62017TJ0814.md | C78: Court Decision | D78: EU | E78: adbf5b23-5582-4b9c-82b5-519ddcf7bc67
A79: 66 | B79: 41554.md | C79: Bulletin article | E79: 7ac322df-dba5-454b-a0e6-0bff2167a703
A80: 67 | B80: 62023CO0138.md | C80: Court Decision | D80: EU | E80: 5abd9264-9c98-4239-bc5a-fd55ba2f17f6
A81: 68 | B81: 62020TJ0452.md | C81: Court Decision | D81: EU | E81: b2ad17a9-5061-42da-938b-6bc18c4c1e54
A82: 69 | B82: 62013CC0583.md | C82: Bulletin article | D82: EU | E82: 778d749c-48cb-405c-a58f-962dd3ceef0c
A83: 70 | B83: 96291-the-eu-court-of-justice-upholds-the-commissions-right-to-continue-inspection-at.md | C83: Bulletin article | E83: b5945681-864a-4470-b1bb-33978a2016ed
A84: 71 | B84: 62009TJ0135.md | C84: Court Decision | D84: EU | E84: 10418f10-8b6f-4bcc-adf6-39e168b49440
A85: 72 | B85: m10149.md | C85: Regulatory Decision | D85: EU | E85: 440344d8-5df6-4302-a894-bc58447b2a18
A86: 73 | B86: 62010TJ0027.md | C86: Court Decision | D86: EU | E86: bc02167d-8c4b-4b56-831c-f9c775215394
A87: 74 | B87: 62016CJ0611.md | C87: Court Decision | D87: EU | E87: 3db04834-4025-49ed-ae15-42e6d03d00b0
A88: 75 | B88: 93368-2520-investigations-the-court-of-justice-of-the-european-union-rules-that-an-act.md | C88: Bulletin article | E88: eb4af447-a8d7-4102-8c9b-20f8865d5fea
A89: 76 | B89: 103260-35-necessary-limits-to-the-commission-s-inspection-powers.md | C89: Article (Review) | E89: bef18b4b-bb03-49c0-a7aa-afed485ec5d2
A90: 77 | B90: 62013TJ0219.md | C90: Court Decision | D90: EU | E90: 87e5f9af-d387-4b32-bab1-26622717af34
A91: 78 | B91: 62018CJ0056.md | C91: Court Decision | D91: EU | E91: 4ba456ff-b77d-491b-bd04-801c30595086
A92: 79 | B92: 62021CJ0795.md | C92: Court Decision | D92: EU | E92: 5a4f02ec-c67d-4d7b-8f01-5d3edbe5e851
A93: 80 | B93: 62021CJ0792.md | C93: Court Decision | D93: EU | E93: 2a32ce23-298f-4d99-a76a-52b5f408feda
A94: 81 | B94: 62018CJ0601.md | C94: Court Decision | D94: EU | E94: d94571df-d56d-45c1-a02e-834714984963
A95: 82 | B95: 94920-2150-inquiries-the-court-of-justice-of-the-european-union-dismisses-appeals-brou.md | C95: Bulletin article | E95: e7e462f6-8d3e-4f46-92a9-57edcae44fd8
A96: 83 | B96: 62015CO0523.md | C96: Court Decision | D96: EU | E96: b66f8514-c7d7-4322-9e3d-b85b2b24d658
A97: 84 | B97: 62016CJ0123.md | C97: Court Decision | D97: EU | E97: 22252c77-2086-4d9e-94b7-b7219394e299
A98: 85 | B98: 62020CC0376.md | C98: Court Decision | D98: EU | E98: cebd4962-06e0-43a6-ac13-b9cc9b05c9e7
A99: 86 | B99: 62021CC0320.md | C99: Bulletin article | D99: EU | E99: 75a5ded3-767b-4407-994f-4851c80f8279
A100: 87 | B100: 42450.md | C100: Bulletin article | E100: a1b4b6f8-67ab-4961-a0e8-5bfb813f0936
...

Sheet Q18
A1: Q18 — Expert Review
A2: Question metadata
A3: Question ID | B3: 18
A4: Topic | B4: Dawn raids — legal professional privilege
A5: Scope | B5: US
A6: Original reviewer | B6: Arthur
A7: Original status | B7: Approved
A8: Question | B8: At what stage is attorney-client privilege breached when US antitrust authorities gather documents — when the investigator reads the document, or only when it is later used?
A9: Generated answer
A10: Paste the generated answer here.
A11: Run ID | C11: Run date
A12: Retrieval set review
A13: Rank | B13: Document name | C13: Document class | D13: Jurisdiction | E13: URL / Document ID | F13: Required source? | G13: Expert verdict | H13: Notes
A14: 1
A15: 2
A16: 3
A17: 4
A18: 5
A19: 6
A20: 7
A21: 8
A22: 9
A24: Claim-by-claim review
A25: Claim ID | B25: Claim from answer | C25: Cited document | D25: Expert verdict | E25: Cited passage | F25: Required fix / comment
A26: 1
A27: 2
A28: 3
A29: 4
A30: 5
A31: 6
A32: 7
A33: 8
A34: 9
A36: Final expert verdict
A37: Reviewer
A38: Is the answer acceptable?
A39: Overall comment / required fixes
A40: Review completed?
A69: Original source notes
A70: WAB notes | B70: Your document gave this as "the same attorney-client privilege question transposed to US inspections". This is our wording of it. We had drafted a wider US question instead — how privilege is protected, what separates a criminal search from civil compulsory process, and what keeps privileged material away from the investigating team. Yours is narrower and sharper, so we used yours. Tell us if you want the wider version, or both.
A71: Reviewer notes from question approval | B71: I suggest including both versions. Please retain the narrower question, but also add the wider question addressing how attorney-client privilege and work-product protection operate under criminal search warrants and civil compulsory process, including the use of filter teams or special masters. The issue is not limited to whether the document is ultimately used: concerns may arise at the stages of seizure, initial review, disclosure to the investigating team, retention, and derivative use.

Sheet Q19
A1: Q19 — Expert Review
A2: Question metadata
A3: Question ID | B3: 19
A4: Topic | B4: Dawn raids — personal data
A5: Scope | B5: US
A6: Original reviewer | B6: Arthur
A7: Original status | B7: Approved
A8: Question | B8: What protections apply to personal or otherwise sensitive data gathered by U.S. antitrust authorities, and on what grounds may material that is irrelevant, overbroad, privileged, or otherwise protected be segregated, withheld, returned, or destroyed?
A9: Generated answer
A10: Paste the generated answer here.
A11: Run ID | C11: Run date
A12: Retrieval set review
A13: Rank | B13: Document name | C13: Document class | D13: Jurisdiction | E13: URL / Document ID | F13: Required source? | G13: Expert verdict | H13: Notes
A14: 1
A15: 2
A16: 3
A17: 4
A18: 5
A19: 6
A20: 7
A21: 8
A22: 9
A24: Claim-by-claim review
A25: Claim ID | B25: Claim from answer | C25: Cited document | D25: Expert verdict | E25: Cited passage | F25: Required fix / comment
A26: 1
A27: 2
A28: 3
A29: 4
A30: 5
A31: 6
A32: 7
A33: 8
A34: 9
A36: Final expert verdict
A37: Reviewer
A38: Is the answer acceptable?
A39: Overall comment / required fixes
A40: Review completed?

Sheet Q20
A1: Q20 — Expert Review
A2: Question metadata
A3: Question ID | B3: 20
A4: Topic | B4: Dawn raids — challenging a seizure
A5: Scope | B5: US
A6: Original reviewer | B6: Arthur
A7: Original status | B7: Approved
A8: Question | B8: What procedural avenues exist to challenge the seizure, review, retention, or use of privileged documents following the execution of a search warrant in a criminal antitrust investigation, and how do those remedies differ from procedures for modifying or setting aside a subpoena or Civil Investigative Demand (CID) in a civil antitrust investigation?
A9: Generated answer
A10: Paste the generated answer here.
A11: Run ID | C11: Run date
A12: Retrieval set review
A13: Rank | B13: Document name | C13: Document class | D13: Jurisdiction | E13: URL / Document ID | F13: Required source? | G13: Expert verdict | H13: Notes
A14: 1
A15: 2
A16: 3
A17: 4
A18: 5
A19: 6
A20: 7
A21: 8
A22: 9
A24: Claim-by-claim review
A25: Claim ID | B25: Claim from answer | C25: Cited document | D25: Expert verdict | E25: Cited passage | F25: Required fix / comment
A26: 1
A27: 2
A28: 3
A29: 4
A30: 5
A31: 6
A32: 7
A33: 8
A34: 9
A36: Final expert verdict
A37: Reviewer
A38: Is the answer acceptable?
A39: Overall comment / required fixes
A40: Review completed?

Sheet Q21
A1: Q21 — Expert Review
A2: Question metadata
A3: Question ID | B3: 21
A4: Topic | B4: Food delivery — data access
A5: Scope | B5: EU + UK
A6: Original reviewer | B6: Carolina
A7: Original status | B7: Approved
A8: Question | B8: Where a platform like Uber leverages data collected across its ecosystem to improve and strengthen its food delivery arm, how would such conduct be characterised under EU competition law — as tying/bundling, as an exploitative abuse, as leveraging into an adjacent market, or as a distinct data-driven theory of harm? Which category best fits, and what would be required to establish it under Article 102 TFEU?
A9: Generated answer
A10: Paste the generated answer here.
A11: Run ID | C11: Run date
A12: Retrieval set review
A13: Rank | B13: Document name | C13: Document class | D13: Jurisdiction | E13: URL / Document ID | F13: Required source? | G13: Expert verdict | H13: Notes
A14: 1
A15: 2
A16: 3
A17: 4
A18: 5
A19: 6
A20: 7
A21: 8
A22: 9
A24: Claim-by-claim review
A25: Claim ID | B25: Claim from answer | C25: Cited document | D25: Expert verdict | E25: Cited passage | F25: Required fix / comment
A26: 1
A27: 2
A28: 3
A29: 4
A30: 5
A31: 6
A32: 7
A33: 8
A34: 9
A36: Final expert verdict
A37: Reviewer
A38: Is the answer acceptable?
A39: Overall comment / required fixes
A40: Review completed?
A69: Original source notes
A70: WAB notes | B70: Deliberately open to the answer "considered and set aside". If in your view none of the food-delivery decisions engaged with data access at all, tell us — a question with no answer in the case law is one we should drop.
A71: Reviewer notes from question approval | B71: question to be replaced with that one "Where a platform like Uber leverages data collected across its ecosystem to improve and strengthen its food delivery arm, how would such conduct be characterised under EU competition law — as tying/bundling, as an exploitative abuse, as leveraging into an adjacent market, or as a distinct data-driven theory of harm? Which category best fits, and what would be required to establish it under Article 102 TFEU?"

Sheet Q22
A1: Q22 — Expert Review
A2: Question metadata
A3: Question ID | B3: 22
A4: Topic | B4: Food delivery — own fleet vs marketplace
A5: Scope | B5: EU + UK + ES
A6: Original reviewer | B6: Carolina
A7: Original status | B7: Approved
A8: Question | B8: Can a food-delivery platform qualify as a provider of online intermediation services within the meaning of the P2B Regulation (EU) 2019/1150 — and if so, which obligations would it additionally have to comply with should it be designated as a gatekeeper under the DMA?
A9: Generated answer
A10: Paste the generated answer here.
A11: Run ID | C11: Run date
A12: Retrieval set review
A13: Rank | B13: Document name | C13: Document class | D13: Jurisdiction | E13: URL / Document ID | F13: Required source? | G13: Expert verdict | H13: Notes
A14: 1
A15: 2
A16: 3
A17: 4
A18: 5
A19: 6
A20: 7
A21: 8
A22: 9
A24: Claim-by-claim review
A25: Claim ID | B25: Claim from answer | C25: Cited document | D25: Expert verdict | E25: Cited passage | F25: Required fix / comment
A26: 1
A27: 2
A28: 3
A29: 4
A30: 5
A31: 6
A32: 7
A33: 8
A34: 9
A36: Final expert verdict
A37: Reviewer
A38: Is the answer acceptable?
A39: Overall comment / required fixes
A40: Review completed?
A69: Original source notes
A70: WAB notes
A71: Reviewer notes from question approval | B71: question to be replaced with that one "Can a food-delivery platform qualify as a provider of online intermediation services within the meaning of the P2B Regulation (EU) 2019/1150 — and if so, which obligations would it additionally have to comply with should it be designated as a gatekeeper under the DMA?'

Sheet Q23
A1: Q23 — Expert Review
A2: Question metadata
A3: Question ID | B3: 23
A4: Topic | B4: Food delivery — which authority reviews
A5: Scope | B5: EU + UK + ES
A6: Original reviewer | B6: Carolina
A7: Original status | B7: Approved
A8: Question | B8: Food-delivery transactions frequently fall below the EU Merger Regulation turnover thresholds yet raise cross-border concerns. In light of the CJEU's Illumina/Grail judgment restricting Article 22 upward referrals for deals that do not meet any national threshold, what mechanisms remain for the Commission to capture a below-threshold food-delivery 'killer acquisition'?
A9: Generated answer
A10: Paste the generated answer here.
A11: Run ID | C11: Run date
A12: Retrieval set review
A13: Rank | B13: Document name | C13: Document class | D13: Jurisdiction | E13: URL / Document ID | F13: Required source? | G13: Expert verdict | H13: Notes
A14: 1
A15: 2
A16: 3
A17: 4
A18: 5
A19: 6
A20: 7
A21: 8
A22: 9
A24: Claim-by-claim review
A25: Claim ID | B25: Claim from answer | C25: Cited document | D25: Expert verdict | E25: Cited passage | F25: Required fix / comment
A26: 1
A27: 2
A28: 3
A29: 4
A30: 5
A31: 6
A32: 7
A33: 8
A34: 9
A36: Final expert verdict
A37: Reviewer
A38: Is the answer acceptable?
A39: Overall comment / required fixes
A40: Review completed?
A69: Original source notes
A70: WAB notes
A71: Reviewer notes from question approval | B71: questions to be replaced with that one: "Food-delivery transactions frequently fall below the EU Merger Regulation turnover thresholds yet raise cross-border concerns. In light of the CJEU's Illumina/Grail judgment restricting Article 22 upward referrals for deals that do not meet any national threshold, what mechanisms remain for the Commission to capture a below-threshold food-delivery 'killer acquisition'?"

Sheet Q24
A1: Q24 — Expert Review
A2: Question metadata
A3: Question ID | B3: 24
A4: Topic | B4: Dawn raids — legal professional privilege
A5: Scope | B5: EU
A6: Original reviewer | B6: Carolina
A7: Original status | B7: Approved
A8: Question | B8: Does legal professional privilege in EU competition law cover advice from a company's own in-house lawyers? How have the courts justified where the line falls, and what does that mean in practice during an inspection?
A9: Generated answer
A10: Paste the generated answer here.
A11: Run ID | C11: Run date
A12: Retrieval set review
A13: Rank | B13: Document name | C13: Document class | D13: Jurisdiction | E13: URL / Document ID | F13: Required source? | G13: Expert verdict | H13: Notes
A14: 1 | B14: eu-antitrust-enforcement--14_xiii_legal_professional_privilege_in_eu_antitrust_enforcement_law_policy_and_procedure.md | C14: Book (Livre) | E14: 751159c7-e8b0-4cba-8ae1-5652058d7980 | H14: Cited in answer: YES
A15: 2 | B15: 129921.md | C15: Article (Review) | E15: f778c4be-e8ad-469a-a0b4-810de049896e | H15: Cited in answer: YES
A16: 3 | B16: 62007CJ0550.md | C16: Court Decision | D16: EU | E16: 77a4dd19-04ce-410f-ba8e-9998f2902880 | H16: Cited in answer: YES
A17: 4 | B17: eu-antitrust-enforcement--11_x_fundamental_procedural_rights_and_effective_enforcement_of_articles_101_and_102_tfeu_in_the_european_competition_network.md | C17: Book (Livre) | E17: 44d971b2-9615-45f5-94c3-342633964481
A18: 5 | B18: 65144.md | C18: Bulletin article | E18: ce8f9970-7bea-4576-a4de-4bd06551adb1
A19: 6 | B19: eu-antitrust-enforcement--12_xi_the_role_of_the_hearing_officer_in_antitrust_proceedings_before_the_european_commission.md | C19: Book (Livre) | E19: 27d55d8c-5b59-43c1-8576-7a718bd009d4
A20: 7 | B20: 34843.md | C20: Bulletin article | D20: EU | E20: 76b0b83a-c3dd-4742-972b-2e257224bb41
A21: 8 | B21: eu-antitrust-enforcement--15_xiv_procedural_rights_and_obligations_of_third_parties_in_antitrust_investigations_and_proceedings_by_the_european_commission.md | C21: Book (Livre) | E21: b2429dd2-ef75-4f34-8bf2-95b08c3a4de5
A22: 9 | B22: 120985.md | C22: Bulletin article | E22: 8743ed4a-36f8-448f-9aa9-ccf29abfc760 | H22: Cited in answer: YES
A23: 10 | B23: inspections-eu-law-2nd--3_chapter_1_-_inspections_upon_decision_regulation_1_2003_article_20_4.md | C23: Book (Livre) | E23: d28b1d20-a2c6-425f-a401-498eab28d744
A24: 11 | B24: 41021.md | C24: Bulletin article | E24: 7b2a2c23-bf06-4bb0-84da-b780b94a649c
A25: 12 | B25: compendium-eu-competition-law--p20.md | C25: Legislation | E25: 4051fc69-a489-4b05-95ab-16bd651b54f1
A26: 13 | B26: 126520.md | C26: Bulletin article | E26: 12452b73-c2de-4280-8e98-eaf8be0779ba
A27: 14 | B27: 121144.md | C27: Bulletin article | E27: 9f96a5ff-2537-45cd-a34f-b0f82767f132
A28: 15 | B28: 41554.md | C28: Bulletin article | E28: 7ac322df-dba5-454b-a0e6-0bff2167a703
A29: 16 | B29: 130104-the-eu-commission-issues-a-policy-brief-on-legal-professional-privilege-in-compe.md | C29: Bulletin article | E29: 865b10b4-e120-4887-a566-4d32965a6785
A30: 17 | B30: 86349.md | C30: Article (Review) | E30: 1cdd887b-6171-4114-a519-848559eecb91
A31: 18 | B31: 74797.md | C31: Bulletin article | E31: 7aa935c3-59fb-4514-b6c3-08e34df697ff
A32: 19 | B32: 62017TJ0249.md | C32: Court Decision | D32: EU | E32: dbf7bda8-39fa-4eb5-a6e2-f02b0787cb54
A33: 20 | B33: 129913.md | C33: Bulletin article | E33: 3a32afa7-1686-4dd5-83df-28c025e3c011 | H33: Cited in answer: YES
A34: 21 | B34: competition-case-law-digest-5th--p10.md | C34: Book (Livre) | E34: 65e060cb-bdeb-413d-b4e8-b9ffe0ed3995
A35: 22 | B35: competition-inspections-25-jurisdictions--16_netherlands.md | C35: Article (Review) | E35: bd91d513-0a9b-4001-afec-498af0c4e9c4
A36: 23 | B36: 96845-the-eu-court-of-justice-rules-that-legal-professional-privilege-does-not-cover-c.md | C36: Bulletin article | E36: ffcd147d-9482-4eff-8ba1-f4eafa068ea6
A37: 24 | B37: 112075.md | C37: Bulletin article | E37: d2417411-7570-40c0-8fde-72b358d5c65a | H37: Cited in answer: YES
A38: 25 | B38: 62014TJ0705.md | C38: Court Decision | D38: EU | E38: a795bd44-0811-455c-9d8e-6e9c125b497b
A39: 26 | B39: 62014TJ0701.md | C39: Court Decision | D39: EU | E39: 82bcdb25-439b-4260-9d81-4848737b9274
A40: 27 | B40: 127784.md | C40: Bulletin article | E40: 470178ab-ccae-498b-a50a-4f7075e27cd0
A41: 28 | B41: 91835.md | C41: Article (Review) | E41: f6ec0179-d152-4059-9a3f-81d669d422b0
A42: 29 | B42: 120341.md | C42: Bulletin article | E42: 62e4c8bf-db38-4627-90b0-e49ff9dbad01
A43: 30 | B43: 62018CJ0403.md | C43: Court Decision | D43: EU | E43: 5b155c4b-0345-4afa-8dee-d56351895c8f
A44: 31 | B44: 62020CC0682.md | C44: Article (Review) | D44: EU | E44: f6fc977b-8c8d-467b-a5f7-04beb77f1b93
A45: 32 | B45: 62023TJ1097.md | C45: Court Decision | D45: EU | E45: 17ecc724-b05f-4f42-9a28-b1282ba34327
A46: 33 | B46: 62003TJ0125.md | C46: Court Decision | D46: EU | E46: a8c1d5f4-d4fb-4365-bf78-e327971748f9
A47: 34 | B47: 26656.md | C47: Bulletin article | E47: 81642e09-5607-418a-a7f4-cf18d6fa7ddf
A48: 35 | B48: 81215.md | C48: Article (Review) | E48: 1326c749-4c6d-42ec-974e-b228dd1bf722
A49: 36 | B49: 131688-30-inspections-the-general-court-of-the-european-union-upholds-the-european-comm.md | C49: Bulletin article | E49: 7de191c9-0221-423b-b670-ef1e047a0196
A50: 37 | B50: 62009TJ0135.md | C50: Court Decision | D50: EU | E50: 10418f10-8b6f-4bcc-adf6-39e168b49440
A51: 38 | B51: 79963.md | C51: Article (Review) | E51: b0c5f913-948d-4dcc-9ea4-98f6136ca5a7
A52: 39 | B52: 95849-3360-inspections-the-court-of-justice-of-the-european-union-gives-the-commission.md | C52: Bulletin article | E52: afe07022-9e8e-4270-a8d4-2c0aaa70652f
A53: 40 | B53: judicial-review-competition-cases--6_european_union_-_judicial_review_of_inspection_decisions.md | C53: Article (Review) | E53: 21a3ec2e-1c42-4307-ab97-e45011d6660a
A54: 41 | B54: 96910-3420-dawn-raids-the-court-of-justice-of-the-european-union-confirms-the-power-of.md | C54: Bulletin article | E54: a95ca40b-ceae-4436-8de6-a7a126b177e3
A55: 42 | B55: 97110-2850-inspection-the-general-court-of-the-european-union-partially-annuls-decisio.md | C55: Bulletin article | E55: 0ff86075-a215-4bce-ac53-21a9aa21cd71
A56: 43 | B56: 97568-3340-investigation-the-court-of-justice-of-the-european-union-recognizes-the-eur.md | C56: Bulletin article | E56: 0a9a6620-916c-4d26-8e97-e91a08871183
A57: 44 | B57: 45408-the-eu-court-of-justice-holds-that-in-house-lawyers-are-not-protected-by-legal-p.md | C57: Bulletin article | E57: 7af38e62-27f7-4570-be20-5b4f80937e5e
A58: 45 | B58: 93368-2520-investigations-the-court-of-justice-of-the-european-union-rules-that-an-act.md | C58: Bulletin article | E58: eb4af447-a8d7-4102-8c9b-20f8865d5fea
A59: 46 | B59: 94920-2150-inquiries-the-court-of-justice-of-the-european-union-dismisses-appeals-brou.md | C59: Bulletin article | E59: e7e462f6-8d3e-4f46-92a9-57edcae44fd8
A60: 47 | B60: AT.37990-DEC_D1115C27-9B1D-401A-A930-8895EBEFC8F6_-ATT3581.md | C60: Regulatory Decision | D60: EU | E60: b320e5cc-5605-4cb5-9f85-f6decae603d2
A61: 48 | B61: 128250-35-dawn-raids-the-general-court-of-the-european-union-partially-upholds-the-lega.md | C61: Bulletin article | E61: e34c0e6d-2771-4073-8165-4a73eff42d4c
A62: 49 | B62: 93706-0060-dawn-raids-advocate-general-kokott-calls-on-the-court-of-justice-to-uphold.md | C62: Bulletin article | E62: 42a1613c-b25b-476e-a3b4-e1cac9b5add2
A63: 50 | B63: 43794.md | C63: Bulletin article | E63: a4eaf6f6-7e47-4725-80b7-6ecdd7d1725a
A64: 51 | B64: AT.38344-DEC_B59735BA-DE29-4610-9932-BD01F21B8EE4_-ATT5856.md | C64: Regulatory Decision | D64: EU | E64: 7c81403f-40e6-418d-bcb3-6cc8cce1e6d9
A65: 52 | B65: 105103.md | C65: Bulletin article | E65: f10e4cc4-d036-4949-b9be-86b79b54fa7d
A66: 53 | B66: 96586.md | C66: Article (Review) | E66: 4cb5c154-4d3a-46c3-8bca-8f09c7e6c562
A67: 54 | B67: 112569-2500-legal-privilege-the-french-supreme-court-censures-the-use-by-trial-judges-o.md | C67: Bulletin article | E67: 2baf52d5-e5a8-438f-89d0-2b75cd31453f
A68: 55 | B68: AT.38629-DEC_B1D1DEEF-69F2-46AD-9CF0-760BDE41FF57_-ATT1056.md | C68: Regulatory Decision | D68: EU | E68: 1d6217b4-c629-433a-b156-7ec855ee567d
A69: 56 | B69: competition-inspections-25-jurisdictions--22_spain.md | C69: Article (Review) | E69: c612bb23-e93e-4e90-be30-4979d304f10e
A70: 57 | B70: 62018CJ0606.md | C70: Court Decision | D70: EU | E70: 2d074327-045b-484e-8bbc-1a0f9c7ed660
A71: 58 | B71: 62020CJ0682.md | C71: Court Decision | D71: EU | E71: 408cfe67-7fe4-45a8-9c3e-de39d86d56cb
A72: 59 | B72: competition-case-law-digest-5th--p09.md | C72: Book (Livre) | E72: 2f0afdb0-43c8-41b3-99e2-c3003ab906c1
A73: 60 | B73: competition-inspections-25-jurisdictions--7_european_union.md | C73: Article (Review) | E73: 1c2fa592-34f0-4656-96c2-024c5ea88b1e
A74: 61 | B74: 19838.md | C74: Bulletin article | E74: 4fbf45d8-5766-4ba1-868c-18f49fdc837f
A75: 62 | B75: AT.39685-DEC_B33871A4-85CF-4460-AF10-A316F0FCD1B3_-ATT1976.md | C75: Regulatory Decision | D75: EU | E75: f4c38de6-b0b1-4d43-bba1-95b9f50b711c
A76: 63 | B76: 57935-361-decisions-adopted-during-an-inspection-the-general-court-reminds-the-commiss.md | C76: Bulletin article | E76: 882aa354-e6cf-464a-b1e2-9486b1cca48f
A77: 64 | B77: competition-inspections-25-jurisdictions--23_sweden.md | C77: Article (Review) | E77: dcf6ff3a-fc96-4095-bbc3-ecdd4afa4808
A78: 65 | B78: 62010TJ0047.md | C78: Court Decision | D78: EU | E78: 3cc76128-e075-4858-8344-bb863faf33fb
A79: 66 | B79: m10149.md | C79: Regulatory Decision | D79: EU | E79: 440344d8-5df6-4302-a894-bc58447b2a18
A80: 67 | B80: 127929-the-eu-general-court-upholds-the-commissions-inspection-methodology-based-on-pub.md | C80: Bulletin article | E80: af2e8c94-00c3-40d4-8e35-233542ca536d
A81: 68 | B81: eu-antitrust-enforcement--20_table_of_cases.md | C81: Article (Review) | E81: b6fab320-df7d-4a91-824a-3b8c5b27c0d9
A82: 69 | B82: 50285.md | C82: Bulletin article | E82: f17418b6-489e-4049-92f0-b9ce2b58968f
A83: 70 | B83: 62011TJ0289.md | C83: Court Decision | D83: EU | E83: 7ecb1eda-828c-4ed1-831c-9ba3cd309425
A84: 71 | B84: 62009TJ0146(01).md | C84: Court Decision | D84: EU | E84: 875d499b-3764-4398-9234-f5a88c4a5b7c
A85: 72 | B85: 62019CJ0152.md | C85: Court Decision | D85: EU | E85: c20ed621-696c-46d8-8f57-7668f6e1913e
A86: 73 | B86: eu-antitrust-enforcement--17_xvi_re_adoption_by_the_european_commission_of_cartel_decisions_annulled_on_procedural_grounds_by_the_eu_courts.md | C86: Article (Review) | E86: 71ba5e7f-b51e-4068-b010-b7e7f422add9
A87: 74 | B87: 87500.md | C87: Conference summary | E87: 01821bca-778a-42dd-a6cc-ef84f6382110
A88: 75 | B88: 62015CJ0516.md | C88: Court Decision | D88: EU | E88: e2a4ba47-2dcd-4ee7-816c-9f32b926eba3
A89: 76 | B89: 62015CC0516.md | C89: Bulletin article | D89: EU | E89: 5f7ad9f4-0208-4c3a-890c-c1407f89787e
A90: 77 | B90: 125471-20-dawn-raids-the-general-court-upholds-the-european-commissions-overall-assessm.md | C90: Bulletin article | E90: e97ed81a-60ca-4112-9207-21a8613078bd
A91: 78 | B91: 62018CJ0595.md | C91: Court Decision | D91: EU | E91: 9cef1570-4dfe-4218-9740-d8f6d239921b
A92: 79 | B92: 62017TJ0254.md | C92: Court Decision | D92: EU | E92: bed91df8-f034-4e81-96a1-ffff25500899
A93: 80 | B93: 62007TJ0421(01).md | C93: Court Decision | D93: EU | E93: 818076c5-da80-4b29-859b-893429f258b6
A94: 81 | B94: competition-inspections-25-jurisdictions--27_united_kingdom.md | C94: Article (Review) | E94: 5261e3c8-c961-4df0-a163-1e489d633173
A95: 82 | B95: 127186-20-inspection-the-general-court-of-the-european-union-considers-that-the-commiss.md | C95: Bulletin article | E95: 329bd68b-1104-4f5c-b636-e9925175dbc6
A96: 83 | B96: competition-case-law-digest-5th--p11.md | C96: Book (Livre) | E96: 40351206-cbf5-40d8-a127-173a24162f6e
A97: 84 | B97: 62012CJ0580.md | C97: Court Decision | D97: EU | E97: fa57de20-7bf4-4ba4-909e-a43f31e59774
A98: 85 | B98: 62015TJ0274.md | C98: Court Decision | D98: EU | E98: d42f923b-c267-4df9-acb3-5abda361a0d6
A99: 86 | B99: 62010TJ0027.md | C99: Court Decision | D99: EU | E99: bc02167d-8c4b-4b56-831c-f9c775215394
A100: 87 | B100: 62018CJ0823.md | C100: Court Decision | D100: EU | E100: 8a4af7ed-4940-4a94-8f4f-db32b00f6a4b
...

Sheet Q25
A1: Q25 — Expert Review
A2: Question metadata
A3: Question ID | B3: 25
A4: Topic | B4: Dawn raids — legal professional privilege
A5: Scope | B5: France
A6: Original reviewer | B6: Carolina
A7: Original status | B7: Approved
A8: Question | B8: Where a French dawn raid seizes a mailbox or a set of files in bulk and privileged correspondence is found inside afterwards, what is the procedure for having it returned or destroyed, and who decides?
A9: Generated answer
A10: Paste the generated answer here.
A11: Run ID | C11: Run date
A12: Retrieval set review
A13: Rank | B13: Document name | C13: Document class | D13: Jurisdiction | E13: URL / Document ID | F13: Required source? | G13: Expert verdict | H13: Notes
A14: 1
A15: 2
A16: 3
A17: 4
A18: 5
A19: 6
A20: 7
A21: 8
A22: 9
A24: Claim-by-claim review
A25: Claim ID | B25: Claim from answer | C25: Cited document | D25: Expert verdict | E25: Cited passage | F25: Required fix / comment
A26: 1
A27: 2
A28: 3
A29: 4
A30: 5
A31: 6
A32: 7
A33: 8
A34: 9
A36: Final expert verdict
A37: Reviewer
A38: Is the answer acceptable?
A39: Overall comment / required fixes
A40: Review completed?
A69: Original source notes
A70: WAB notes | B70: Possible overlap with question 14.
A71: Reviewer notes from question approval | B71: no overlap with question 14, we can keep the question.

Sheet Q26
A1: Q26 — Expert Review
A2: Question metadata
A3: Question ID | B3: 26
A4: Topic | B4: Dawn raids — challenging a seizure
A5: Scope | B5: France
A6: Original reviewer | B6: Carolina
A7: Original status | B7: Approved
A8: Question | B8: French law separates a challenge to the order authorising a dawn raid from a challenge to how the raid was carried out. What are the two routes, who hears each, what are the time limits, and what can each achieve?
A9: Generated answer
A10: Paste the generated answer here.
A11: Run ID | C11: Run date
A12: Retrieval set review
A13: Rank | B13: Document name | C13: Document class | D13: Jurisdiction | E13: URL / Document ID | F13: Required source? | G13: Expert verdict | H13: Notes
A14: 1
A15: 2
A16: 3
A17: 4
A18: 5
A19: 6
A20: 7
A21: 8
A22: 9
A24: Claim-by-claim review
A25: Claim ID | B25: Claim from answer | C25: Cited document | D25: Expert verdict | E25: Cited passage | F25: Required fix / comment
A26: 1
A27: 2
A28: 3
A29: 4
A30: 5
A31: 6
A32: 7
A33: 8
A34: 9
A36: Final expert verdict
A37: Reviewer
A38: Is the answer acceptable?
A39: Overall comment / required fixes
A40: Review completed?
A69: Original source notes
A70: WAB notes | B70: Possible overlap with question 14.
A71: Reviewer notes from question approval | B71: no overlap with question 14, we can keep the question.

Sheet Q27
A1: Q27 — Expert Review
A2: Question metadata
A3: Question ID | B3: 27
A4: Topic | B4: Dawn raids — the inspection decision
A5: Scope | B5: EU
A6: Original reviewer | B6: Carolina
A7: Original status | B7: Approved
A8: Question | B8: What is the extent of the Commission's duty to state reasons under Article 20(4) of Regulation 1/2003 as regards the subject matter and purpose of an inspection decision and the identification of its addressees — and what are the consequences, in light of Nexans, Deutsche Bahn and Les Laboratoires Servier, where the scope of the inspection exceeds the reasonable grounds (indicia) actually in the Commission's possession?
A9: Generated answer
A10: Paste the generated answer here.
A11: Run ID | C11: Run date
A12: Retrieval set review
A13: Rank | B13: Document name | C13: Document class | D13: Jurisdiction | E13: URL / Document ID | F13: Required source? | G13: Expert verdict | H13: Notes
A14: 1
A15: 2
A16: 3
A17: 4
A18: 5
A19: 6
A20: 7
A21: 8
A22: 9
A24: Claim-by-claim review
A25: Claim ID | B25: Claim from answer | C25: Cited document | D25: Expert verdict | E25: Cited passage | F25: Required fix / comment
A26: 1
A27: 2
A28: 3
A29: 4
A30: 5
A31: 6
A32: 7
A33: 8
A34: 9
A36: Final expert verdict
A37: Reviewer
A38: Is the answer acceptable?
A39: Overall comment / required fixes
A40: Review completed?
A69: Original source notes
A70: WAB notes
A71: Reviewer notes from question approval | B71: I like the question but let's frame it like this "What is the extent of the Commission's duty to state reasons under Article 20(4) of Regulation 1/2003 as regards the subject matter and purpose of an inspection decision and the identification of its addressees — and what are the consequences, in light of Nexans, Deutsche Bahn and Les Laboratoires Servier, where the scope of the inspection exceeds the reasonable grounds (indicia) actually in the Commission's possession?"

Sheet Q28
A1: Q28 — Expert Review
A2: Question metadata
A3: Question ID | B3: 28
A4: Topic | B4: Dawn raids — the inspection decision
A5: Scope | B5: EU
A6: Original reviewer | B6: Carolina
A7: Original status | B7: Approved
A8: Question | B8: Can an inspection decision be annulled in part where the Commission's evidence supports only some of the suspected infringement period it covers, and what then happens to material already gathered?
A9: Generated answer
A10: Paste the generated answer here.
A11: Run ID | C11: Run date
A12: Retrieval set review
A13: Rank | B13: Document name | C13: Document class | D13: Jurisdiction | E13: URL / Document ID | F13: Required source? | G13: Expert verdict | H13: Notes
A14: 1 | B14: 62014TJ0475.md | C14: Court Decision | D14: EU | E14: cba40d0a-c143-4bc9-af97-af13ef20db3a
A15: 2 | B15: 62014TJ0449.md | C15: Court Decision | D15: EU | E15: 2f594756-bc0a-4332-829f-e65319b3211c
A16: 3 | B16: inspections-eu-law-2nd--3_chapter_1_-_inspections_upon_decision_regulation_1_2003_article_20_4.md | C16: Book (Livre) | E16: d28b1d20-a2c6-425f-a401-498eab28d744
A17: 4 | B17: 62018CC0606.md | C17: Article (Review) | D17: EU | E17: 0655b4ec-4821-4b46-91b6-b6ddaebd8d5d
A18: 5 | B18: 62020CC0682.md | C18: Article (Review) | D18: EU | E18: f6fc977b-8c8d-467b-a5f7-04beb77f1b93 | H18: Cited in answer: YES
A19: 6 | B19: 62011TJ0289.md | C19: Court Decision | D19: EU | E19: 7ecb1eda-828c-4ed1-831c-9ba3cd309425
A20: 7 | B20: 62013CC0583.md | C20: Bulletin article | D20: EU | E20: 778d749c-48cb-405c-a58f-962dd3ceef0c
A21: 8 | B21: 62020CJ0693.md | C21: Court Decision | D21: EU | E21: 74ccf3f4-5d27-4c74-9208-62829cc5bcf1
A22: 9 | B22: 62020CJ0690.md | C22: Court Decision | D22: EU | E22: 75c2da13-00ee-43b2-baa4-a6f2e5a71e73
A23: 10 | B23: 62017TJ0249.md | C23: Court Decision | D23: EU | E23: dbf7bda8-39fa-4eb5-a6e2-f02b0787cb54 | H23: Cited in answer: YES
A24: 11 | B24: 62018CJ0606.md | C24: Court Decision | D24: EU | E24: 2d074327-045b-484e-8bbc-1a0f9c7ed660
A25: 12 | B25: competition-case-law-digest-5th--p10.md | C25: Book (Livre) | E25: 65e060cb-bdeb-413d-b4e8-b9ffe0ed3995
A26: 13 | B26: 62018CJ0601.md | C26: Court Decision | D26: EU | E26: d94571df-d56d-45c1-a02e-834714984963
A27: 14 | B27: 81215.md | C27: Article (Review) | E27: 1326c749-4c6d-42ec-974e-b228dd1bf722
A28: 15 | B28: 93706-0060-dawn-raids-advocate-general-kokott-calls-on-the-court-of-justice-to-uphold.md | C28: Bulletin article | E28: 42a1613c-b25b-476e-a3b4-e1cac9b5add2
A29: 16 | B29: 62016TJ0325.md | C29: Court Decision | D29: EU | E29: b7c29457-b49b-44b3-a09c-8c0dfd4574fa
A30: 17 | B30: 62014TJ0447.md | C30: Court Decision | D30: EU | E30: aef64236-c9f7-4cf3-b707-108a4788237a
A31: 18 | B31: 62020CJ0682.md | C31: Court Decision | D31: EU | E31: 408cfe67-7fe4-45a8-9c3e-de39d86d56cb
A32: 19 | B32: 62009TJ0135.md | C32: Court Decision | D32: EU | E32: 10418f10-8b6f-4bcc-adf6-39e168b49440 | H32: Cited in answer: YES
A33: 20 | B33: 62013CJ0037.md | C33: Court Decision | D33: EU | E33: 2426e61d-f1e3-4fe6-a1e7-1b0d6d4deb24 | H33: Cited in answer: YES
A34: 21 | B34: 62013CJ0583.md | C34: Court Decision | D34: EU | E34: 7b8f60ed-1acc-484e-b298-5a745b6b18f3
A35: 22 | B35: 62013CC0037.md | C35: Bulletin article | D35: EU | E35: 632273f6-990f-4cc6-85ff-77f86f45c537 | H35: Cited in answer: YES
A36: 23 | B36: 79963.md | C36: Article (Review) | E36: b0c5f913-948d-4dcc-9ea4-98f6136ca5a7
A37: 24 | B37: 62020CC0690.md | C37: Bulletin article | D37: EU | E37: 349cac6b-c1bd-4e7c-a092-8bef2db77ad2
A38: 25 | B38: 57935-361-decisions-adopted-during-an-inspection-the-general-court-reminds-the-commiss.md | C38: Bulletin article | E38: 882aa354-e6cf-464a-b1e2-9486b1cca48f
A39: 26 | B39: 105103.md | C39: Bulletin article | E39: f10e4cc4-d036-4949-b9be-86b79b54fa7d
A40: 27 | B40: 62014TJ0438.md | C40: Court Decision | D40: EU | E40: 6a32efef-ff93-4a71-a7ee-b89b0ce42186
A41: 28 | B41: 62014TJ0444.md | C41: Court Decision | D41: EU | E41: ad848645-bb6b-44c9-97d8-1d02f8e2faea
A42: 29 | B42: 62014TJ0450.md | C42: Court Decision | D42: EU | E42: 41438462-5717-4e1a-90f5-29e9bd19df4e
A43: 30 | B43: 62014TJ0448.md | C43: Court Decision | D43: EU | E43: a1cedab5-8bac-4b53-b449-d548df1478bd
A44: 31 | B44: 91835.md | C44: Article (Review) | E44: f6ec0179-d152-4059-9a3f-81d669d422b0
A45: 32 | B45: 62014TJ0446.md | C45: Court Decision | D45: EU | E45: 0544383c-55cc-41be-80a9-8bbf021f4238
A46: 33 | B46: 62014TJ0439.md | C46: Court Decision | D46: EU | E46: f6678f66-34ee-437e-a7ec-e20f61c0a6a8
A47: 34 | B47: 62004TJ0340.md | C47: Court Decision | D47: EU | E47: d9fb7f73-952b-4b71-a502-6f63b7f95073
A48: 35 | B48: competition-case-law-digest-5th--p09.md | C48: Book (Livre) | E48: 2f0afdb0-43c8-41b3-99e2-c3003ab906c1
A49: 36 | B49: 62014TJ0419.md | C49: Court Decision | D49: EU | E49: 9a680967-760d-4fb3-a9cc-e2fd31c2ce70
A50: 37 | B50: judicial-review-competition-cases--6_european_union_-_judicial_review_of_inspection_decisions.md | C50: Article (Review) | E50: 21a3ec2e-1c42-4307-ab97-e45011d6660a
A51: 38 | B51: 62014TJ0445.md | C51: Court Decision | D51: EU | E51: f87fc08e-9d0b-4701-9a4c-d68f6d2155c7
A52: 39 | B52: 62014TJ0422.md | C52: Court Decision | D52: EU | E52: 6c23abb3-f168-4c55-89cb-8b100b4c23a5
A53: 40 | B53: 62023TJ0263.md | C53: Court Decision | D53: EU | E53: 16791fea-a958-4950-92a6-5a1b65fb3a04
A54: 41 | B54: 96586.md | C54: Article (Review) | E54: 4cb5c154-4d3a-46c3-8bca-8f09c7e6c562
A55: 42 | B55: 62018CJ0403.md | C55: Court Decision | D55: EU | E55: 5b155c4b-0345-4afa-8dee-d56351895c8f
A56: 43 | B56: 97110-2850-inspection-the-general-court-of-the-european-union-partially-annuls-decisio.md | C56: Bulletin article | E56: 0ff86075-a215-4bce-ac53-21a9aa21cd71 | H56: Cited in answer: YES
A57: 44 | B57: 62020CC0682.md | C57: Bulletin article | D57: EU | E57: 4228e89d-bc15-4a00-9ed7-bd703f8ec05a | H57: Cited in answer: YES
A58: 45 | B58: 62014TJ0441.md | C58: Court Decision | D58: EU | E58: 29f8781d-6d42-4188-b0d7-1ff604cf8a33
A59: 46 | B59: 82445.md | C59: Article (Review) | E59: 1be45df1-87e1-4ba2-bdd9-76e5fe184f97
A60: 47 | B60: 103260-35-necessary-limits-to-the-commission-s-inspection-powers.md | C60: Article (Review) | E60: bef18b4b-bb03-49c0-a7aa-afed485ec5d2
A61: 48 | B61: 97568-3340-investigation-the-court-of-justice-of-the-european-union-recognizes-the-eur.md | C61: Bulletin article | E61: 0a9a6620-916c-4d26-8e97-e91a08871183
A62: 49 | B62: 62014CC0247.md | C62: Article (Review) | D62: EU | E62: 9fefd6d8-a7ab-424b-a847-9a604ddaaf0f
A63: 50 | B63: 62012TJ0272.md | C63: Court Decision | D63: EU | E63: 5955aed3-ab0f-4414-a06a-9abbbc834dab
A64: 51 | B64: 131688-30-inspections-the-general-court-of-the-european-union-upholds-the-european-comm.md | C64: Bulletin article | E64: 7de191c9-0221-423b-b670-ef1e047a0196
A65: 52 | B65: 62013TJ0402.md | C65: Court Decision | D65: EU | E65: d193f5d4-ad74-4d17-8105-30b02e493c35
A66: 53 | B66: 128250-35-dawn-raids-the-general-court-of-the-european-union-partially-upholds-the-lega.md | C66: Bulletin article | E66: e34c0e6d-2771-4073-8165-4a73eff42d4c
A67: 54 | B67: 62009TJ0521.md | C67: Court Decision | D67: EU | E67: a9632e6f-3217-4f96-abc5-8577a99e80fb
A68: 55 | B68: 93368-2520-investigations-the-court-of-justice-of-the-european-union-rules-that-an-act.md | C68: Bulletin article | E68: eb4af447-a8d7-4102-8c9b-20f8865d5fea
A69: 56 | B69: 95849-3360-inspections-the-court-of-justice-of-the-european-union-gives-the-commission.md | C69: Bulletin article | E69: afe07022-9e8e-4270-a8d4-2c0aaa70652f
A70: 57 | B70: competition-case-law-digest-5th--p11.md | C70: Book (Livre) | E70: 40351206-cbf5-40d8-a127-173a24162f6e
A71: 58 | B71: 96910-3420-dawn-raids-the-court-of-justice-of-the-european-union-confirms-the-power-of.md | C71: Bulletin article | E71: a95ca40b-ceae-4436-8de6-a7a126b177e3
A72: 59 | B72: 62009TJ0023.md | C72: Court Decision | D72: EU | E72: 094ea41b-a505-436b-a0dd-4ba40b31dfdd
A73: 60 | B73: 62017TJ0799.md | C73: Court Decision | D73: EU | E73: 0e2b9d12-e2ef-4e5a-a4ff-3e040d05d2e9
A74: 61 | B74: 62023TJ1119.md | C74: Court Decision | D74: EU | E74: ce0e3df2-f4ea-4345-a297-e54a4f805a9f
A75: 62 | B75: 62023TJ1097.md | C75: Court Decision | D75: EU | E75: 17ecc724-b05f-4f42-9a28-b1282ba34327
A76: 63 | B76: 62014TJ0451.md | C76: Court Decision | D76: EU | E76: 7fadce2f-3077-4603-8776-ea37b6694dd9
A77: 64 | B77: 62010TJ0027.md | C77: Court Decision | D77: EU | E77: bc02167d-8c4b-4b56-831c-f9c775215394
A78: 65 | B78: 62020TO0451(01).md | C78: Court Decision | D78: EU | E78: b261ed51-2a85-4d85-a20a-92143a7cd6a5
A79: 66 | B79: 62018CO0065(01).md | C79: Court Decision | D79: EU | E79: b916c103-d758-48d4-b1f9-3ada35e78ed9
A80: 67 | B80: 125471-20-dawn-raids-the-general-court-upholds-the-european-commissions-overall-assessm.md | C80: Bulletin article | E80: e97ed81a-60ca-4112-9207-21a8613078bd
A81: 68 | B81: 50285.md | C81: Bulletin article | E81: f17418b6-489e-4049-92f0-b9ce2b58968f
A82: 69 | B82: 94920-2150-inquiries-the-court-of-justice-of-the-european-union-dismisses-appeals-brou.md | C82: Bulletin article | E82: e7e462f6-8d3e-4f46-92a9-57edcae44fd8
A83: 70 | B83: 121144.md | C83: Bulletin article | E83: 9f96a5ff-2537-45cd-a34f-b0f82767f132
A84: 71 | B84: 62011TJ0655.md | C84: Court Decision | D84: EU | E84: 9bbae35a-5d48-465b-8d08-793e521ab06a
A85: 72 | B85: 62020TO0452(01).md | C85: Court Decision | D85: EU | E85: 2768689e-df78-453e-8a77-732820fda1c8
A86: 73 | B86: eu-antitrust-enforcement--15_xiv_procedural_rights_and_obligations_of_third_parties_in_antitrust_investigations_and_proceedings_by_the_european_commission.md | C86: Book (Livre) | E86: b2429dd2-ef75-4f34-8bf2-95b08c3a4de5
A87: 74 | B87: eu-antitrust-enforcement--11_x_fundamental_procedural_rights_and_effective_enforcement_of_articles_101_and_102_tfeu_in_the_european_competition_network.md | C87: Book (Livre) | E87: 44d971b2-9615-45f5-94c3-342633964481
A88: 75 | B88: 62020TJ0451.md | C88: Court Decision | D88: EU | E88: 48c42881-8462-4197-885e-35fd7e697950
A89: 76 | B89: 62011TJ0297.md | C89: Court Decision | D89: EU | E89: b5e94e7b-4cfc-4447-a323-0eaa92692c11
A90: 77 | B90: 62014TJ0455.md | C90: Court Decision | D90: EU | E90: aebaf118-9ca2-4ace-b9cf-c95d8b94a361
A91: 78 | B91: 62017TJ0341.md | C91: Court Decision | D91: EU | E91: 4880dcf3-a2d5-46ce-b920-b87ae618c34b
A92: 79 | B92: 62018CJ0538.md | C92: Court Decision | D92: EU | E92: aeddddae-2bb4-43b2-812c-37431b53023f
A93: 80 | B93: 92103.md | C93: Article (Review) | E93: f12761a7-4a04-47fb-aa09-a2155912c60c
A94: 81 | B94: 62014CC0248.md | C94: Bulletin article | D94: EU | E94: 339a87b5-3e47-45f8-9184-ec4d2919899c
A95: 82 | B95: 62017TJ0240.md | C95: Court Decision | D95: EU | E95: 13277655-c149-434f-8ecc-63d7d1017b10
A96: 83 | B96: 62018CJ0607.md | C96: Court Decision | D96: EU | E96: fcc024df-7fa5-407e-9fb8-ca0374628e37
A97: 84 | B97: 62016CJ0123.md | C97: Court Decision | D97: EU | E97: 22252c77-2086-4d9e-94b7-b7219394e299
A98: 85 | B98: 62014TJ0103.md | C98: Bulletin article | D98: EU | E98: 71644769-41f5-4da2-82b3-225292de42cb
A99: 86 | B99: 62011TJ0090.md | C99: Court Decision | D99: EU | E99: 197c7e77-a1de-4f47-ac70-5bda9b6053b2
A100: 87 | B100: 96291-the-eu-court-of-justice-upholds-the-commissions-right-to-continue-inspection-at.md | C100: Bulletin article | E100: b5945681-864a-4470-b1bb-33978a2016ed
...

Sheet Q29
A1: Q29 — Expert Review
A2: Question metadata
A3: Question ID | B3: 29
A4: Topic | B4: Dawn raids — the inspection decision
A5: Scope | B5: France
A6: Original reviewer | B6: Jeanne
A7: Original status | B7: Approved
A8: Question | B8: How specific must a French dawn-raid authorisation be about the premises to be visited, the practices suspected, and the period covered? What has been held insufficient?
A9: Generated answer
A10: Paste the generated answer here.
A11: Run ID | C11: Run date
A12: Retrieval set review
A13: Rank | B13: Document name | C13: Document class | D13: Jurisdiction | E13: URL / Document ID | F13: Required source? | G13: Expert verdict | H13: Notes
A14: 1
A15: 2
A16: 3
A17: 4
A18: 5
A19: 6
A20: 7
A21: 8
A22: 9
A24: Claim-by-claim review
A25: Claim ID | B25: Claim from answer | C25: Cited document | D25: Expert verdict | E25: Cited passage | F25: Required fix / comment
A26: 1
A27: 2
A28: 3
A29: 4
A30: 5
A31: 6
A32: 7
A33: 8
A34: 9
A36: Final expert verdict
A37: Reviewer
A38: Is the answer acceptable?
A39: Overall comment / required fixes
A40: Review completed?
A69: Original source notes
A70: WAB notes | B70: Possible overlap with question 33.
A71: Reviewer notes from question approval | B71: no overlap with question 33, we can keep the question.

Sheet Q30
A1: Q30 — Expert Review
A2: Question metadata
A3: Question ID | B3: 30
A4: Topic | B4: Dawn raids — obstruction and seals
A5: Scope | B5: EU
A6: Original reviewer | B6: Carolina
A7: Original status | B7: Approved
A8: Question | B8: Does the obstruction regime of Article 23(1) of Regulation 1/2003 — conceived for physical records and corporate email — still fit an environment of ephemeral, encrypted messaging on employees' personal devices? Where does the deletion of a WhatsApp or Signal message during or ahead of an inspection cross from ordinary personal housekeeping into a sanctionable procedural infringement, and how must intent and attribution be established when the device and the account belong to the individual rather than the undertaking?
A9: Generated answer
A10: Paste the generated answer here.
A11: Run ID | C11: Run date
A12: Retrieval set review
A13: Rank | B13: Document name | C13: Document class | D13: Jurisdiction | E13: URL / Document ID | F13: Required source? | G13: Expert verdict | H13: Notes
A14: 1
A15: 2
A16: 3
A17: 4
A18: 5
A19: 6
A20: 7
A21: 8
A22: 9
A24: Claim-by-claim review
A25: Claim ID | B25: Claim from answer | C25: Cited document | D25: Expert verdict | E25: Cited passage | F25: Required fix / comment
A26: 1
A27: 2
A28: 3
A29: 4
A30: 5
A31: 6
A32: 7
A33: 8
A34: 9
A36: Final expert verdict
A37: Reviewer
A38: Is the answer acceptable?
A39: Overall comment / required fixes
A40: Review completed?
A69: Original source notes
A70: WAB notes
A71: Reviewer notes from question approval | B71: Carolina's note: let's use this question instead "Does the obstruction regime of Article 23(1) of Regulation 1/2003 — conceived for physical records and corporate email — still fit an environment of ephemeral, encrypted messaging on employees' personal devices? Where does the deletion of a WhatsApp or Signal message during or ahead of an inspection cross from ordinary personal housekeeping into a sanctionable procedural infringement, and how must intent and attribution be established when the device and the account belong to the individual rather than the undertaking?"

Sheet Q31
A1: Q31 — Expert Review
A2: Question metadata
A3: Question ID | B3: 31
A4: Topic | B4: Dawn raids — obstruction and seals
A5: Scope | B5: EU
A6: Original reviewer | B6: Carolina
A7: Original status | B7: Approved
A8: Question | B8: To what extent may an undertaking be fined for the breaking of a seal in the absence of any fault or intent, and how is that reconciled with the presumption of innocence?
A9: Generated answer
A10: Paste the generated answer here.
A11: Run ID | C11: Run date
A12: Retrieval set review
A13: Rank | B13: Document name | C13: Document class | D13: Jurisdiction | E13: URL / Document ID | F13: Required source? | G13: Expert verdict | H13: Notes
A14: 1 | B14: 62008TJ0141.md | C14: Court Decision | D14: EU | E14: 4cc62180-dfa2-4e99-8d8a-324189542e16 | H14: Cited in answer: YES
A15: 2 | B15: inspections-eu-law-2nd--3_chapter_1_-_inspections_upon_decision_regulation_1_2003_article_20_4.md | C15: Book (Livre) | E15: d28b1d20-a2c6-425f-a401-498eab28d744
A16: 3 | B16: 62011CJ0089.md | C16: Court Decision | D16: EU | E16: 23628ecf-7ba6-463d-9416-c186b18e1fa6 | H16: Cited in answer: YES
A17: 4 | B17: competition-case-law-digest-5th--p10.md | C17: Book (Livre) | E17: 65e060cb-bdeb-413d-b4e8-b9ffe0ed3995
A18: 5 | B18: 91494-3080-sanction-the-french-competition-authority-fines-a-company-for-breach-of-sea.md | C18: Bulletin article | E18: 71e5b841-6612-4ab1-b06c-ad0c3a576691
A19: 6 | B19: 93706-0060-dawn-raids-advocate-general-kokott-calls-on-the-court-of-justice-to-uphold.md | C19: Bulletin article | E19: 42a1613c-b25b-476e-a3b4-e1cac9b5add2
A20: 7 | B20: eu-antitrust-enforcement--2_i_regulation_1_2003_an_assessment_after_twenty_years.md | C20: Article (Review) | E20: 55871bec-fbf6-4f9f-9931-66f8481120f2
A21: 8 | B21: 131688-30-inspections-the-general-court-of-the-european-union-upholds-the-european-comm.md | C21: Bulletin article | E21: 7de191c9-0221-423b-b670-ef1e047a0196
A22: 9 | B22: 62014TJ0475.md | C22: Court Decision | D22: EU | E22: cba40d0a-c143-4bc9-af97-af13ef20db3a
A23: 10 | B23: 97110-2850-inspection-the-general-court-of-the-european-union-partially-annuls-decisio.md | C23: Bulletin article | E23: 0ff86075-a215-4bce-ac53-21a9aa21cd71
A24: 11 | B24: 105103.md | C24: Bulletin article | E24: f10e4cc4-d036-4949-b9be-86b79b54fa7d
A25: 12 | B25: 50125.md | C25: Bulletin article | E25: 12c12f97-4ff1-460e-b3ec-87a432e3248d | H25: Cited in answer: YES
A26: 13 | B26: 128250-35-dawn-raids-the-general-court-of-the-european-union-partially-upholds-the-lega.md | C26: Bulletin article | E26: e34c0e6d-2771-4073-8165-4a73eff42d4c
A27: 14 | B27: competition-case-law-digest-5th--p09.md | C27: Book (Livre) | E27: 2f0afdb0-43c8-41b3-99e2-c3003ab906c1
A28: 15 | B28: 62017TJ0799.md | C28: Court Decision | D28: EU | E28: 0e2b9d12-e2ef-4e5a-a4ff-3e040d05d2e9
A29: 16 | B29: 91835.md | C29: Article (Review) | E29: f6ec0179-d152-4059-9a3f-81d669d422b0
A30: 17 | B30: 62017TJ0249.md | C30: Court Decision | D30: EU | E30: dbf7bda8-39fa-4eb5-a6e2-f02b0787cb54
A31: 18 | B31: judicial-review-competition-cases--7_european_union_-_are_there_any_limits_to_unlimited_jurisdiction_judicial_review_of_commission_discretion_in_setting_fines_for_breaches_of_eu_competition_rules.md | C31: Article (Review) | E31: db161723-dcab-4880-a411-5ede0c406c3a
A32: 19 | B32: 62014CC0155.md | C32: Bulletin article | D32: EU | E32: 91bac28d-160b-44ac-8548-a0266f43bdd3
A33: 20 | B33: 57935-361-decisions-adopted-during-an-inspection-the-general-court-reminds-the-commiss.md | C33: Bulletin article | E33: 882aa354-e6cf-464a-b1e2-9486b1cca48f
A34: 21 | B34: 50285.md | C34: Bulletin article | E34: f17418b6-489e-4049-92f0-b9ce2b58968f
A35: 22 | B35: 127186-20-inspection-the-general-court-of-the-european-union-considers-that-the-commiss.md | C35: Bulletin article | E35: 329bd68b-1104-4f5c-b636-e9925175dbc6
A36: 23 | B36: 62014CC0373.md | C36: Bulletin article | D36: EU | E36: 4a4b14bb-85ff-4118-89e5-bbe883bbbf6f
A37: 24 | B37: 62023CJ0031.md | C37: Court Decision | D37: EU | E37: 27a00cb7-0235-44dc-96ab-a0b2dc338ae2
A38: 25 | B38: competition-case-law-digest-5th--p03.md | C38: Book (Livre) | E38: 7f6e4945-ae8e-4226-a870-8594977f3130
A39: 26 | B39: 54659.md | C39: Bulletin article | E39: 375b8d61-6e36-4a94-a867-bb58342c68ac | H39: Cited in answer: YES
A40: 27 | B40: competition-case-law-digest-5th--p18.md | C40: Book (Livre) | E40: 809791e0-9f7f-4654-a1cb-08568b608c2d
A41: 28 | B41: 62018CJ0601.md | C41: Court Decision | D41: EU | E41: d94571df-d56d-45c1-a02e-834714984963
A42: 29 | B42: 125471-20-dawn-raids-the-general-court-upholds-the-european-commissions-overall-assessm.md | C42: Bulletin article | E42: e97ed81a-60ca-4112-9207-21a8613078bd
A43: 30 | B43: 62011TJ0289.md | C43: Court Decision | D43: EU | E43: 7ecb1eda-828c-4ed1-831c-9ba3cd309425
A44: 31 | B44: 62020CJ0693.md | C44: Court Decision | D44: EU | E44: 74ccf3f4-5d27-4c74-9208-62829cc5bcf1
A45: 32 | B45: 62014TJ0691.md | C45: Court Decision | D45: EU | E45: 29822ba5-b389-4ac8-b2c3-e877ae057dae
A46: 33 | B46: 121144.md | C46: Bulletin article | E46: 9f96a5ff-2537-45cd-a34f-b0f82767f132
A47: 34 | B47: 62018CC0606.md | C47: Article (Review) | D47: EU | E47: 0655b4ec-4821-4b46-91b6-b6ddaebd8d5d
A48: 35 | B48: 62012TJ0272.md | C48: Court Decision | D48: EU | E48: 5955aed3-ab0f-4414-a06a-9abbbc834dab
A49: 36 | B49: 96586.md | C49: Article (Review) | E49: 4cb5c154-4d3a-46c3-8bca-8f09c7e6c562
A50: 37 | B50: 62020CC0377.md | C50: Bulletin article | D50: EU | E50: 0be6fa29-444a-4309-9fcb-db98a194eb98
A51: 38 | B51: 62010TJ0027.md | C51: Court Decision | D51: EU | E51: bc02167d-8c4b-4b56-831c-f9c775215394
A52: 39 | B52: 62019CC0883.md | C52: Court Decision | D52: EU | E52: d0b07834-6630-4196-a01e-66dbde751361
A53: 40 | B53: 87921.md | C53: Article (Review) | E53: 0e8b0115-34a2-49dd-adf0-d5c7fd213d2b
A54: 41 | B54: 62009TJ0286(01).md | C54: Court Decision | D54: EU | E54: 74962cec-aae6-4e27-be02-e1330bbc7016
A55: 42 | B55: 127929-the-eu-general-court-upholds-the-commissions-inspection-methodology-based-on-pub.md | C55: Bulletin article | E55: af2e8c94-00c3-40d4-8e35-233542ca536d
A56: 43 | B56: 62013CJ0093.md | C56: Court Decision | D56: EU | E56: c5743b22-59b0-4e9b-81eb-65a38ee24ded
A57: 44 | B57: antitrust-digital-economy--p02.md | C57: Book (Livre) | E57: 34eb60b4-07b4-42bc-a415-26d07058256e
A58: 45 | B58: 79963.md | C58: Article (Review) | E58: b0c5f913-948d-4dcc-9ea4-98f6136ca5a7
A59: 46 | B59: competition-case-law-digest-5th--p11.md | C59: Book (Livre) | E59: 40351206-cbf5-40d8-a127-173a24162f6e
A60: 47 | B60: 62014TJ0682.md | C60: Court Decision | D60: EU | E60: 379ce84c-817a-4c5d-ab28-068e642c5c00
A61: 48 | B61: 62018CJ0606.md | C61: Court Decision | D61: EU | E61: 2d074327-045b-484e-8bbc-1a0f9c7ed660
A62: 49 | B62: 95849-3360-inspections-the-court-of-justice-of-the-european-union-gives-the-commission.md | C62: Bulletin article | E62: afe07022-9e8e-4270-a8d4-2c0aaa70652f
A63: 50 | B63: inspections-eu-law-2nd--4_chapter_2_-_inspections_upon_authorisation_regulation_1_2003_article_20_3.md | C63: Book (Livre) | E63: 303ee9d6-4f67-4e00-a80a-195318e324af
A64: 51 | B64: 62014TJ0449.md | C64: Court Decision | D64: EU | E64: 2f594756-bc0a-4332-829f-e65319b3211c
A65: 52 | B65: 62019CJ0440.md | C65: Court Decision | D65: EU | E65: 6b42430f-5188-454f-b88c-1b61c887e740
A66: 53 | B66: 62012CJ0238.md | C66: Court Decision | D66: EU | E66: d3c3e52b-5c1a-4b38-9789-9389e1db12d6
A67: 54 | B67: 62016TJ0433.md | C67: Court Decision | D67: EU | E67: cb3d4ba1-924b-4a42-b093-a16cdb3cbc40
A68: 55 | B68: 62019CJ0164.md | C68: Court Decision | D68: EU | E68: 3872faf4-4481-4304-9c4c-5817225f5556
A69: 56 | B69: 62019CC0440.md | C69: Article (Review) | D69: EU | E69: 94d57b7e-923e-4001-a6dc-7beb60464156
A70: 57 | B70: 62018TJ0425.md | C70: Court Decision | D70: EU | E70: 840826ce-05c9-4b6c-a758-4d8e43087d6d
A71: 58 | B71: 62019CJ0166.md | C71: Court Decision | D71: EU | E71: 7db4e755-cdb4-431e-a261-3651dc96db83
A72: 59 | B72: 62022TJ0084.md | C72: Court Decision | D72: EU | E72: dddb0eaf-bfa6-45a0-87f7-59ef954decf0
A73: 60 | B73: 97568-3340-investigation-the-court-of-justice-of-the-european-union-recognizes-the-eur.md | C73: Bulletin article | E73: 0a9a6620-916c-4d26-8e97-e91a08871183
A74: 61 | B74: 77256.md | C74: Bulletin article | E74: c9e1ccc6-fb57-4f51-a309-ad5610b44ca4
A75: 62 | B75: 96910-3420-dawn-raids-the-court-of-justice-of-the-european-union-confirms-the-power-of.md | C75: Bulletin article | E75: a95ca40b-ceae-4436-8de6-a7a126b177e3
A76: 63 | B76: judicial-review-competition-cases--11_hong_kong_-_the_impact_of_fundamental_rights_on_judicial_review_in_hong_kong_competition_law.md | C76: Article (Review) | E76: 9553d170-0780-434d-ae17-4244a7a6174f
A77: 64 | B77: eu-antitrust-enforcement--11_x_fundamental_procedural_rights_and_effective_enforcement_of_articles_101_and_102_tfeu_in_the_european_competition_network.md | C77: Book (Livre) | E77: 44d971b2-9615-45f5-94c3-342633964481
A78: 65 | B78: 62013CC0293.md | C78: Bulletin article | D78: EU | E78: 263a5c3a-ec5b-45f5-8742-bb183e535585
A79: 66 | B79: 62014TJ0704.md | C79: Court Decision | D79: EU | E79: 5a5789e0-67b0-47cd-8cf8-593c8a0c2663
A80: 67 | B80: 62014TJ0679.md | C80: Court Decision | D80: EU | E80: 9cafaa99-eee3-446a-a109-cf71f0b793f0
A81: 68 | B81: 62009TJ0286.md | C81: Court Decision | D81: EU | E81: cc5062a8-375f-4cbf-bb7f-f12fede3a709
A82: 69 | B82: 62004TJ0340.md | C82: Court Decision | D82: EU | E82: d9fb7f73-952b-4b71-a502-6f63b7f95073
A83: 70 | B83: 111517.md | C83: Bulletin article | E83: 9f4ffd59-c022-4300-938a-2b854b1bd91b
A84: 71 | B84: 62018TJ0604.md | C84: Court Decision | D84: EU | E84: bcc538ee-5aef-45cb-b7ae-77997761f325
A85: 72 | B85: 62019CC0212.md | C85: Bulletin article | D85: EU | E85: e28504f4-d37a-4976-9f02-bedc6fd39abe
A86: 73 | B86: 93368-2520-investigations-the-court-of-justice-of-the-european-union-rules-that-an-act.md | C86: Bulletin article | E86: eb4af447-a8d7-4102-8c9b-20f8865d5fea
A87: 74 | B87: 62018CJ0595.md | C87: Court Decision | D87: EU | E87: 9cef1570-4dfe-4218-9740-d8f6d239921b
A88: 75 | B88: 96291-the-eu-court-of-justice-upholds-the-commissions-right-to-continue-inspection-at.md | C88: Bulletin article | E88: b5945681-864a-4470-b1bb-33978a2016ed
A89: 76 | B89: eu-antitrust-enforcement--15_xiv_procedural_rights_and_obligations_of_third_parties_in_antitrust_investigations_and_proceedings_by_the_european_commission.md | C89: Book (Livre) | E89: b2429dd2-ef75-4f34-8bf2-95b08c3a4de5
A90: 77 | B90: 62019CJ0144.md | C90: Court Decision | D90: EU | E90: e647276f-29ce-4d0f-8283-ae7ca504c2f0
A91: 78 | B91: 62016CJ0123.md | C91: Court Decision | D91: EU | E91: 22252c77-2086-4d9e-94b7-b7219394e299
A92: 79 | B92: 94920-2150-inquiries-the-court-of-justice-of-the-european-union-dismisses-appeals-brou.md | C92: Bulletin article | E92: e7e462f6-8d3e-4f46-92a9-57edcae44fd8
A93: 80 | B93: 62019CC0882.md | C93: Court Decision | D93: EU | E93: 2c7a71bd-7e78-4de7-8c4b-b53a884d2a3a
A94: 81 | B94: 62015TJ0180.md | C94: Court Decision | D94: EU | E94: 90270bb0-7eec-4e94-84af-da67e9e0c14f
A95: 82 | B95: 87398.md | C95: Article (Review) | E95: b475e74d-8ef8-4d61-8a63-efbb64eb9ec3
A96: 83 | B96: 62008TJ0551.md | C96: Court Decision | D96: EU | E96: ca11741a-b7bd-42f4-8f09-0236d569e94c
A97: 84 | B97: 62017CJ0099.md | C97: Court Decision | D97: EU | E97: 14d53621-6d37-44ec-a6ef-0c6671582da0
A98: 85 | B98: 62020CJ0682.md | C98: Court Decision | D98: EU | E98: 408cfe67-7fe4-45a8-9c3e-de39d86d56cb
A99: 86 | B99: judicial-review-competition-cases--15_poland_-_intensity_of_judicial_review_of_decisions_on_competition_protection_in_polish_law.md | C99: Article (Review) | E99: 1860320d-3678-486f-b0a4-66f57380533d
A100: 87 | B100: 62014CJ0033.md | C100: Court Decision | D100: EU | E100: 416f824d-8129-498b-86b2-330a30a0f664
...

Sheet Q32
A1: Q32 — Expert Review
A2: Question metadata
A3: Question ID | B3: 32
A4: Topic | B4: Dawn raids — obstruction and seals
A5: Scope | B5: France
A6: Original reviewer | B6: Jeanne
A7: Original status | B7: Approved
A8: Question | B8: What behavior during a French dawn raid (OVS) exposes a company to obstruction liability, and what training precautions follow from recent enforcement?
A9: Generated answer
A10: Paste the generated answer here.
A11: Run ID | C11: Run date
A12: Retrieval set review
A13: Rank | B13: Document name | C13: Document class | D13: Jurisdiction | E13: URL / Document ID | F13: Required source? | G13: Expert verdict | H13: Notes
A14: 1
A15: 2
A16: 3
A17: 4
A18: 5
A19: 6
A20: 7
A21: 8
A22: 9
A24: Claim-by-claim review
A25: Claim ID | B25: Claim from answer | C25: Cited document | D25: Expert verdict | E25: Cited passage | F25: Required fix / comment
A26: 1
A27: 2
A28: 3
A29: 4
A30: 5
A31: 6
A32: 7
A33: 8
A34: 9
A36: Final expert verdict
A37: Reviewer
A38: Is the answer acceptable?
A39: Overall comment / required fixes
A40: Review completed?
A69: Original source notes
A70: WAB notes
A71: Reviewer notes from question approval | B71: Question to be replaced by this one : What behavior during a French dawn raid (OVS) exposes a company to obstruction liability, and what training precautions follow from recent enforcement?

Sheet Q33
A1: Q33 — Expert Review
A2: Question metadata
A3: Question ID | B3: 33
A4: Topic | B4: Dawn raids — obstruction and preservation of evidence
A5: Scope | B5: US
A6: Original reviewer | B6: Arthur
A7: Original status | B7: Approved
A8: Question | B8: What consequences may follow from obstructing an actual or contemplated federal antitrust investigation, including by destroying, altering, or concealing evidence, and when do separate legal obligations to preserve potentially relevant evidence arise?
A9: Generated answer
A10: Paste the generated answer here.
A11: Run ID | C11: Run date
A12: Retrieval set review
A13: Rank | B13: Document name | C13: Document class | D13: Jurisdiction | E13: URL / Document ID | F13: Required source? | G13: Expert verdict | H13: Notes
A14: 1
A15: 2
A16: 3
A17: 4
A18: 5
A19: 6
A20: 7
A21: 8
A22: 9
A24: Claim-by-claim review
A25: Claim ID | B25: Claim from answer | C25: Cited document | D25: Expert verdict | E25: Cited passage | F25: Required fix / comment
A26: 1
A27: 2
A28: 3
A29: 4
A30: 5
A31: 6
A32: 7
A33: 8
A34: 9
A36: Final expert verdict
A37: Reviewer
A38: Is the answer acceptable?
A39: Overall comment / required fixes
A40: Review completed?

Sheet Q34
A1: Q34 — Expert Review
A2: Question metadata
A3: Question ID | B3: 34
A4: Topic | B4: Dawn raids — questioning staff
A5: Scope | B5: EU
A6: Original reviewer | B6: Carolina
A7: Original status | B7: Approved
A8: Question | B8: To what extent may the Commission compel answers under Article 20(2)(e) of Regulation 1/2003 before the privilege against self-incrimination intervenes — and how the distinction between answering questions of fact and admitting an infringement remain workable in practice?
A9: Generated answer
A10: Paste the generated answer here.
A11: Run ID | C11: Run date
A12: Retrieval set review
A13: Rank | B13: Document name | C13: Document class | D13: Jurisdiction | E13: URL / Document ID | F13: Required source? | G13: Expert verdict | H13: Notes
A14: 1
A15: 2
A16: 3
A17: 4
A18: 5
A19: 6
A20: 7
A21: 8
A22: 9
A24: Claim-by-claim review
A25: Claim ID | B25: Claim from answer | C25: Cited document | D25: Expert verdict | E25: Cited passage | F25: Required fix / comment
A26: 1
A27: 2
A28: 3
A29: 4
A30: 5
A31: 6
A32: 7
A33: 8
A34: 9
A36: Final expert verdict
A37: Reviewer
A38: Is the answer acceptable?
A39: Overall comment / required fixes
A40: Review completed?
A69: Original source notes
A70: WAB notes
A71: Reviewer notes from question approval | B71: agreed on the substance but let's frame it in the following way: "To what extent may the Commission compel answers under Article 20(2)(e) of Regulation 1/2003 before the privilege against self-incrimination intervenes — and how the distinction between answering questions of fact and admitting an infringement remain workable in practice?"

Sheet Q35
A1: Q35 — Expert Review
A2: Question metadata
A3: Question ID | B3: 35
A4: Topic | B4: Dawn raids — questioning staff
A5: Scope | B5: France
A6: Original reviewer | B6: Jeanne
A7: Original status | B7: Approved
A8: Question | B8: Can employees be required to answer questions during a French dawn raid, and what protection against self-incrimination do they and the company have?
A9: Generated answer
A10: Paste the generated answer here.
A11: Run ID | C11: Run date
A12: Retrieval set review
A13: Rank | B13: Document name | C13: Document class | D13: Jurisdiction | E13: URL / Document ID | F13: Required source? | G13: Expert verdict | H13: Notes
A14: 1
A15: 2
A16: 3
A17: 4
A18: 5
A19: 6
A20: 7
A21: 8
A22: 9
A24: Claim-by-claim review
A25: Claim ID | B25: Claim from answer | C25: Cited document | D25: Expert verdict | E25: Cited passage | F25: Required fix / comment
A26: 1
A27: 2
A28: 3
A29: 4
A30: 5
A31: 6
A32: 7
A33: 8
A34: 9
A36: Final expert verdict
A37: Reviewer
A38: Is the answer acceptable?
A39: Overall comment / required fixes
A40: Review completed?
A69: Original source notes
A70: WAB notes
A71: Reviewer notes from question approval | B71: We can keep this one

Sheet Q36
A1: Q36 — Expert Review
A2: Question metadata
A3: Question ID | B3: 36
A4: Topic | B4: Dawn raids — questioning staff
A5: Scope | B5: US
A6: Original reviewer | B6: Arthur
A7: Original status | B7: Approved
A8: Question | B8: How does the Fifth Amendment privilege against self-incrimination apply in a U.S. antitrust investigation to compelled oral testimony versus the production of documents? Why does the privilege belong to natural persons rather than corporations, and how does the collective-entity doctrine affect an individual custodian who is required to produce corporate records?
A9: Generated answer
A10: Paste the generated answer here.
A11: Run ID | C11: Run date
A12: Retrieval set review
A13: Rank | B13: Document name | C13: Document class | D13: Jurisdiction | E13: URL / Document ID | F13: Required source? | G13: Expert verdict | H13: Notes
A14: 1
A15: 2
A16: 3
A17: 4
A18: 5
A19: 6
A20: 7
A21: 8
A22: 9
A24: Claim-by-claim review
A25: Claim ID | B25: Claim from answer | C25: Cited document | D25: Expert verdict | E25: Cited passage | F25: Required fix / comment
A26: 1
A27: 2
A28: 3
A29: 4
A30: 5
A31: 6
A32: 7
A33: 8
A34: 9
A36: Final expert verdict
A37: Reviewer
A38: Is the answer acceptable?
A39: Overall comment / required fixes
A40: Review completed?

Sheet Q37
A1: Q37 — Expert Review
A2: Question metadata
A3: Question ID | B3: 37
A4: Topic | B4: Dawn raids — electronic data
A5: Scope | B5: EU
A6: Original reviewer | B6: Carolina
A7: Original status | B7: Approved
A8: Question | B8: May the Commission take a forensic copy of a company's electronic data and carry on examining it at its own premises after the inspection has ended? What safeguards apply, and what rights does the company keep over that copy?
A9: Generated answer
A10: Paste the generated answer here.
A11: Run ID | C11: Run date
A12: Retrieval set review
A13: Rank | B13: Document name | C13: Document class | D13: Jurisdiction | E13: URL / Document ID | F13: Required source? | G13: Expert verdict | H13: Notes
A14: 1 | B14: inspections-eu-law-2nd--3_chapter_1_-_inspections_upon_decision_regulation_1_2003_article_20_4.md | C14: Book (Livre) | E14: d28b1d20-a2c6-425f-a401-498eab28d744
A15: 2 | B15: 62014TJ0449.md | C15: Court Decision | D15: EU | E15: 2f594756-bc0a-4332-829f-e65319b3211c | H15: Cited in answer: YES
A16: 3 | B16: 62018CC0606.md | C16: Article (Review) | D16: EU | E16: 0655b4ec-4821-4b46-91b6-b6ddaebd8d5d | H16: Cited in answer: YES
A17: 4 | B17: 62014TJ0475.md | C17: Court Decision | D17: EU | E17: cba40d0a-c143-4bc9-af97-af13ef20db3a
A18: 5 | B18: 57935-361-decisions-adopted-during-an-inspection-the-general-court-reminds-the-commiss.md | C18: Bulletin article | E18: 882aa354-e6cf-464a-b1e2-9486b1cca48f
A19: 6 | B19: 62018CJ0606.md | C19: Court Decision | D19: EU | E19: 2d074327-045b-484e-8bbc-1a0f9c7ed660 | H19: Cited in answer: YES
A20: 7 | B20: 128250-35-dawn-raids-the-general-court-of-the-european-union-partially-upholds-the-lega.md | C20: Bulletin article | E20: e34c0e6d-2771-4073-8165-4a73eff42d4c
A21: 8 | B21: 93706-0060-dawn-raids-advocate-general-kokott-calls-on-the-court-of-justice-to-uphold.md | C21: Bulletin article | E21: 42a1613c-b25b-476e-a3b4-e1cac9b5add2
A22: 9 | B22: 97110-2850-inspection-the-general-court-of-the-european-union-partially-annuls-decisio.md | C22: Bulletin article | E22: 0ff86075-a215-4bce-ac53-21a9aa21cd71
A23: 10 | B23: 125471-20-dawn-raids-the-general-court-upholds-the-european-commissions-overall-assessm.md | C23: Bulletin article | E23: e97ed81a-60ca-4112-9207-21a8613078bd
A24: 11 | B24: 131688-30-inspections-the-general-court-of-the-european-union-upholds-the-european-comm.md | C24: Bulletin article | E24: 7de191c9-0221-423b-b670-ef1e047a0196
A25: 12 | B25: 62018CJ0601.md | C25: Court Decision | D25: EU | E25: d94571df-d56d-45c1-a02e-834714984963
A26: 13 | B26: eu-antitrust-enforcement--12_xi_the_role_of_the_hearing_officer_in_antitrust_proceedings_before_the_european_commission.md | C26: Book (Livre) | E26: 27d55d8c-5b59-43c1-8576-7a718bd009d4
A27: 14 | B27: 96586.md | C27: Article (Review) | E27: 4cb5c154-4d3a-46c3-8bca-8f09c7e6c562
A28: 15 | B28: 127929-the-eu-general-court-upholds-the-commissions-inspection-methodology-based-on-pub.md | C28: Bulletin article | E28: af2e8c94-00c3-40d4-8e35-233542ca536d
A29: 16 | B29: 127186-20-inspection-the-general-court-of-the-european-union-considers-that-the-commiss.md | C29: Bulletin article | E29: 329bd68b-1104-4f5c-b636-e9925175dbc6
A30: 17 | B30: 62011TJ0289.md | C30: Court Decision | D30: EU | E30: 7ecb1eda-828c-4ed1-831c-9ba3cd309425
A31: 18 | B31: competition-inspections-25-jurisdictions--7_european_union.md | C31: Article (Review) | E31: 1c2fa592-34f0-4656-96c2-024c5ea88b1e | H31: Cited in answer: YES
A32: 19 | B32: 67860.md | C32: Bulletin article | E32: f3b54f3e-52e4-4232-8e7a-129fe9239fec
A33: 20 | B33: eu-antitrust-enforcement--10_ix_the_compatibility_with_fundamental_rights_of_the_eu_antitrust_enforcement_system_in_which_the_european_commission_acts_both_as_investigator_and_as_first_instance_decision_maker.md | C33: Article (Review) | E33: 2c996db6-dd0f-46f5-be34-12be8f73b817
A34: 21 | B34: competition-inspections-25-jurisdictions--2_austria.md | C34: Article (Review) | E34: ec7e95f2-ae1b-4c2b-9635-0ae49e53ba19
A35: 22 | B35: competition-inspections-25-jurisdictions--23_sweden.md | C35: Article (Review) | E35: dcf6ff3a-fc96-4095-bbc3-ecdd4afa4808
A36: 23 | B36: 62017TJ0249.md | C36: Court Decision | D36: EU | E36: dbf7bda8-39fa-4eb5-a6e2-f02b0787cb54
A37: 24 | B37: 95849-3360-inspections-the-court-of-justice-of-the-european-union-gives-the-commission.md | C37: Bulletin article | E37: afe07022-9e8e-4270-a8d4-2c0aaa70652f
A38: 25 | B38: competition-case-law-digest-5th--p09.md | C38: Book (Livre) | E38: 2f0afdb0-43c8-41b3-99e2-c3003ab906c1
A39: 26 | B39: 103260-35-necessary-limits-to-the-commission-s-inspection-powers.md | C39: Article (Review) | E39: bef18b4b-bb03-49c0-a7aa-afed485ec5d2
A40: 27 | B40: 123082.md | C40: Bulletin article | E40: 18ab192b-10fe-48eb-95a5-bfcc61cd2c9d
A41: 28 | B41: 81215.md | C41: Article (Review) | E41: 1326c749-4c6d-42ec-974e-b228dd1bf722
A42: 29 | B42: 131258-the-eu-general-court-dismisses-an-action-challenging-commission-s-inspection-pow.md | C42: Bulletin article | E42: b5e40090-4f79-422a-997e-8eaa7a359c88
A43: 30 | B43: 62020CJ0682.md | C43: Court Decision | D43: EU | E43: 408cfe67-7fe4-45a8-9c3e-de39d86d56cb
A44: 31 | B44: 62014CC0033.md | C44: Bulletin article | D44: EU | E44: 1dfad74b-fd57-47bb-bfab-18e86ff8d695
A45: 32 | B45: eu-antitrust-enforcement--17_xvi_re_adoption_by_the_european_commission_of_cartel_decisions_annulled_on_procedural_grounds_by_the_eu_courts.md | C45: Article (Review) | E45: 71ba5e7f-b51e-4068-b010-b7e7f422add9
A46: 33 | B46: 62009TJ0135.md | C46: Court Decision | D46: EU | E46: 10418f10-8b6f-4bcc-adf6-39e168b49440
A47: 34 | B47: 62014CJ0413.md | C47: Court Decision | D47: EU | E47: 72ccc95a-3fea-4dbb-b7f6-3d6b4b3fd958
A48: 35 | B48: 62010TJ0391.md | C48: Court Decision | D48: EU | E48: 5f2ef93f-f3a7-4390-b273-c71155847140
A49: 36 | B49: 62023CC0070.md | C49: Bulletin article | D49: EU | E49: 2a493229-62c6-48e3-be4c-c06477e996fc
A50: 37 | B50: 129745.md | C50: Bulletin article | E50: d77ab0a2-b289-4ca9-981f-ff910bb4451b
A51: 38 | B51: eu-antitrust-enforcement--15_xiv_procedural_rights_and_obligations_of_third_parties_in_antitrust_investigations_and_proceedings_by_the_european_commission.md | C51: Book (Livre) | E51: b2429dd2-ef75-4f34-8bf2-95b08c3a4de5
A52: 39 | B52: judicial-review-competition-cases--7_european_union_-_are_there_any_limits_to_unlimited_jurisdiction_judicial_review_of_commission_discretion_in_setting_fines_for_breaches_of_eu_competition_rules.md | C52: Article (Review) | E52: db161723-dcab-4880-a411-5ede0c406c3a
A53: 40 | B53: 62015CO0523.md | C53: Court Decision | D53: EU | E53: b66f8514-c7d7-4322-9e3d-b85b2b24d658
A54: 41 | B54: AT.39226-DEC_0F3A3B18-111D-43A8-836E-D0A7EA9CD4E1_-ATT8310.md | C54: Regulatory Decision | D54: EU | E54: 530c713d-168b-4e73-828b-429d06bf028f
A55: 42 | B55: 62014CJ0033.md | C55: Court Decision | D55: EU | E55: 416f824d-8129-498b-86b2-330a30a0f664
A56: 43 | B56: 62020CC0376.md | C56: Court Decision | D56: EU | E56: cebd4962-06e0-43a6-ac13-b9cc9b05c9e7
A57: 44 | B57: 62019CJ0563.md | C57: Court Decision | D57: EU | E57: e913f312-653c-49c1-b77a-4a633a3b4bfc
A58: 45 | B58: 62011TJ0479.md | C58: Court Decision | D58: EU | E58: 90b1484a-0221-4975-aa87-a00b163ae751
A59: 46 | B59: 58160.md | C59: Bulletin article | E59: 9230c853-1214-4548-9896-650afa1d0132
A60: 47 | B60: 105103.md | C60: Bulletin article | E60: f10e4cc4-d036-4949-b9be-86b79b54fa7d
A61: 48 | B61: 62023CJ0258.md | C61: Court Decision | D61: EU | E61: 5aa970eb-b95b-47f7-848c-8251ba16e8bc
A62: 49 | B62: 62018CJ0312.md | C62: Court Decision | D62: EU | E62: 08dfceb2-3d7f-4ffa-9cfb-5b557d7cae14
A63: 50 | B63: 62017CJ0114.md | C63: Court Decision | D63: EU | E63: 3a7152cd-6afa-4e4f-8c45-eaaf4bc248a6
A64: 51 | B64: 62016CJ0128.md | C64: Court Decision | D64: EU | E64: 59490de3-8af2-4a5c-aa9b-14f059c7301f
A65: 52 | B65: 62024CO0089(01).md | C65: Court Decision | D65: EU | E65: c937b817-5c56-4e36-8458-4a937aa0c4a4
A66: 53 | B66: m10262.md | C66: Regulatory Decision | D66: EU | E66: 371d0689-523b-4cfd-b127-c2e6980e3905
A67: 54 | B67: 62022CJ0381.md | C67: Court Decision | D67: EU | E67: 71722674-1979-43b0-b9fb-45efc66190fe
A68: 55 | B68: 62021CC0127.md | C68: Bulletin article | D68: EU | E68: dbfdd0df-0a72-4d2b-ba4d-e1e7ead79ba5
A69: 56 | B69: 62019CJ0466.md | C69: Court Decision | D69: EU | E69: d689bd0f-f033-4a3f-b10f-6ff4843115fe
A70: 57 | B70: 62022CJ0588.md | C70: Court Decision | D70: EU | E70: 0979c7ef-861a-452d-8976-0e0c34984b26
A71: 58 | B71: 82445.md | C71: Article (Review) | E71: 1be45df1-87e1-4ba2-bdd9-76e5fe184f97
A72: 59 | B72: 62023CJ0469.md | C72: Court Decision | D72: EU | E72: a84d24e9-3bea-4652-8dc3-644d6a4adcea
A73: 60 | B73: 62016CC0127.md | C73: Bulletin article | D73: EU | E73: 4c7242f9-9257-43fb-b899-956982e01af3
A74: 61 | B74: 62022CC0710.md | C74: Bulletin article | D74: EU | E74: 80298346-8dbb-46c6-a5bb-6cef92615f48
A75: 62 | B75: competition-inspections-25-jurisdictions--6_czech_republic.md | C75: Article (Review) | E75: 08f914a6-de6d-4956-ab36-2b0f38bbe6b1
A76: 63 | B76: 62017CC0099.md | C76: Bulletin article | D76: EU | E76: 8e8bced1-37dc-412f-ba1b-7dfd92e6c516
A77: 64 | B77: 62014CJ0247.md | C77: Court Decision | D77: EU | E77: df8c7156-3176-4c1f-8b15-ec687b386142
A78: 65 | B78: 100066.md | C78: Bulletin article | E78: cf5bb273-df83-4359-89b3-f6c951998319
A79: 66 | B79: competition-case-law-digest-5th--p10.md | C79: Book (Livre) | E79: 65e060cb-bdeb-413d-b4e8-b9ffe0ed3995
A80: 67 | B80: 62014TJ0447.md | C80: Court Decision | D80: EU | E80: aef64236-c9f7-4cf3-b707-108a4788237a
A81: 68 | B81: 62021CC0124.md | C81: Bulletin article | D81: EU | E81: b3a3307a-ef8c-4201-9ba6-9f545169d731
A82: 69 | B82: 62012CJ0533.md | C82: Court Decision | D82: EU | E82: 1b83fc6f-23d8-430a-bc98-6c6d212694cb
A83: 70 | B83: 62023TJ0263.md | C83: Court Decision | D83: EU | E83: 16791fea-a958-4950-92a6-5a1b65fb3a04
A84: 71 | B84: 62016CJ0438.md | C84: Court Decision | D84: EU | E84: 4e193755-9e03-49a1-bd07-727bc33bd6fe
A85: 72 | B85: 62019CJ0160.md | C85: Court Decision | D85: EU | E85: b909ae04-0469-4faf-a32c-037f231befa9
A86: 73 | B86: 62014CO0291.md | C86: Court Decision | D86: EU | E86: f7ba2f7e-59c8-4e8a-9987-b6c312dd273c
A87: 74 | B87: competition-inspections-25-jurisdictions--27_united_kingdom.md | C87: Article (Review) | E87: 5261e3c8-c961-4df0-a163-1e489d633173
A88: 75 | B88: 62011TJ0479(01).md | C88: Court Decision | D88: EU | E88: 07ad3a2d-7c73-4692-8d66-691144bafcda
A89: 76 | B89: 62013TJ0454.md | C89: Court Decision | D89: EU | E89: 13f96c8f-8068-4f0e-85e3-db089fa1364f
A90: 77 | B90: 62018CJ0403.md | C90: Court Decision | D90: EU | E90: 5b155c4b-0345-4afa-8dee-d56351895c8f
A91: 78 | B91: 62015CC0467.md | C91: Court Decision | D91: EU | E91: 6258d26c-7799-4c68-9bde-a5865bbc5c84
A92: 79 | B92: 62015CJ0088.md | C92: Court Decision | D92: EU | E92: 80f4c149-8f30-416e-b690-ada942e3745a
A93: 80 | B93: 62013CJ0603.md | C93: Court Decision | D93: EU | E93: 976727e2-93f1-4a8f-b52f-9f894dfa12db
A94: 81 | B94: 62023CJ0059.md | C94: Court Decision | D94: EU | E94: 8cc32865-be8d-4e30-9d85-465402543a82
A95: 82 | B95: 62021CJ0127.md | C95: Court Decision | D95: EU | E95: f4b45116-6120-413a-ab5f-34f6f1413e14
A96: 83 | B96: 62018CJ0590.md | C96: Court Decision | D96: EU | E96: 1db3fe06-7b9f-4005-ab48-86392aea088a
A97: 84 | B97: 62014TJ0446.md | C97: Court Decision | D97: EU | E97: 0544383c-55cc-41be-80a9-8bbf021f4238
A98: 85 | B98: 62015CJ0588.md | C98: Court Decision | D98: EU | E98: cbfe5e8c-1d2b-4e1f-97dc-7016f799a8bb
A99: 86 | B99: 62013CJ0618.md | C99: Court Decision | D99: EU | E99: 6dfc65f9-0a4e-4de2-9e2d-e07e5063be34
A100: 87 | B100: eu-antitrust-enforcement--13_xii_the_oral_hearing_in_antitrust_proceedings_before_the_european_commission.md | C100: Article (Review) | E100: 8edbd753-7757-4163-9662-1b5feeeadeb4
...

Sheet Q38
A1: Q38 — Expert Review
A2: Question metadata
A3: Question ID | B3: 38
A4: Topic | B4: Dawn raids — electronic data
A5: Scope | B5: EU
A6: Original reviewer | B6: Carolina
A7: Original status | B7: Approved
A8: Question | B8: Whose interests prevail when an inspection captures the private communications of employees who are not themselves under investigation — the Commission's investigative reach, or the privacy protected by Articles 7 and 8 of the Charter? And when does an undertaking's effort to shield that data become obstruction?
A9: Generated answer
A10: Paste the generated answer here.
A11: Run ID | C11: Run date
A12: Retrieval set review
A13: Rank | B13: Document name | C13: Document class | D13: Jurisdiction | E13: URL / Document ID | F13: Required source? | G13: Expert verdict | H13: Notes
A14: 1
A15: 2
A16: 3
A17: 4
A18: 5
A19: 6
A20: 7
A21: 8
A22: 9
A24: Claim-by-claim review
A25: Claim ID | B25: Claim from answer | C25: Cited document | D25: Expert verdict | E25: Cited passage | F25: Required fix / comment
A26: 1
A27: 2
A28: 3
A29: 4
A30: 5
A31: 6
A32: 7
A33: 8
A34: 9
A36: Final expert verdict
A37: Reviewer
A38: Is the answer acceptable?
A39: Overall comment / required fixes
A40: Review completed?
A69: Original source notes
A70: WAB notes
A71: Reviewer notes from question approval | B71: lets replace the question with the following one "Whose interests prevail when an inspection captures the private communications of employees who are not themselves under investigation — the Commission's investigative reach, or the privacy protected by Articles 7 and 8 of the Charter? And when does an undertaking's effort to shield that data become obstruction?"

Sheet Q39
A1: Q39 — Expert Review
A2: Question metadata
A3: Question ID | B3: 39
A4: Topic | B4: Dawn raids — electronic data
A5: Scope | B5: France
A6: Original reviewer | B6: Jeanne
A7: Original status | B7: Approved
A8: Question | B8: Under what conditions can French competition authorities seize entire mailboxes during a dawn raid rather than sorting them on-site, how is the in-scope material subsequently identified, and what happens to material found to be out of scope?
A9: Generated answer
A10: Paste the generated answer here.
A11: Run ID | C11: Run date
A12: Retrieval set review
A13: Rank | B13: Document name | C13: Document class | D13: Jurisdiction | E13: URL / Document ID | F13: Required source? | G13: Expert verdict | H13: Notes
A14: 1
A15: 2
A16: 3
A17: 4
A18: 5
A19: 6
A20: 7
A21: 8
A22: 9
A24: Claim-by-claim review
A25: Claim ID | B25: Claim from answer | C25: Cited document | D25: Expert verdict | E25: Cited passage | F25: Required fix / comment
A26: 1
A27: 2
A28: 3
A29: 4
A30: 5
A31: 6
A32: 7
A33: 8
A34: 9
A36: Final expert verdict
A37: Reviewer
A38: Is the answer acceptable?
A39: Overall comment / required fixes
A40: Review completed?
A69: Original source notes
A70: WAB notes
A71: Reviewer notes from question approval | B71: lets replace the question with the following one : Under what conditions can French competition authorities seize entire mailboxes during a dawn raid rather than sorting on-site, how is the in-scope material subsequently identified, and what happens to material found to be out of scope? The initial version presents the blanket seizure as a given fact, which invites the tool to simply describe it rather than to set out the conditions of its lawfulness precisely the point most disputed in case law (technical necessity, impossibility of on-site sorting, proportionality).

Sheet Q40
A1: Q40 — Expert Review
A2: Question metadata
A3: Question ID | B3: 40
A4: Topic | B4: Dawn raids — electronic data
A5: Scope | B5: US
A6: Original reviewer | B6: Arthur
A7: Original status | B7: Approved
A8: Question | B8: In a criminal U.S. antitrust investigation, when may electronic devices or electronically stored information be seized or copied for later off-site review, and what limits do the search warrant, Rule 41, the Fourth Amendment, and privilege-review procedures impose?
A9: Generated answer
A10: Paste the generated answer here.
A11: Run ID | C11: Run date
A12: Retrieval set review
A13: Rank | B13: Document name | C13: Document class | D13: Jurisdiction | E13: URL / Document ID | F13: Required source? | G13: Expert verdict | H13: Notes
A14: 1
A15: 2
A16: 3
A17: 4
A18: 5
A19: 6
A20: 7
A21: 8
A22: 9
A24: Claim-by-claim review
A25: Claim ID | B25: Claim from answer | C25: Cited document | D25: Expert verdict | E25: Cited passage | F25: Required fix / comment
A26: 1
A27: 2
A28: 3
A29: 4
A30: 5
A31: 6
A32: 7
A33: 8
A34: 9
A36: Final expert verdict
A37: Reviewer
A38: Is the answer acceptable?
A39: Overall comment / required fixes
A40: Review completed?

Sheet Q41
A1: Q41 — Expert Review
A2: Question metadata
A3: Question ID | B3: 41
A4: Topic | B4: Dawn raids — evidence found by accident
A5: Scope | B5: EU
A6: Original reviewer | B6: Carolina
A7: Original status | B7: Approved
A8: Question | B8: May the Commission use evidence of an infringement falling outside the subject matter of the inspection decision? What are the limits imposed by the relevant case law on the use of such incidental findings, and on what conditions may a chance discovery justify a new inspection?
A9: Generated answer
A10: Paste the generated answer here.
A11: Run ID | C11: Run date
A12: Retrieval set review
A13: Rank | B13: Document name | C13: Document class | D13: Jurisdiction | E13: URL / Document ID | F13: Required source? | G13: Expert verdict | H13: Notes
A14: 1 | B14: inspections-eu-law-2nd--3_chapter_1_-_inspections_upon_decision_regulation_1_2003_article_20_4.md | C14: Book (Livre) | E14: d28b1d20-a2c6-425f-a401-498eab28d744
A15: 2 | B15: 62013CC0583.md | C15: Bulletin article | D15: EU | E15: 778d749c-48cb-405c-a58f-962dd3ceef0c | H15: Cited in answer: YES
A16: 3 | B16: competition-case-law-digest-5th--p10.md | C16: Book (Livre) | E16: 65e060cb-bdeb-413d-b4e8-b9ffe0ed3995 | H16: Cited in answer: YES
A17: 4 | B17: 62011TJ0289.md | C17: Court Decision | D17: EU | E17: 7ecb1eda-828c-4ed1-831c-9ba3cd309425
A18: 5 | B18: 131688-30-inspections-the-general-court-of-the-european-union-upholds-the-european-comm.md | C18: Bulletin article | E18: 7de191c9-0221-423b-b670-ef1e047a0196
A19: 6 | B19: 128250-35-dawn-raids-the-general-court-of-the-european-union-partially-upholds-the-lega.md | C19: Bulletin article | E19: e34c0e6d-2771-4073-8165-4a73eff42d4c
A20: 7 | B20: eu-antitrust-enforcement--10_ix_the_compatibility_with_fundamental_rights_of_the_eu_antitrust_enforcement_system_in_which_the_european_commission_acts_both_as_investigator_and_as_first_instance_decision_maker.md | C20: Article (Review) | E20: 2c996db6-dd0f-46f5-be34-12be8f73b817
A21: 8 | B21: 97110-2850-inspection-the-general-court-of-the-european-union-partially-annuls-decisio.md | C21: Bulletin article | E21: 0ff86075-a215-4bce-ac53-21a9aa21cd71
A22: 9 | B22: 125471-20-dawn-raids-the-general-court-upholds-the-european-commissions-overall-assessm.md | C22: Bulletin article | E22: e97ed81a-60ca-4112-9207-21a8613078bd
A23: 10 | B23: 93706-0060-dawn-raids-advocate-general-kokott-calls-on-the-court-of-justice-to-uphold.md | C23: Bulletin article | E23: 42a1613c-b25b-476e-a3b4-e1cac9b5add2
A24: 11 | B24: 57935-361-decisions-adopted-during-an-inspection-the-general-court-reminds-the-commiss.md | C24: Bulletin article | E24: 882aa354-e6cf-464a-b1e2-9486b1cca48f | H24: Cited in answer: YES
A25: 12 | B25: 91835.md | C25: Article (Review) | E25: f6ec0179-d152-4059-9a3f-81d669d422b0
A26: 13 | B26: competition-case-law-digest-5th--p11.md | C26: Book (Livre) | E26: 40351206-cbf5-40d8-a127-173a24162f6e
A27: 14 | B27: 95849-3360-inspections-the-court-of-justice-of-the-european-union-gives-the-commission.md | C27: Bulletin article | E27: afe07022-9e8e-4270-a8d4-2c0aaa70652f
A28: 15 | B28: 127929-the-eu-general-court-upholds-the-commissions-inspection-methodology-based-on-pub.md | C28: Bulletin article | E28: af2e8c94-00c3-40d4-8e35-233542ca536d
A29: 16 | B29: judicial-review-competition-cases--6_european_union_-_judicial_review_of_inspection_decisions.md | C29: Article (Review) | E29: 21a3ec2e-1c42-4307-ab97-e45011d6660a
A30: 17 | B30: 81215.md | C30: Article (Review) | E30: 1326c749-4c6d-42ec-974e-b228dd1bf722
A31: 18 | B31: 105103.md | C31: Bulletin article | E31: f10e4cc4-d036-4949-b9be-86b79b54fa7d
A32: 19 | B32: 103260-35-necessary-limits-to-the-commission-s-inspection-powers.md | C32: Article (Review) | E32: bef18b4b-bb03-49c0-a7aa-afed485ec5d2
A33: 20 | B33: 127186-20-inspection-the-general-court-of-the-european-union-considers-that-the-commiss.md | C33: Bulletin article | E33: 329bd68b-1104-4f5c-b636-e9925175dbc6
A34: 21 | B34: 62013CC0037.md | C34: Bulletin article | D34: EU | E34: 632273f6-990f-4cc6-85ff-77f86f45c537
A35: 22 | B35: 62018CJ0403.md | C35: Court Decision | D35: EU | E35: 5b155c4b-0345-4afa-8dee-d56351895c8f
A36: 23 | B36: 62018CC0606.md | C36: Article (Review) | D36: EU | E36: 0655b4ec-4821-4b46-91b6-b6ddaebd8d5d
A37: 24 | B37: 92103.md | C37: Article (Review) | E37: f12761a7-4a04-47fb-aa09-a2155912c60c
A38: 25 | B38: 62017TJ0249.md | C38: Court Decision | D38: EU | E38: dbf7bda8-39fa-4eb5-a6e2-f02b0787cb54
A39: 26 | B39: 96586.md | C39: Article (Review) | E39: 4cb5c154-4d3a-46c3-8bca-8f09c7e6c562
A40: 27 | B40: 79963.md | C40: Article (Review) | E40: b0c5f913-948d-4dcc-9ea4-98f6136ca5a7 | H40: Cited in answer: YES
A41: 28 | B41: eu-antitrust-enforcement--12_xi_the_role_of_the_hearing_officer_in_antitrust_proceedings_before_the_european_commission.md | C41: Book (Livre) | E41: 27d55d8c-5b59-43c1-8576-7a718bd009d4
A42: 29 | B42: 62013CJ0583.md | C42: Court Decision | D42: EU | E42: 7b8f60ed-1acc-484e-b298-5a745b6b18f3 | H42: Cited in answer: YES
A43: 30 | B43: 97568-3340-investigation-the-court-of-justice-of-the-european-union-recognizes-the-eur.md | C43: Bulletin article | E43: 0a9a6620-916c-4d26-8e97-e91a08871183
A44: 31 | B44: judicial-review-competition-cases--7_european_union_-_are_there_any_limits_to_unlimited_jurisdiction_judicial_review_of_commission_discretion_in_setting_fines_for_breaches_of_eu_competition_rules.md | C44: Article (Review) | E44: db161723-dcab-4880-a411-5ede0c406c3a
A45: 32 | B45: eu-antitrust-enforcement--15_xiv_procedural_rights_and_obligations_of_third_parties_in_antitrust_investigations_and_proceedings_by_the_european_commission.md | C45: Book (Livre) | E45: b2429dd2-ef75-4f34-8bf2-95b08c3a4de5
A46: 33 | B46: competition-case-law-digest-5th--p09.md | C46: Book (Livre) | E46: 2f0afdb0-43c8-41b3-99e2-c3003ab906c1
A47: 34 | B47: AT.38823-DEC_F66ED65C-2649-42E8-A2B2-0540E4650925_-ATT1340.md | C47: Regulatory Decision | D47: EU | E47: 7dce14d9-8a1f-49fd-84f4-e04e86fb3760
A48: 35 | B48: 62012CJ0365.md | C48: Court Decision | D48: EU | E48: 26887c6b-0bac-4894-86e5-157231b4f370
A49: 36 | B49: 96910-3420-dawn-raids-the-court-of-justice-of-the-european-union-confirms-the-power-of.md | C49: Bulletin article | E49: a95ca40b-ceae-4436-8de6-a7a126b177e3
A50: 37 | B50: 62018CJ0606.md | C50: Court Decision | D50: EU | E50: 2d074327-045b-484e-8bbc-1a0f9c7ed660
A51: 38 | B51: eu-antitrust-enforcement--13_xii_the_oral_hearing_in_antitrust_proceedings_before_the_european_commission.md | C51: Article (Review) | E51: 8edbd753-7757-4163-9662-1b5feeeadeb4
A52: 39 | B52: 96291-the-eu-court-of-justice-upholds-the-commissions-right-to-continue-inspection-at.md | C52: Bulletin article | E52: b5945681-864a-4470-b1bb-33978a2016ed
A53: 40 | B53: 62020CC0682.md | C53: Article (Review) | D53: EU | E53: f6fc977b-8c8d-467b-a5f7-04beb77f1b93
A54: 41 | B54: 62020CJ0682.md | C54: Court Decision | D54: EU | E54: 408cfe67-7fe4-45a8-9c3e-de39d86d56cb
A55: 42 | B55: 62013TJ0402.md | C55: Court Decision | D55: EU | E55: d193f5d4-ad74-4d17-8105-30b02e493c35
A56: 43 | B56: eu-antitrust-enforcement--2_i_regulation_1_2003_an_assessment_after_twenty_years.md | C56: Article (Review) | E56: 55871bec-fbf6-4f9f-9931-66f8481120f2
A57: 44 | B57: 93368-2520-investigations-the-court-of-justice-of-the-european-union-rules-that-an-act.md | C57: Bulletin article | E57: eb4af447-a8d7-4102-8c9b-20f8865d5fea
A58: 45 | B58: 94920-2150-inquiries-the-court-of-justice-of-the-european-union-dismisses-appeals-brou.md | C58: Bulletin article | E58: e7e462f6-8d3e-4f46-92a9-57edcae44fd8
A59: 46 | B59: 62018CJ0601.md | C59: Court Decision | D59: EU | E59: d94571df-d56d-45c1-a02e-834714984963
A60: 47 | B60: 62016CJ0123.md | C60: Court Decision | D60: EU | E60: 22252c77-2086-4d9e-94b7-b7219394e299
A61: 48 | B61: 62014CJ0413.md | C61: Court Decision | D61: EU | E61: 72ccc95a-3fea-4dbb-b7f6-3d6b4b3fd958
A62: 49 | B62: 123082.md | C62: Bulletin article | E62: 18ab192b-10fe-48eb-95a5-bfcc61cd2c9d
A63: 50 | B63: 62020TJ0312.md | C63: Court Decision | D63: EU | E63: 30e60d1c-01b4-48f2-927c-8817ef32a545
A64: 51 | B64: 62019CJ0697.md | C64: Court Decision | D64: EU | E64: 78e44658-9979-4418-94c6-4c9429b2b966
A65: 52 | B65: 62015CO0523.md | C65: Court Decision | D65: EU | E65: b66f8514-c7d7-4322-9e3d-b85b2b24d658
A66: 53 | B66: 62016CJ0611.md | C66: Court Decision | D66: EU | E66: 3db04834-4025-49ed-ae15-42e6d03d00b0
A67: 54 | B67: 62020CC0690.md | C67: Bulletin article | D67: EU | E67: 349cac6b-c1bd-4e7c-a092-8bef2db77ad2
A68: 55 | B68: 62014CJ0033.md | C68: Court Decision | D68: EU | E68: 416f824d-8129-498b-86b2-330a30a0f664
A69: 56 | B69: 62020CC0376.md | C69: Court Decision | D69: EU | E69: cebd4962-06e0-43a6-ac13-b9cc9b05c9e7
A70: 57 | B70: 62016TJ0640(01).md | C70: Court Decision | D70: EU | E70: 1880a767-4e18-44da-ae27-47011320e498
A71: 58 | B71: 62015TJ0274.md | C71: Court Decision | D71: EU | E71: d42f923b-c267-4df9-acb3-5abda361a0d6
A72: 59 | B72: competition-inspections-25-jurisdictions--7_european_union.md | C72: Article (Review) | E72: 1c2fa592-34f0-4656-96c2-024c5ea88b1e
A73: 60 | B73: 62014TJ0639(01).md | C73: Court Decision | D73: EU | E73: cf1d6ba5-9892-4d66-a0d2-60e0ebf5e920
A74: 61 | B74: 62019CJ0563.md | C74: Court Decision | D74: EU | E74: e913f312-653c-49c1-b77a-4a633a3b4bfc
A75: 62 | B75: 62015CJ0088.md | C75: Court Decision | D75: EU | E75: 80f4c149-8f30-416e-b690-ada942e3745a
A76: 63 | B76: 62023TJ0263.md | C76: Court Decision | D76: EU | E76: 16791fea-a958-4950-92a6-5a1b65fb3a04
A77: 64 | B77: 62013CJ0037.md | C77: Court Decision | D77: EU | E77: 2426e61d-f1e3-4fe6-a1e7-1b0d6d4deb24
A78: 65 | B78: 62019CJ0699.md | C78: Court Decision | D78: EU | E78: 75b09e77-929c-4a7a-b100-8fd1f054e367
A79: 66 | B79: 62016CJ0586.md | C79: Court Decision | D79: EU | E79: e5c9a320-8674-4436-ab55-a45fb5d4fd8b
A80: 67 | B80: eu-antitrust-enforcement--16_xv_publication_of_antitrust_decisions_of_the_european_commission.md | C80: Book (Livre) | E80: 3c9799ff-7e91-4daf-9fef-671444f16757
A81: 68 | B81: eu-antitrust-enforcement--17_xvi_re_adoption_by_the_european_commission_of_cartel_decisions_annulled_on_procedural_grounds_by_the_eu_courts.md | C81: Article (Review) | E81: 71ba5e7f-b51e-4068-b010-b7e7f422add9
A82: 69 | B82: 131258-the-eu-general-court-dismisses-an-action-challenging-commission-s-inspection-pow.md | C82: Bulletin article | E82: b5e40090-4f79-422a-997e-8eaa7a359c88
A83: 70 | B83: 62019CJ0698.md | C83: Court Decision | D83: EU | E83: ad8e8c6c-9d66-45d9-bc05-6962f20d0bf7
A84: 71 | B84: 62018CJ0312.md | C84: Court Decision | D84: EU | E84: 08dfceb2-3d7f-4ffa-9cfb-5b557d7cae14
A85: 72 | B85: 62014CC0033.md | C85: Bulletin article | D85: EU | E85: 1dfad74b-fd57-47bb-bfab-18e86ff8d695
A86: 73 | B86: 62017CJ0114.md | C86: Court Decision | D86: EU | E86: 3a7152cd-6afa-4e4f-8c45-eaaf4bc248a6
A87: 74 | B87: 62016CJ0128.md | C87: Court Decision | D87: EU | E87: 59490de3-8af2-4a5c-aa9b-14f059c7301f
A88: 75 | B88: 62024CO0089(01).md | C88: Court Decision | D88: EU | E88: c937b817-5c56-4e36-8458-4a937aa0c4a4
A89: 76 | B89: 62016CJ0579.md | C89: Court Decision | D89: EU | E89: eaf6f2fd-63a3-4636-b157-ce4c8e58127e
A90: 77 | B90: 62014CC0268.md | C90: Bulletin article | D90: EU | E90: 70d6a636-85b1-4767-8035-ab01f7ceae06
A91: 78 | B91: 62014CC0267.md | C91: Bulletin article | D91: EU | E91: 4e120783-7054-40f4-9568-0136a08681b0
A92: 79 | B92: 62019CJ0638.md | C92: Court Decision | D92: EU | E92: 39fe21f4-d9f9-46ee-8007-6acb00688f30
A93: 80 | B93: 62020CJ0690.md | C93: Court Decision | D93: EU | E93: 75c2da13-00ee-43b2-baa4-a6f2e5a71e73
A94: 81 | B94: 62020CJ0693.md | C94: Court Decision | D94: EU | E94: 74ccf3f4-5d27-4c74-9208-62829cc5bcf1
... A100: 87 | B100: 62023CC0070.md | C100: Bulletin article | D100: EU | E100: 2a493229-62c6-48e3-be4c-c06477e996fc
A101: 88 | B101: 129745.md | C101: Bulletin article | E101: d77ab0a2-b289-4ca9-981f-ff910bb4451b
A102: 89 | B102: 123380-the-eu-court-of-justice-issues-2-judgments-defining-the-scope-of-the-commission.md | C102: Bulletin article | E102: ae379537-4ebe-4c1e-a2a4-dd2a0f8af464 | H102: Cited in answer: YES
A103: 90 | B103: 62019CC0883.md | C103: Court Decision | D103: EU | E103: d0b07834-6630-4196-a01e-66dbde751361
A104: 91 | B104: 62014TJ0827.md | C104: Court Decision | D104: EU | E104: 14ea7734-2bf8-475d-9a43-08b64218d89f
A105: 92 | B105: 62015CJ0086.md | C105: Court Decision | D105: EU | E105: ff68b6da-b4b5-43cc-ac9a-d1c8ef082f67
...

Sheet Q42
A1: Q42 — Expert Review
A2: Question metadata
A3: Question ID | B3: 42
A4: Topic | B4: Dawn raids — evidence found by accident
A5: Scope | B5: EU
A6: Original reviewer | B6: Carolina
A7: Original status | B7: Approved
A8: Question | B8: Can the Commission inspect a company over conduct a national authority has already investigated? What limits apply, and how have the courts treated the overlap?
A9: Generated answer
A10: Paste the generated answer here.
A11: Run ID | C11: Run date
A12: Retrieval set review
A13: Rank | B13: Document name | C13: Document class | D13: Jurisdiction | E13: URL / Document ID | F13: Required source? | G13: Expert verdict | H13: Notes
A14: 1
A15: 2
A16: 3
A17: 4
A18: 5
A19: 6
A20: 7
A21: 8
A22: 9
A24: Claim-by-claim review
A25: Claim ID | B25: Claim from answer | C25: Cited document | D25: Expert verdict | E25: Cited passage | F25: Required fix / comment
A26: 1
A27: 2
A28: 3
A29: 4
A30: 5
A31: 6
A32: 7
A33: 8
A34: 9
A36: Final expert verdict
A37: Reviewer
A38: Is the answer acceptable?
A39: Overall comment / required fixes
A40: Review completed?
A69: Original source notes
A70: WAB notes
A71: Reviewer notes from question approval | B71: agreed, let's keep the question.

Sheet Q43
A1: Q43 — Expert Review
A2: Question metadata
A3: Question ID | B3: 43
A4: Topic | B4: Dawn raids — premises and the courts
A5: Scope | B5: EU
A6: Original reviewer | B6: Carolina
A7: Original status | B7: Approved
A8: Question | B8: How is the inviolability of business premises reconciled with the Commission's inspection powers under Article 20 of Regulation 1/2003 — in particular, when is prior judicial authorisation required, and what may the national court asked to authorise coercive assistance review under Article 20(8)?
A9: Generated answer
A10: Paste the generated answer here.
A11: Run ID | C11: Run date
A12: Retrieval set review
A13: Rank | B13: Document name | C13: Document class | D13: Jurisdiction | E13: URL / Document ID | F13: Required source? | G13: Expert verdict | H13: Notes
A14: 1
A15: 2
A16: 3
A17: 4
A18: 5
A19: 6
A20: 7
A21: 8
A22: 9
A24: Claim-by-claim review
A25: Claim ID | B25: Claim from answer | C25: Cited document | D25: Expert verdict | E25: Cited passage | F25: Required fix / comment
A26: 1
A27: 2
A28: 3
A29: 4
A30: 5
A31: 6
A32: 7
A33: 8
A34: 9
A36: Final expert verdict
A37: Reviewer
A38: Is the answer acceptable?
A39: Overall comment / required fixes
A40: Review completed?
A69: Original source notes
A70: WAB notes | B70: Article 21 of Regulation 1/2003 covers inspections of homes and other non-business premises, where prior authorisation by a national court is always required. We have folded that into this question — tell us if it deserves its own.
A71: Reviewer notes from question approval | B71: agreed on the substance but let's frame it this way "How is the inviolability of business premises reconciled with the Commission's inspection powers under Article 20 of Regulation 1/2003 — in particular, when is prior judicial authorisation required, and what may the national court asked to authorise coercive assistance review under Article 20(8)?"

Sheet Q44
A1: Q44 — Expert Review
A2: Question metadata
A3: Question ID | B3: 44
A4: Topic | B4: Dawn raids — premises and the courts
A5: Scope | B5: EU
A6: Original reviewer | B6: Carolina
A7: Original status | B7: Approved
A8: Question | B8: In light of the recent case law of the Court of Justice, may a national competition authority seize an undertaking's business emails without prior judicial authorisation, and does full ex post review adequately protect the right to respect for communications under Article 7 of the Charter?
A9: Generated answer
A10: Paste the generated answer here.
A11: Run ID | C11: Run date
A12: Retrieval set review
A13: Rank | B13: Document name | C13: Document class | D13: Jurisdiction | E13: URL / Document ID | F13: Required source? | G13: Expert verdict | H13: Notes
A14: 1
A15: 2
A16: 3
A17: 4
A18: 5
A19: 6
A20: 7
A21: 8
A22: 9
A24: Claim-by-claim review
A25: Claim ID | B25: Claim from answer | C25: Cited document | D25: Expert verdict | E25: Cited passage | F25: Required fix / comment
A26: 1
A27: 2
A28: 3
A29: 4
A30: 5
A31: 6
A32: 7
A33: 8
A34: 9
A36: Final expert verdict
A37: Reviewer
A38: Is the answer acceptable?
A39: Overall comment / required fixes
A40: Review completed?
A69: Original source notes
A70: WAB notes
A71: Reviewer notes from question approval | B71: agreed on substance but let's frame it like this: "In light of the recent case law of the Court of Justice, may a national competition authority seize an undertaking's business emails without prior judicial authorisation, and does full ex post review adequately protect the right to respect for communications under Article 7 of the Charter?"

Sheet Q45
A1: Q45 — Expert Review
A2: Question metadata
A3: Question ID | B3: 45
A4: Topic | B4: Dawn raids — premises and the courts
A5: Scope | B5: France
A6: Original reviewer | B6: Jeanne
A7: Original status | B7: Approved
A8: Question | B8: When must a French dawn raid be authorised in advance by the juge des libertés et de la détention , and what does that judge control before, during, and after the operation?
A9: Generated answer
A10: Paste the generated answer here.
A11: Run ID | C11: Run date
A12: Retrieval set review
A13: Rank | B13: Document name | C13: Document class | D13: Jurisdiction | E13: URL / Document ID | F13: Required source? | G13: Expert verdict | H13: Notes
A14: 1
A15: 2
A16: 3
A17: 4
A18: 5
A19: 6
A20: 7
A21: 8
A22: 9
A24: Claim-by-claim review
A25: Claim ID | B25: Claim from answer | C25: Cited document | D25: Expert verdict | E25: Cited passage | F25: Required fix / comment
A26: 1
A27: 2
A28: 3
A29: 4
A30: 5
A31: 6
A32: 7
A33: 8
A34: 9
A36: Final expert verdict
A37: Reviewer
A38: Is the answer acceptable?
A39: Overall comment / required fixes
A40: Review completed?
A69: Original source notes
A70: WAB notes | B70: Possible overlap with question 33.
A71: Reviewer notes from question approval | B71: no overlap with question 33, we can keep the question.

Sheet Q46
A1: Q46 — Expert Review
A2: Question metadata
A3: Question ID | B3: 46
A4: Topic | B4: Dawn raids — premises and the courts
A5: Scope | B5: US
A6: Original reviewer | B6: Arthur
A7: Original status | B7: Approved
A8: Question | B8: What must the Department of Justice establish to obtain and execute a search warrant in a criminal antitrust investigation, and what limits apply to the search? How do criminal search warrants differ from grand-jury subpoenas in criminal investigations and from subpoenas or Civil Investigative Demands (CIDs) used in civil antitrust investigations?
A9: Generated answer
A10: Paste the generated answer here.
A11: Run ID | C11: Run date
A12: Retrieval set review
A13: Rank | B13: Document name | C13: Document class | D13: Jurisdiction | E13: URL / Document ID | F13: Required source? | G13: Expert verdict | H13: Notes
A14: 1
A15: 2
A16: 3
A17: 4
A18: 5
A19: 6
A20: 7
A21: 8
A22: 9
A24: Claim-by-claim review
A25: Claim ID | B25: Claim from answer | C25: Cited document | D25: Expert verdict | E25: Cited passage | F25: Required fix / comment
A26: 1
A27: 2
A28: 3
A29: 4
A30: 5
A31: 6
A32: 7
A33: 8
A34: 9
A36: Final expert verdict
A37: Reviewer
A38: Is the answer acceptable?
A39: Overall comment / required fixes
A40: Review completed?

Sheet Q47
A1: Q47 — Expert Review
A2: Question metadata
A3: Question ID | B3: 47
A4: Topic | B4: Dawn raids — personal data
A5: Scope | B5: EU
A6: Original reviewer | B6: Carolina
A7: Original status | B7: Approved
A8: Question | B8: To what extent may the Commission inspect private correspondence, personal devices and employees’ personal data during a dawn raid, and does the sealed-envelope procedure extend beyond legally privileged material?
A9: Generated answer
A10: Paste the generated answer here.
A11: Run ID | C11: Run date
A12: Retrieval set review
A13: Rank | B13: Document name | C13: Document class | D13: Jurisdiction | E13: URL / Document ID | F13: Required source? | G13: Expert verdict | H13: Notes
A14: 1
A15: 2
A16: 3
A17: 4
A18: 5
A19: 6
A20: 7
A21: 8
A22: 9
A24: Claim-by-claim review
A25: Claim ID | B25: Claim from answer | C25: Cited document | D25: Expert verdict | E25: Cited passage | F25: Required fix / comment
A26: 1
A27: 2
A28: 3
A29: 4
A30: 5
A31: 6
A32: 7
A33: 8
A34: 9
A36: Final expert verdict
A37: Reviewer
A38: Is the answer acceptable?
A39: Overall comment / required fixes
A40: Review completed?
A69: Original source notes
A70: WAB notes | B70: Wider version of question 16, added following Carolina’s request to keep both.
A71: Reviewer notes from question approval | B71: agreed.

Sheet Q48
A1: Q48 — Expert Review
A2: Question metadata
A3: Question ID | B3: 48
A4: Topic | B4: Dawn raids — legal professional privilege
A5: Scope | B5: France
A6: Original reviewer | B6: Carolina
A7: Original status | B7: Approved
A8: Question | B8: Under French law, to what extent are communications between a company and its lawyers protected during a competition dawn raid, how can the company challenge the seizure of allegedly privileged material, and what remedies are available if privileged documents have been seized (including return, destruction, or exclusion from the investigation)?
A9: Generated answer
A10: Paste the generated answer here.
A11: Run ID | C11: Run date
A12: Retrieval set review
A13: Rank | B13: Document name | C13: Document class | D13: Jurisdiction | E13: URL / Document ID | F13: Required source? | G13: Expert verdict | H13: Notes
A14: 1
A15: 2
A16: 3
A17: 4
A18: 5
A19: 6
A20: 7
A21: 8
A22: 9
A24: Claim-by-claim review
A25: Claim ID | B25: Claim from answer | C25: Cited document | D25: Expert verdict | E25: Cited passage | F25: Required fix / comment
A26: 1
A27: 2
A28: 3
A29: 4
A30: 5
A31: 6
A32: 7
A33: 8
A34: 9
A36: Final expert verdict
A37: Reviewer
A38: Is the answer acceptable?
A39: Overall comment / required fixes
A40: Review completed?
A69: Original source notes
A70: WAB notes | B70: Wider French version added following Carolina’s request to keep both. It complements question 12.
A71: Reviewer notes from question approval | B71: agreed.

Sheet Q49
A1: Q49 — Expert Review
A2: Question metadata
A3: Question ID | B3: 49
A4: Topic | B4: Dawn raids — grounds for an inspection
A5: Scope | B5: EU
A6: Original reviewer | B6: Carolina
A7: Original status | B7: Approved
A8: Question | B8: What evidentiary threshold must the European Commission meet to justify a dawn raid, including the requirement for “sufficiently serious indicia”?
A9: Generated answer
A10: Paste the generated answer here.
A11: Run ID | C11: Run date
A12: Retrieval set review
A13: Rank | B13: Document name | C13: Document class | D13: Jurisdiction | E13: URL / Document ID | F13: Required source? | G13: Expert verdict | H13: Notes
A14: 1 | B14: 62011TJ0289.md | C14: Court Decision | D14: EU | E14: 7ecb1eda-828c-4ed1-831c-9ba3cd309425
A15: 2 | B15: inspections-eu-law-2nd--3_chapter_1_-_inspections_upon_decision_regulation_1_2003_article_20_4.md | C15: Book (Livre) | E15: d28b1d20-a2c6-425f-a401-498eab28d744 | H15: Cited in answer: YES
A16: 3 | B16: 62016TJ0325.md | C16: Court Decision | D16: EU | E16: b7c29457-b49b-44b3-a09c-8c0dfd4574fa
A17: 4 | B17: 62020CC0682.md | C17: Article (Review) | D17: EU | E17: f6fc977b-8c8d-467b-a5f7-04beb77f1b93
A18: 5 | B18: 62013CC0583.md | C18: Bulletin article | D18: EU | E18: 778d749c-48cb-405c-a58f-962dd3ceef0c
A19: 6 | B19: judicial-review-competition-cases--6_european_union_-_judicial_review_of_inspection_decisions.md | C19: Article (Review) | E19: 21a3ec2e-1c42-4307-ab97-e45011d6660a
A20: 7 | B20: 62017TJ0249.md | C20: Court Decision | D20: EU | E20: dbf7bda8-39fa-4eb5-a6e2-f02b0787cb54
A21: 8 | B21: 96586.md | C21: Article (Review) | E21: 4cb5c154-4d3a-46c3-8bca-8f09c7e6c562
A22: 9 | B22: 50285.md | C22: Bulletin article | E22: f17418b6-489e-4049-92f0-b9ce2b58968f
A23: 10 | B23: 62014TJ0475.md | C23: Court Decision | D23: EU | E23: cba40d0a-c143-4bc9-af97-af13ef20db3a
A24: 11 | B24: 62023TJ0263.md | C24: Court Decision | D24: EU | E24: 16791fea-a958-4950-92a6-5a1b65fb3a04 | H24: Cited in answer: YES
A25: 12 | B25: 62014TJ0449.md | C25: Court Decision | D25: EU | E25: 2f594756-bc0a-4332-829f-e65319b3211c
A26: 13 | B26: 103260-35-necessary-limits-to-the-commission-s-inspection-powers.md | C26: Article (Review) | E26: bef18b4b-bb03-49c0-a7aa-afed485ec5d2
A27: 14 | B27: 62009TJ0135.md | C27: Court Decision | D27: EU | E27: 10418f10-8b6f-4bcc-adf6-39e168b49440
A28: 15 | B28: eu-antitrust-enforcement--10_ix_the_compatibility_with_fundamental_rights_of_the_eu_antitrust_enforcement_system_in_which_the_european_commission_acts_both_as_investigator_and_as_first_instance_decision_maker.md | C28: Article (Review) | E28: 2c996db6-dd0f-46f5-be34-12be8f73b817
A29: 16 | B29: 62018CC0606.md | C29: Article (Review) | D29: EU | E29: 0655b4ec-4821-4b46-91b6-b6ddaebd8d5d
A30: 17 | B30: 62014CC0247.md | C30: Article (Review) | D30: EU | E30: 9fefd6d8-a7ab-424b-a847-9a604ddaaf0f
A31: 18 | B31: 62020CJ0682.md | C31: Court Decision | D31: EU | E31: 408cfe67-7fe4-45a8-9c3e-de39d86d56cb
A32: 19 | B32: 62013CC0037.md | C32: Bulletin article | D32: EU | E32: 632273f6-990f-4cc6-85ff-77f86f45c537
A33: 20 | B33: 62020CJ0693.md | C33: Court Decision | D33: EU | E33: 74ccf3f4-5d27-4c74-9208-62829cc5bcf1
A34: 21 | B34: 62020CC0690.md | C34: Bulletin article | D34: EU | E34: 349cac6b-c1bd-4e7c-a092-8bef2db77ad2
A35: 22 | B35: competition-case-law-digest-5th--p09.md | C35: Book (Livre) | E35: 2f0afdb0-43c8-41b3-99e2-c3003ab906c1
A36: 23 | B36: 81215.md | C36: Article (Review) | E36: 1326c749-4c6d-42ec-974e-b228dd1bf722
A37: 24 | B37: 62020CJ0690.md | C37: Court Decision | D37: EU | E37: 75c2da13-00ee-43b2-baa4-a6f2e5a71e73
A38: 25 | B38: 62018CJ0606.md | C38: Court Decision | D38: EU | E38: 2d074327-045b-484e-8bbc-1a0f9c7ed660
A39: 26 | B39: 62009TJ0521.md | C39: Court Decision | D39: EU | E39: a9632e6f-3217-4f96-abc5-8577a99e80fb
A40: 27 | B40: eu-antitrust-enforcement--15_xiv_procedural_rights_and_obligations_of_third_parties_in_antitrust_investigations_and_proceedings_by_the_european_commission.md | C40: Book (Livre) | E40: b2429dd2-ef75-4f34-8bf2-95b08c3a4de5
A41: 28 | B41: 62004TJ0340.md | C41: Court Decision | D41: EU | E41: d9fb7f73-952b-4b71-a502-6f63b7f95073
A42: 29 | B42: 79963.md | C42: Article (Review) | E42: b0c5f913-948d-4dcc-9ea4-98f6136ca5a7
A43: 30 | B43: eu-antitrust-enforcement--12_xi_the_role_of_the_hearing_officer_in_antitrust_proceedings_before_the_european_commission.md | C43: Book (Livre) | E43: 27d55d8c-5b59-43c1-8576-7a718bd009d4
A44: 31 | B44: 62013CJ0583.md | C44: Court Decision | D44: EU | E44: 7b8f60ed-1acc-484e-b298-5a745b6b18f3
A45: 32 | B45: 62013TJ0402.md | C45: Court Decision | D45: EU | E45: d193f5d4-ad74-4d17-8105-30b02e493c35
A46: 33 | B46: competition-case-law-digest-5th--p10.md | C46: Book (Livre) | E46: 65e060cb-bdeb-413d-b4e8-b9ffe0ed3995
A47: 34 | B47: judicial-review-competition-cases--7_european_union_-_are_there_any_limits_to_unlimited_jurisdiction_judicial_review_of_commission_discretion_in_setting_fines_for_breaches_of_eu_competition_rules.md | C47: Article (Review) | E47: db161723-dcab-4880-a411-5ede0c406c3a
A48: 35 | B48: eu-antitrust-enforcement--11_x_fundamental_procedural_rights_and_effective_enforcement_of_articles_101_and_102_tfeu_in_the_european_competition_network.md | C48: Book (Livre) | E48: 44d971b2-9615-45f5-94c3-342633964481
A49: 36 | B49: 57935-361-decisions-adopted-during-an-inspection-the-general-court-reminds-the-commiss.md | C49: Bulletin article | E49: 882aa354-e6cf-464a-b1e2-9486b1cca48f
A50: 37 | B50: 62020TO0451(01).md | C50: Court Decision | D50: EU | E50: b261ed51-2a85-4d85-a20a-92143a7cd6a5
A51: 38 | B51: 62014CC0267.md | C51: Bulletin article | D51: EU | E51: 4e120783-7054-40f4-9568-0136a08681b0
A52: 39 | B52: 91835.md | C52: Article (Review) | E52: f6ec0179-d152-4059-9a3f-81d669d422b0
A53: 40 | B53: 62023TJ0306.md | C53: Court Decision | D53: EU | E53: 9618c09b-f7de-44f3-84b6-43e0a65b9002
A54: 41 | B54: 62020TO0452(01).md | C54: Court Decision | D54: EU | E54: 2768689e-df78-453e-8a77-732820fda1c8
A55: 42 | B55: 62009TJ0023.md | C55: Court Decision | D55: EU | E55: 094ea41b-a505-436b-a0dd-4ba40b31dfdd
A56: 43 | B56: 62014CC0268.md | C56: Bulletin article | D56: EU | E56: 70d6a636-85b1-4767-8035-ab01f7ceae06
A57: 44 | B57: 62020CC0682.md | C57: Bulletin article | D57: EU | E57: 4228e89d-bc15-4a00-9ed7-bd703f8ec05a
A58: 45 | B58: 49706.md | C58: Bulletin article | E58: 69e18734-70c1-4002-916f-4aed9d0e9352
A59: 46 | B59: 62018CJ0601.md | C59: Court Decision | D59: EU | E59: d94571df-d56d-45c1-a02e-834714984963
A60: 47 | B60: 62014CC0248.md | C60: Bulletin article | D60: EU | E60: 339a87b5-3e47-45f8-9184-ec4d2919899c
A61: 48 | B61: 62018CJ0403.md | C61: Court Decision | D61: EU | E61: 5b155c4b-0345-4afa-8dee-d56351895c8f
A62: 49 | B62: 49705.md | C62: Bulletin article | E62: a81d247a-6baa-4e69-8435-23b0a663e83f
A63: 50 | B63: 62018CJ0538.md | C63: Court Decision | D63: EU | E63: aeddddae-2bb4-43b2-812c-37431b53023f
A64: 51 | B64: competition-inspections-25-jurisdictions--7_european_union.md | C64: Article (Review) | E64: 1c2fa592-34f0-4656-96c2-024c5ea88b1e
A65: 52 | B65: 95849-3360-inspections-the-court-of-justice-of-the-european-union-gives-the-commission.md | C65: Bulletin article | E65: afe07022-9e8e-4270-a8d4-2c0aaa70652f
A66: 53 | B66: 105103.md | C66: Bulletin article | E66: f10e4cc4-d036-4949-b9be-86b79b54fa7d
A67: 54 | B67: 62013CJ0037.md | C67: Court Decision | D67: EU | E67: 2426e61d-f1e3-4fe6-a1e7-1b0d6d4deb24
A68: 55 | B68: 97568-3340-investigation-the-court-of-justice-of-the-european-union-recognizes-the-eur.md | C68: Bulletin article | E68: 0a9a6620-916c-4d26-8e97-e91a08871183
A69: 56 | B69: 62011TJ0296.md | C69: Court Decision | D69: EU | E69: 9bd983cd-32e8-43eb-bad0-dc190b31c9d2
A70: 57 | B70: 123082.md | C70: Bulletin article | E70: 18ab192b-10fe-48eb-95a5-bfcc61cd2c9d
A71: 58 | B71: 103227-30-des-limites-necessaires-aux-pouvoirs-dinspection-de-la-commission.md | C71: Article (Review) | E71: 315845a8-75c2-4d8f-88bd-d0486da25720 | H71: Cited in answer: YES
A72: 59 | B72: 129262.md | C72: Bulletin article | E72: 34a94fc2-9bfb-4101-8ad0-221a66364bdf
A73: 60 | B73: 62011TJ0655.md | C73: Court Decision | D73: EU | E73: 9bbae35a-5d48-465b-8d08-793e521ab06a
A74: 61 | B74: 62014TJ0441.md | C74: Court Decision | D74: EU | E74: 29f8781d-6d42-4188-b0d7-1ff604cf8a33
A75: 62 | B75: competition-case-law-digest-5th--p11.md | C75: Book (Livre) | E75: 40351206-cbf5-40d8-a127-173a24162f6e
A76: 63 | B76: 62023CJ0258.md | C76: Court Decision | D76: EU | E76: 5aa970eb-b95b-47f7-848c-8251ba16e8bc
A77: 64 | B77: 90706.md | C77: Article (Review) | E77: 53fd7b9e-f939-427f-a193-dde8d89572a2
A78: 65 | B78: 62012TJ0272.md | C78: Court Decision | D78: EU | E78: 5955aed3-ab0f-4414-a06a-9abbbc834dab
A79: 66 | B79: 129745.md | C79: Bulletin article | E79: d77ab0a2-b289-4ca9-981f-ff910bb4451b
A80: 67 | B80: 62014TJ0450.md | C80: Court Decision | D80: EU | E80: 41438462-5717-4e1a-90f5-29e9bd19df4e
A81: 68 | B81: 62014TJ0445.md | C81: Court Decision | D81: EU | E81: f87fc08e-9d0b-4701-9a4c-d68f6d2155c7
A82: 69 | B82: 62014TJ0422.md | C82: Court Decision | D82: EU | E82: 6c23abb3-f168-4c55-89cb-8b100b4c23a5
A83: 70 | B83: 100066.md | C83: Bulletin article | E83: cf5bb273-df83-4359-89b3-f6c951998319
